Workbook
Name Дисциплина: #REF!
Name Дисциплина: #REF!
Name Опыт: #REF!
Name Опыт: #REF!
Name ПДЗ: #REF!
Name ПДЗ: #REF!
Name ПДЗ: #REF!

Sheet РСБУ расчет лимита
F1: ЭКСПРЕСС-ОЦЕНКА КОНТРАГЕНТА
K3: Дата оценки | L3: 46266 | N3: (Голубая ячейка заполняется вручную)
B5: ДАННЫЕ О КОНТРАГЕНТЕ
B7: 1.1 Наименование контрагента: | H7: ООО "КОМПАНИЯ" | N7: (Голубая ячейка заполняется вручную)
B8: 1.2 ИНН контрагента: | H8: 1234567890 | N8: (Голубая ячейка заполняется вручную)
B9: 1.3 Код контрагента в системе учета (при наличии): | N9: (Заполняется вручную)
B10: 1.3 Код основного вида деятельности (ОКВЭД) | H10: 20.41.2 | J10: Категория | K10: =IFERROR(IF(OR(AND(MID($H$10,1,2)*1<=43, MID($H$10,1,2)*1>=41),MID($H$10,1,2)*1=71),"Строительство",IF(OR(MID($H$10,1,2)*1=6,MID($H$10,1,4)="49.5",MID($H$10,1,2)*1=9,MID($H$10,1,4)="19.2"),"Добыча, переработка и транспортировка газа, нефти и нефтепродуктов",IF(OR(MID($H$10,1,2)*1=49,MID($H$10,1,2)*1=53,MID($H$10,1,2)*1=52),"Транспортировка и хранение",IF(OR(AND(MID($H$10,1,2)*1<=47, MID($H$10,1,2)*1>=45)),"Торговля",IF(OR(AND(MID($H$10,1,2)*1<=33, MID($H$10,1,2)*1>=10),MID($H$10,1,2)*1=35,MID($H$10,1,2)*1=5,MID($H$10,1,2)*1=7,MID($H$10,1,2)*1=8),"Производство",IF(OR(MID($H$10,1,2)*1=51),"Авиакомпания",IF(OR(MID($H$10,1,2)*1=50),"Судовладелец",IF(OR(MID($H$10,1,2)*1=62,MID($H$10,1,2)*1=63),"ИТ","Прочие")))))))),"Укажите код ОКВЭД") -> Производство | N10: (Голубая ячейка заполняется вручную)
B11: 1.4 Наличие СТОП-факторов: | H11: Нет | N11: (В голубой ячейке выбрать значение из списка)
B13: ИТОГОВОЕ ЗАКЛЮЧЕНИЕ
H14: =J22 -> 46022 | L14: =L22 -> 45657 | N14: (Автоматический расчет)
B15: ВНУТРЕННИЙ КРЕДИТНЫЙ РЕЙТИНГ | H15: =J61&J60 -> B1 | J15: =J60 -> 1 | M15: =L61&L60 -> B1 | N15: (Автоматический расчет)
B16: СКОРИНГ-БАЛЛ | H16: =ROUND(J58,0)&" "&K58 -> 84 из 100 | J16: =J58 -> 84 | M16: =L58&" "&K58 -> 80 из 100 | N16: (Автоматический расчет)
B17: ="КРЕДИТНЫЙ ЛИМИТ КОНТРАГЕНТА, "&'РСБУ отчетность'!C2&'РСБУ отчетность'!C3 -> КРЕДИТНЫЙ ЛИМИТ КОНТРАГЕНТА, тыс. руб. | H17: =J92 -> 1912919.9 | J17: =H17 -> 1912919.9 | K17: =L86*L88*L90*(1-L91) -> 1580215.5 | L17: =L92 -> 1580215.5 | N17: (Автоматический расчет)
B18: ="ЛИМИТ АВАНСОВОГО ПЛАТЕЖА, "&'РСБУ отчетность'!C2&'РСБУ отчетность'!C3 -> ЛИМИТ АВАНСОВОГО ПЛАТЕЖА, тыс. руб. | H18: =J93 -> 58919.895 | J18: =H18 -> 58919.895 | L18: =L93 -> 40481.007 | N18: (Автоматический расчет)
B20: 1. ФИНАНСОВЫЕ ПОКАЗАТЕЛИ
J22: ='РСБУ отчетность'!E5 -> 46022 | L22: ='РСБУ отчетность'!F5 -> 45657 | N22: (Автоматический расчет)
B23: Наименование показателя | I23: Макс. балл | J23: Значение | K23: Баллы | L23: Значение | M23: Баллы
B24: 1.1 Коэффициент текущей ликвидности | I24: 10 | J24: ='РСБУ отчетность'!E79 -> 3.2836953 | K24: =ROUND(IF(J24="",0,IF($K$10="Строительство",Подложка!G45*I24/100,IF($K$10="Добыча, переработка и транспортировка газа, нефти и нефтепродуктов",Подложка!L45*I24/100,IF($K$10="Транспортировка и хранение",Подложка!Q45*I24/100,IF($K$10="Торговля",Подложка!V45*I24/100,IF($K$10="Производство",Подложка!AA45*I24/100,IF($K$10="Авиакомпания",Подложка!AF45*I24/100,IF($K$10="Судовладелец",Подложка!AK45*I24/100,IF($K$10="Прочие",Подложка!AP45*I24/100,IF($K$10="ИТ",Подложка!AU45*I24/100,0)))))))))),0) -> 10 | L24: ='РСБУ отчетность'!F79 -> 2.9821276 | M24: =IF(L24="",0,IF($K$10="Строительство",Подложка!G55*I24/100,IF($K$10="Добыча, переработка и транспортировка газа, нефти и нефтепродуктов",Подложка!L55*I24/100,IF($K$10="Транспортировка и хранение",Подложка!Q55*I24/100,IF($K$10="Торговля",Подложка!V55*I24/100,IF($K$10="Производство",Подложка!AA55*I24/100,IF($K$10="Авиакомпания",Подложка!AF55*I24/100,IF($K$10="Судовладелец",Подложка!AK55*I24/100,IF($K$10="Прочие",Подложка!AP55*I24/100,IF($K$10="ИТ",Подложка!AU55*I24/100,0)))))))))) -> 10 | N24: (Автоматический расчет)
B25: 1.2 Коэффициент быстрой ликвидности | I25: 5 | J25: ='РСБУ отчетность'!E80 -> 1.7494151 | K25: =ROUND(IF(J25="",0,IF($K$10="Строительство",Подложка!G46*I25/100,IF($K$10="Добыча, переработка и транспортировка газа, нефти и нефтепродуктов",Подложка!L46*I25/100,IF($K$10="Транспортировка и хранение",Подложка!Q46*I25/100,IF($K$10="Торговля",Подложка!V46*I25/100,IF($K$10="Производство",Подложка!AA46*I25/100,IF($K$10="Авиакомпания",Подложка!AF46*I25/100,IF($K$10="Судовладелец",Подложка!AK46*I25/100,IF($K$10="Прочие",Подложка!AP46*I25/100,IF($K$10="ИТ",Подложка!AU46*I25/100,0)))))))))),0) -> 5 | L25: ='РСБУ отчетность'!F80 -> 1.755559 | M25: =IF(L25="",0,IF($K$10="Строительство",Подложка!G56*I25/100,IF($K$10="Добыча, переработка и транспортировка газа, нефти и нефтепродуктов",Подложка!L56*I25/100,IF($K$10="Транспортировка и хранение",Подложка!Q56*I25/100,IF($K$10="Торговля",Подложка!V56*I25/100,IF($K$10="Производство",Подложка!AA56*I25/100,IF($K$10="Авиакомпания",Подложка!AF56*I25/100,IF($K$10="Судовладелец",Подложка!AK56*I25/100,IF($K$10="Прочие",Подложка!AP56*I25/100,IF($K$10="ИТ",Подложка!AU56*I25/100,0)))))))))) -> 5 | N25: (Автоматический расчет)
B26: 1.3 Длительность операционного цикла | I26: 5 | J26: ='РСБУ отчетность'!E81 -> 166.83719 | K26: =ROUND(IF($K$10="Строительство",Подложка!G47*I26/100,IF($K$10="Добыча, переработка и транспортировка газа, нефти и нефтепродуктов",Подложка!L47*I26/100,IF($K$10="Транспортировка и хранение",Подложка!Q47*I26/100,IF($K$10="Торговля",Подложка!V47*I26/100,IF($K$10="Производство",Подложка!AA47*I26/100,IF($K$10="Авиакомпания",Подложка!AF47*I26/100,IF($K$10="Судовладелец",Подложка!AK47*I26/100,IF($K$10="Прочие",Подложка!AP47*I26/100,IF($K$10="ИТ",Подложка!AU47*I26/100,0))))))))),0) -> 0 | L26: ='РСБУ отчетность'!F81 -> 140.56013 | M26: =IF(L26="",0,IF($K$10="Строительство",Подложка!G57*I26/100,IF($K$10="Добыча, переработка и транспортировка газа, нефти и нефтепродуктов",Подложка!L57*I26/100,IF($K$10="Транспортировка и хранение",Подложка!Q57*I26/100,IF($K$10="Торговля",Подложка!V57*I26/100,IF($K$10="Производство",Подложка!AA57*I26/100,IF($K$10="Авиакомпания",Подложка!AF57*I26/100,IF($K$10="Судовладелец",Подложка!AK57*I26/100,IF($K$10="Прочие",Подложка!AP57*I26/100,IF($K$10="ИТ",Подложка!AU57*I26/100,0)))))))))) -> 0 | N26: (Автоматический расчет)
B27: 1.4 Коэффициент автономии | I27: 10 | J27: ='РСБУ отчетность'!E82 -> 0.70509515 | K27: =ROUND(IF(J27="",0,IF($K$10="Строительство",Подложка!G48*I27/100,IF($K$10="Добыча, переработка и транспортировка газа, нефти и нефтепродуктов",Подложка!L48*I27/100,IF($K$10="Транспортировка и хранение",Подложка!Q48*I27/100,IF($K$10="Торговля",Подложка!V48*I27/100,IF($K$10="Производство",Подложка!AA48*I27/100,IF($K$10="Авиакомпания",Подложка!AF48*I27/100,IF($K$10="Судовладелец",Подложка!AK48*I27/100,IF($K$10="Прочие",Подложка!AP48*I27/100,IF($K$10="ИТ",Подложка!AU48*I27/100,0)))))))))),0) -> 10 | L27: ='РСБУ отчетность'!F82 -> 0.67351065 | M27: =IF(L27="",0,IF($K$10="Строительство",Подложка!G58*I27/100,IF($K$10="Добыча, переработка и транспортировка газа, нефти и нефтепродуктов",Подложка!L58*I27/100,IF($K$10="Транспортировка и хранение",Подложка!Q58*I27/100,IF($K$10="Торговля",Подложка!V58*I27/100,IF($K$10="Производство",Подложка!AA58*I27/100,IF($K$10="Авиакомпания",Подложка!AF58*I27/100,IF($K$10="Судовладелец",Подложка!AK58*I27/100,IF($K$10="Прочие",Подложка!AP58*I27/100,IF($K$10="ИТ",Подложка!AU58*I27/100,0)))))))))) -> 7 | N27: (Автоматический расчет)
B28: 1.5 Рентабельность продаж | I28: 5 | J28: ='РСБУ отчетность'!E83 -> 9.6934592 | K28: =ROUND(IF(J28="",0,IF($K$10="Строительство",Подложка!G49*I28/100,IF($K$10="Добыча, переработка и транспортировка газа, нефти и нефтепродуктов",Подложка!L49*I28/100,IF($K$10="Транспортировка и хранение",Подложка!Q49*I28/100,IF($K$10="Торговля",Подложка!V49*I28/100,IF($K$10="Производство",Подложка!AA49*I28/100,IF($K$10="Авиакомпания",Подложка!AF49*I28/100,IF($K$10="Судовладелец",Подложка!AK49*I28/100,IF($K$10="Прочие",Подложка!AP49*I28/100,IF($K$10="ИТ",Подложка!AU49*I28/100,0)))))))))),0) -> 4 | L28: ='РСБУ отчетность'!F83 -> 21.337774 | M28: =IF(L28="",0,IF($K$10="Строительство",Подложка!G59*I28/100,IF($K$10="Добыча, переработка и транспортировка газа, нефти и нефтепродуктов",Подложка!L59*I28/100,IF($K$10="Транспортировка и хранение",Подложка!Q59*I28/100,IF($K$10="Торговля",Подложка!V59*I28/100,IF($K$10="Производство",Подложка!AA59*I28/100,IF($K$10="Авиакомпания",Подложка!AF59*I28/100,IF($K$10="Судовладелец",Подложка!AK59*I28/100,IF($K$10="Прочие",Подложка!AP59*I28/100,IF($K$10="ИТ",Подложка!AU59*I28/100,0)))))))))) -> 5 | N28: (Автоматический расчет)
B29: 1.6 Коэффициент долговой нагрузки | I29: 10 | J29: ='РСБУ отчетность'!E84 -> 0.30470929 | K29: =ROUND(IF(J29=0,I29,IF(OR(J29="",J29<0),0,IF($K$10="Строительство",Подложка!G50*I29/100,IF($K$10="Добыча, переработка и транспортировка газа, нефти и нефтепродуктов",Подложка!L50*I29/100,IF($K$10="Транспортировка и хранение",Подложка!Q50*I29/100,IF($K$10="Торговля",Подложка!V50*I29/100,IF($K$10="Производство",Подложка!AA50*I29/100,IF($K$10="Авиакомпания",Подложка!AF50*I29/100,IF($K$10="Судовладелец",Подложка!AK50*I29/100,IF($K$10="Прочие",Подложка!AP50*I29/100,IF($K$10="ИТ",Подложка!AU50*I29/100,0))))))))))),0) -> 7 | L29: ='РСБУ отчетность'!F84 -> 0.16220914 | M29: =IF(L29="",0,IF($K$10="Строительство",Подложка!G60*I29/100,IF($K$10="Добыча, переработка и транспортировка газа, нефти и нефтепродуктов",Подложка!L60*I29/100,IF($K$10="Транспортировка и хранение",Подложка!Q60*I29/100,IF($K$10="Торговля",Подложка!V60*I29/100,IF($K$10="Производство",Подложка!AA60*I29/100,IF($K$10="Авиакомпания",Подложка!AF60*I29/100,IF($K$10="Судовладелец",Подложка!AK60*I29/100,IF($K$10="Прочие",Подложка!AP60*I29/100,IF($K$10="ИТ",Подложка!AU60*I29/100,0)))))))))) -> 7 | N29: (Автоматический расчет)
B30: 1.7 Коэффициент покрытия процентов | I30: 5 | J30: ='РСБУ отчетность'!E85 -> 18.721681 | K30: =ROUND(IF(J30=0,I30,IF(OR(J30="",J30<0),0,IF($K$10="Строительство",Подложка!G51*I30/100,IF($K$10="Добыча, переработка и транспортировка газа, нефти и нефтепродуктов",Подложка!L51*I30/100,IF($K$10="Транспортировка и хранение",Подложка!Q51*I30/100,IF($K$10="Торговля",Подложка!V51*I30/100,IF($K$10="Производство",Подложка!AA51*I30/100,IF($K$10="Авиакомпания",Подложка!AF51*I30/100,IF($K$10="Судовладелец",Подложка!AK51*I30/100,IF($K$10="Прочие",Подложка!AP51*I30/100,IF($K$10="ИТ",Подложка!AU51*I30/100,0))))))))))),0) -> 5 | L30: ='РСБУ отчетность'!F85 -> 34.086001 | M30: =IF(L30="",0,IF($K$10="Строительство",Подложка!G61*I30/100,IF($K$10="Добыча, переработка и транспортировка газа, нефти и нефтепродуктов",Подложка!L61*I30/100,IF($K$10="Транспортировка и хранение",Подложка!Q61*I30/100,IF($K$10="Торговля",Подложка!V61*I30/100,IF($K$10="Производство",Подложка!AA61*I30/100,IF($K$10="Авиакомпания",Подложка!AF61*I30/100,IF($K$10="Судовладелец",Подложка!AK61*I30/100,IF($K$10="Прочие",Подложка!AP61*I30/100,IF($K$10="ИТ",Подложка!AU61*I30/100,0)))))))))) -> 5 | N30: (Автоматический расчет)
B31: 1.8 Коэффициент маневренности | I31: 5 | J31: ='РСБУ отчетность'!E86 -> 0.68527449 | K31: =ROUND(IF(J24="",0,IF(OR(J31="",J31<0),0,IF($K$10="Строительство",Подложка!G52*I31/100,IF($K$10="Добыча, переработка и транспортировка газа, нефти и нефтепродуктов",Подложка!L52*I31/100,IF($K$10="Транспортировка и хранение",Подложка!Q52*I31/100,IF($K$10="Торговля",Подложка!V52*I31/100,IF($K$10="Производство",Подложка!AA52*I31/100,IF($K$10="Авиакомпания",Подложка!AF52*I31/100,IF($K$10="Судовладелец",Подложка!AK52*I31/100,IF($K$10="Прочие",Подложка!AP52*I31/100,IF($K$10="ИТ",Подложка!AU52*I31/100,0))))))))))),0) -> 5 | L31: ='РСБУ отчетность'!F86 -> 0.65401698 | M31: =IF(L31="",0,IF($K$10="Строительство",Подложка!G62*I31/100,IF($K$10="Добыча, переработка и транспортировка газа, нефти и нефтепродуктов",Подложка!L62*I31/100,IF($K$10="Транспортировка и хранение",Подложка!Q62*I31/100,IF($K$10="Торговля",Подложка!V62*I31/100,IF($K$10="Производство",Подложка!AA62*I31/100,IF($K$10="Авиакомпания",Подложка!AF62*I31/100,IF($K$10="Судовладелец",Подложка!AK62*I31/100,IF($K$10="Прочие",Подложка!AP62*I31/100,IF($K$10="ИТ",Подложка!AU62*I31/100,0)))))))))) -> 5 | N31: (Автоматический расчет)
B32: 1.9 Рентабельность капитала | I32: 4 | J32: ='РСБУ отчетность'!E87 -> 26.007659 | K32: =ROUND(IF(J32="",0,IF(OR(J32="",J32<0),0,IF($K$10="Строительство",Подложка!G53*I32/100,IF($K$10="Добыча, переработка и транспортировка газа, нефти и нефтепродуктов",Подложка!L53*I32/100,IF($K$10="Транспортировка и хранение",Подложка!Q53*I32/100,IF($K$10="Торговля",Подложка!V53*I32/100,IF($K$10="Производство",Подложка!AA53*I32/100,IF($K$10="Авиакомпания",Подложка!AF53*I32/100,IF($K$10="Судовладелец",Подложка!AK53*I32/100,IF($K$10="Прочие",Подложка!AP53*I32/100,IF($K$10="ИТ",Подложка!AU53*I32/100,0))))))))))),0) -> 3 | L32: ='РСБУ отчетность'!F87 -> 65.990771 | M32: =IF(L32="",0,IF($K$10="Строительство",Подложка!G63*I32/100,IF($K$10="Добыча, переработка и транспортировка газа, нефти и нефтепродуктов",Подложка!L63*I32/100,IF($K$10="Транспортировка и хранение",Подложка!Q63*I32/100,IF($K$10="Торговля",Подложка!V63*I32/100,IF($K$10="Производство",Подложка!AA63*I32/100,IF($K$10="Авиакомпания",Подложка!AF63*I32/100,IF($K$10="Судовладелец",Подложка!AK63*I32/100,IF($K$10="Прочие",Подложка!AP63*I32/100,IF($K$10="ИТ",Подложка!AU63*I32/100,0)))))))))) -> 4 | N32: (Автоматический расчет)
B33: 1.10 Динамика ликвидности | I33: 3 | J33: ='РСБУ отчетность'!E88 -> Рост | K33: =VLOOKUP(J33,Подложка!$AD$3:$AE$6,2,0) -> 3 | L33: ='РСБУ отчетность'!F88 -> На прежнем уровне | M33: =VLOOKUP(L33,Подложка!$AD$3:$AE$6,2,0) -> 0 | N33: (Автоматический расчет)
B34: 1.11 Динамика рентабельности продаж | I34: 3 | J34: ='РСБУ отчетность'!E89 -> Снижение | K34: =VLOOKUP(J34,Подложка!$AD$3:$AE$6,2,0) -> -3 | L34: ='РСБУ отчетность'!F89 -> Снижение | M34: =VLOOKUP(L34,Подложка!$AD$3:$AE$6,2,0) -> -3 | N34: (Автоматический расчет)
B35: Итого баллов с учетом веса показателей | I35: =SUM(I24:I34) -> 65 | K35: =SUM(K24:K34) -> 49 | M35: =SUM(M24:M34) -> 45 | N35: (Автоматический расчет)
B37: 2. ПОКАЗАТЕЛИ ДЕЛОВОЙ РЕПУТАЦИИ
J39: ='РСБУ отчетность'!E5 -> 46022 | L39: ='РСБУ отчетность'!F5 -> 45657 | N39: (Автоматический расчет)
B40: Наименование показателя | I40: Макс. балл | J40: Значение | K40: Баллы | L40: Значение | M40: Баллы
B41: 2.1 Опыт работы с контрагентом | I41: 5 | J41: более 3-х лет | K41: =IF($J$41="более 3-х лет",100*I41/100,IF($J$41="от 1 до 3-х лет",70*I41/100,IF($J$41="менее 1 года",40*I41/100,0))) -> 5 | L41: более 3-х лет | M41: =IF($L$41="более 3-х лет",100*I41/100,IF($L$41="от 1 до 3-х лет",70*I41/100,IF($L$41="менее 1 года",40*I41/100,0))) -> 5 | N41: (В голубых ячейках выбрать значение из списка)
B42: 2.2 Платежная дисциплина контрагента | I42: 15 | J42: ПДЗ отсутствовала | K42: =IF(OR(J42="ПДЗ отсутствовала",J42="Техническая ПДЗ"),15,IF(J42="Разовая ПДЗ продолжительностью менее 30 дней",10,IF(J42="Разовая ПДЗ продолжительностью более 30 дней",7.5,IF(J42="Неоднократное возникновение ПДЗ",3.5,IF(J42="Информация отсутствует",3.5,0))))) -> 15 | L42: ПДЗ отсутствовала | M42: =IF(OR(L42="ПДЗ отсутствовала",L42="Техническая ПДЗ"),15,IF(L42="Разовая ПДЗ продолжительностью менее 30 дней",10,IF(L42="Разовая ПДЗ продолжительностью более 30 дней",7.5,IF(L42="Неоднократное возникновение ПДЗ",3.5,IF(L42="Информация отсутствует",3.5,0))))) -> 15 | N42: (В голубых ячейках выбрать значение из списка)
B43: Итого баллов с учетом веса показателей | I43: 20 | K43: =SUM(K41:K42) -> 20 | M43: =SUM(M41:M42) -> 20 | N43: (Автоматический расчет)
B45: 3. ПОКАЗАТЕЛИ ИЗ ВНЕШНИХ ИСТОЧНИКОВ
J48: ='РСБУ отчетность'!E5 -> 46022
B49: Повышающие показатели | I49: Макс. балл | J49: Значение | K49: Баллы | L49: Дата регистрации
B50: 3.1 Возраст компании | I50: 5 | J50: =IF(OR(L50="",L50=0),"Информация отсутствует",IF(L50>TODAY(),"Информация некорректна",IF(TODAY()-L50<730,"Менее 2 лет",IF(TODAY()-L50<1825,"От 2 до 5-и лет","Более 5 лет")))) -> Более 5 лет | K50: =IF(OR(L50="Информация отсутствует",L50="Информация некорректна"),0,IF(L50="Менее 2 лет",40*I50/100,IF(L50="От 2 до 5-и лет",70*I50/100,100*I50/100))) -> 5 | L50: 34928 | N50: (Голубая ячейка заполняется вручную)
B51: 3.2 Сводный индикатор риска СПАРК | I51: 10 | J51: Низкий | K51: =IF(J51="Информация отсутствует",0.001,IF(J51="Низкий",100*I51/100,IF(J51="Средний",50*I51/100,0))) -> 10 | N51: (В голубой ячейке выбрать значение из списка)
B52: Понижающий показатель
B53: 3.3 Реестр недобросовестных поставщиков | I53: -5 | J53: Отсутствует в реестре | K53: =IF(J53="",-0.000001,IF(J53="Информация отсутствует",-0.000001,IF(J53="Включен в реестр",100*I53/100,0))) -> 0 | N53: (В голубой ячейке выбрать значение из списка)
B54: Итого баллов с учетом веса показателей | I54: 15 | K54: =IF(ROUND(SUM(K50:K51,II53),2)<0,0,ROUND(SUM(K50:K51,K53),2)) -> 15 | N54: (Автоматический расчет)
J57: ='РСБУ отчетность'!E5 -> 46022 | L57: ='РСБУ отчетность'!F5 -> 45657 | N57: (Автоматический расчет)
B58: ИТОГО СКОРИНГ-БАЛЛ (1.+2.+3.) | I58: =SUM(I35,I43,I54) -> 100 | J58: =IF(LEFT(H11,2)="Да",0,SUM(K35,K43,K54)) -> 84 | K58: из 100 | L58: =IF(LEFT(H11,2)="Да",0,SUM(M35,M43,K54)) -> 80 | M58: из 100 | N58: (Автоматический расчет)
B60: Группа кредитоспособности (1-4) | J60: =IF(LEFT(H11,2)="Да",4,IF($K$10="Строительство",Подложка!G82,IF($K$10="Добыча, переработка и транспортировка газа, нефти и нефтепродуктов",Подложка!L82,IF($K$10="Транспортировка и хранение",Подложка!Q82,IF($K$10="Торговля",Подложка!V82,IF($K$10="Производство",Подложка!AA82,IF($K$10="Авиакомпания",Подложка!AF82,IF($K$10="Судовладелец",Подложка!AK82,IF($K$10="Прочие",Подложка!AP82,IF($K$10="ИТ",Подложка!AU82,0)))))))))) -> 1 | L60: =IF(LEFT(H11,2)="Да",4,IF($K$10="Строительство",Подложка!G83,IF($K$10="Добыча, переработка и транспортировка газа, нефти и нефтепродуктов",Подложка!L83,IF($K$10="Транспортировка и хранение",Подложка!Q83,IF($K$10="Торговля",Подложка!V83,IF($K$10="Производство",Подложка!AA83,IF($K$10="Авиакомпания",Подложка!AF83,IF($K$10="Судовладелец",Подложка!AK83,IF($K$10="Прочие",Подложка!AP83,IF($K$10="ИТ",Подложка!AU83,0)))))))))) -> 1 | N60: (Автоматический расчет)
B61: Класс контрагента (А-С) | J61: B | L61: B | N61: (В голубых ячейках выбрать значение из списка )
B64: 4. ДОПОЛНИТЕЛЬНЫЕ ПОКАЗАТЕЛИ
I66: Макс. балл | J66: Значение | K66: Баллы
B67: 4.1 Графовый индикатор БАНК ГПБ (АО) | I67: 10 | J67: AAA | K67: =VLOOKUP(J67,Подложка!X3:Z28,2,0) -> 10 | N67: (В голубых ячейках выбрать значение из списка )
B68: 4.2 Исковый индикатор БАНК ГПБ (АО) | I68: 10 | J68: BBB | K68: =VLOOKUP(J68,Подложка!X3:Z28,3,0) -> 3 | N68: (В голубых ячейках выбрать значение из списка )
B69: Итого дополнительных баллов | I69: 20 | K69: =K67+K68 -> 13 | N69: (Автоматический расчет)
B71: 5. ДАННЫЕ О ПРЕТЕНЗИОННО-ИСКОВОЙ РАБОТЕ С КОНТРАГЕНТОМ
J73: Значение | L73: Размер штрафа
B74: 5.1 Наличие досудебных претензий | J74: Отсутствуют | L74: =VLOOKUP(J74,Подложка!Q3:R7,2,0) -> 0 | N74: (В голубых ячейках выбрать значение из списка )
B75: 5.2 Наличие исковых требований | J75: Отсутствуют | L75: =VLOOKUP(J75,Подложка!S2:T5,2,0) -> 0 | N75: (В голубых ячейках выбрать значение из списка )
B76: Итого штрафные баллы с учетом показателей | L76: =MAX(K74:M75) -> 0 | N76: (Автоматический расчет)
B78: ="6. РАСЧЕТ КРЕДИТНОГО ЛИМИТА И АВАНСОВОГО ПЛАТЕЖА"&", "&'РСБУ отчетность'!C2&'РСБУ отчетность'!C3 -> 6. РАСЧЕТ КРЕДИТНОГО ЛИМИТА И АВАНСОВОГО ПЛАТЕЖА, тыс. руб.
J79: =J22 -> 46022 | L79: =L22 -> 45657
B80: ="Внеоборотные активы (ОС+НС), "&'РСБУ отчетность'!C2&'РСБУ отчетность'!C3 -> Внеоборотные активы (ОС+НС), тыс. руб. | J80: ='РСБУ отчетность'!E12 -> 173805 | L80: ='РСБУ отчетность'!F12 -> 119413 | N80: (Автоматический расчет)
B81: ="Чистые активы (ЧА), "&'РСБУ отчетность'!C2&'РСБУ отчетность'!C3 -> Чистые активы (ЧА), тыс. руб. | J81: ='РСБУ отчетность'!E76 -> 2211450 | L81: ='РСБУ отчетность'!F76 -> 1899362 | N81: (Автоматический расчет)
B82: Наименьшее значение (показатель 1) | J82: =MIN(J80,J81) -> 173805 | L82: =MIN(L80,L81) -> 119413 | N82: (Автоматический расчет)
B83: ="Оборотные активы (ОА), "&'РСБУ отчетность'!C2&'РСБУ отчетность'!C3 -> Оборотные активы (ОА), тыс. руб. | J83: ='РСБУ отчетность'!E19 -> 2935952 | L83: ='РСБУ отчетность'!F19 -> 2661200 | N83: (Автоматический расчет)
B84: ="Краткосрочные обязательства (КО), "&'РСБУ отчетность'!C2&'РСБУ отчетность'!C3 -> Краткосрочные обязательства (КО), тыс. руб. | J84: ='РСБУ отчетность'!E44 -> 920655 | L84: ='РСБУ отчетность'!F44 -> 913174 | N84: (Автоматический расчет)
B85: ОА-КО (показатель 2) | J85: =J83-J84 -> 2015297 | L85: =L83-L84 -> 1748026 | N85: (Автоматический расчет)
B86: База для расчета кредитного лимита (наибольшее из показателей 1 и 2) | J86: =MAX(J82,J85) -> 2015297 | L86: =MAX(L82,L85) -> 1748026 | N86: (Автоматический расчет)
B87: База для расчета лимита авансового платежа (показатель 1) | J87: =J82 -> 173805 | L87: =L82 -> 119413 | N87: (Автоматический расчет)
B88: Понижающий коэффициент (итого баллов/100) | J88: =J58/100 -> 0.84 | L88: =L58/100 -> 0.8 | N88: (Автоматический расчет)
B89: Коэффициент надежности ( по группе кредитоспособности) | J89: =IF(J60=1,0.3,IF(J60=2,0.2,IF(J60=3,0.1,IF(J60=4,0,"ошибка")))) -> 0.3 | L89: =IF(L60=1,0.3,IF(L60=2,0.2,IF(L60=3,0.1,IF(L60=4,0,"ошибка")))) -> 0.3
B90: Доп. коэффициент по индикаторам (1+доп. баллы/100) | J90: =1+K69/100 -> 1.13 | L90: =1+K69/100 -> 1.13 | N90: (Автоматический расчет)
B91: Штраф за наличие претензионно-исковой работы (штрафные баллы/100) | J91: =L76/100 -> 0 | L91: =L76/100 -> 0 | N91: (Автоматический расчет)
B92: ="Кредитный лимит контрагента, "&'РСБУ отчетность'!C2&'РСБУ отчетность'!C3 -> Кредитный лимит контрагента, тыс. руб. | J92: =IF(IF(J86>0,J86*J88*J90*(1-J91),0)<0,0,IF(J86>0,J86*J88*J90*(1-J91),0)) -> 1912919.9 | L92: =IF(IF(L86>0,L86*L88*L90*(1-L91),0)<0,0,IF(L86>0,L86*L88*L90*(1-L91),0)) -> 1580215.5 | N92: (Автоматический расчет)
B93: ="Лимит авансового платежа, "&'РСБУ отчетность'!C2&'РСБУ отчетность'!C3 -> Лимит авансового платежа, тыс. руб. | J93: =IF(J87*J89*J90*(1-J91)<0,0,IF(J87>0,J87*J89*J90*(1-J91),0)) -> 58919.895 | L93: =IF(L87*L89*L90*(1-L91)<0,0,IF(L87>0,L87*L89*L90*(1-L91),0)) -> 40481.007 | N93: (Автоматический расчет)
B95: Расчеты проводил(а): | E95: Смирнов С.С. | N95: (Голубая ячейка заполняется вручную)

Sheet РСБУ отчетность
A1: ДАННЫЕ ОТЧЕТНОСТИ | F1: заполнять вручную
A2: Единица измерения | C2: тыс. | F2: заполняется автоматически
A3: Валюта отчетности | C3: руб.
A4: Бухгалтерский баланс (Форма №1)
D5: Код строки | E5: 46022 | F5: 45657 | G5: 45291
A6: АКТИВ
A7: I. Внеоборотные активы: | D7: 1100 | E7: =SUM(E8:E18) -> 199517 | F7: =SUM(F8:F18) -> 158892 | G7: =SUM(G8:G18) -> 136886
A8: Нематериальные активы | D8: 1110 | E8: =18170 -> 18170 | F8: 33163 | G8: 39653
A9: Результаты исследований и разработок | D9: 1120 | E9: 0 | F9: 0 | G9: 0
A10: Нематериальные поисковые активы | D10: 1130 | E10: 0 | F10: 0 | G10: 0
A11: Материальные поисковые активы | D11: 1140 | E11: 0 | F11: 0 | G11: 0
A12: Основные средства (в т.ч. НЗ) | D12: 1150 | E12: 173805 | F12: 119413 | G12: 94029
A13: Право пользования активом | D13: 1157 | E13: 0 | F13: 0 | G13: 0
A14: Инвестиционная недвижимость | D14: 1160 | E14: 0 | F14: 0 | G14: 0
A15: Финансовые вложения | D15: 1170 | E15: 900 | F15: 812 | G15: 822
A16: Отложенные налоговые активы | D16: 1180 | E16: 6642 | F16: 5504 | G16: 2382
A17: Дебиторская задолженность, платежи по которой ожидаются более чем через 12 месяцев после отчетной даты | D17: 1185
A18: Прочие внеоборотные активы | D18: 1190 | E18: 0 | F18: 0 | G18: 0
A19: II. Оборотные активы | D19: 1200 | E19: =SUM(E20:E23,E25:E27) -> 2935952 | F19: =SUM(F20:F23,F25:F27) -> 2661200 | G19: =SUM(G20:G23,G25:G27) -> 1806482
A20: Запасы | D20: 1210 | E20: 1351289 | F20: 1061615 | G20: 932045
A21: Долгосрочные активы к продаже | D21: 1215 | E21: 0 | F21: 0 | G21: 0
A22: НДС по приобретенным ценностям | D22: 1220 | E22: 7 | F22: 0 | G22: 0
A23: Дебиторская задолженность | D23: 1230 | E23: 1354059 | F23: 1470512 | G23: 732868
A24: Задолженность учредителей по взносам в УК | D24: 1237 | E24: 0 | F24: 0 | G24: 0
A25: Фин.вложения (за искл.денеж.эквивалентов) | D25: 1240 | E25: 0 | F25: 15000 | G25: 75905
A26: Денежные средства и денежные эквиваленты | D26: 1250 | E26: 210093 | F26: 96119 | G26: 44876
A27: Прочие оборотные активы | D27: 1260 | E27: 20504 | F27: 17954 | G27: 20788
A28: ИТОГО АКТИВ | D28: 1600 | E28: =E7+E19 -> 3135469 | F28: =F7+F19 -> 2820092 | G28: =G7+G19 -> 1943368
A29: ПАССИВ
A30: III. Капитал и резервы: | D30: 1300 | E30: =SUM(E31:E36) -> 2210804 | F30: =SUM(F31:F36) -> 1899362 | G30: =SUM(G31:G36) -> 1345353
A31: Уставной капитал | D31: 1310 | E31: 19896 | F31: 19896 | G31: 19896
A32: Собственные акции, выкупленные у акционеров | D32: 1320 | E32: 0 | F32: 0
A33: Накопленная дооценка внеоборотных активов | D33: 1340 | E33: 20729 | F33: 86449 | G33: 86449
A34: Добавочный капитал (без накопленной дооценки) | D34: 1350 | E34: 33333 | F34: 33333 | G34: 33333
A35: Резервный капитал | D35: 1360 | E35: 995 | F35: 995 | G35: 995
A36: Нераспределенная прибыль (непокрытый убыток) | D36: 1370 | E36: 2135851 | F36: 1758689 | G36: 1204680
A37: IV. Долгосрочные обязательства | D37: 1400 | E37: =SUM(E38:E42) -> 4010 | F37: =SUM(F38:F42) -> 7556 | G37: =SUM(G38:G42) -> 7277
A38: Заемные средства | D38: 1410 | F38: 0 | G38: 0
A39: Отложенные налоговые обязательства | D39: 1420 | E39: 4010 | F39: 7556 | G39: 7277
A40: Оценочные обязательства | D40: 1430 | E40: 0 | F40: 0 | G40: 0
A41: Кредиторская задолженность со сроком погашения более чем 12 месяцев после отчетной даты | D41: 1440
A42: Прочие долгосрочные обязательства | D42: 1450 | E42: 0 | F42: 0 | G42: 0
A43: Обязательство по аренде | D43: 1460 | E43: 0 | F43: 0 | G43: 0
A44: V. Краткосрочные обязательства: | D44: 1500 | E44: =SUM(E45:E46,E47:E49) -> 920655 | F44: =SUM(F45:F46,F47:F49) -> 913174 | G44: =SUM(G45:G46,G47:G49) -> 590738
A45: Заемные средства | D45: 1510 | E45: 163319 | F45: 174456 | G45: 78924
A46: Кредиторская задолженность | D46: 1520 | E46: 730781 | F46: 717927 | G46: 501764
A47: Доходы будущих периодов | D47: 1530 | E47: 646 | F47: 0 | G47: 0
A48: Оценочные обязательства | D48: 1540 | E48: 25909 | F48: 20791 | G48: 10050
A49: Прочие краткосрочные обязательства | D49: 1550 | E49: 0 | F49: 0 | G49: 0
A50: Обязательство по аренде | D50: 1560 | E50: 0 | F50: 0 | G50: 0
A51: ИТОГО ПАССИВ | D51: 1700 | E51: =E30+E37+E44 -> 3135469 | F51: =F30+F37+F44 -> 2820092 | G51: =G30+G37+G44 -> 1943368
E52: =E28-E51 -> 0 | F52: =F28-F51 -> 0 | G52: =G28-G51 -> 0
A53: Отчет о финансовых результатах (Форма №2)
D54: Код строки | E54: =E5 -> 46022 | F54: =F5 -> 45657 | G54: =G5 -> 45291
A55: Выручка | D55: 2110 | E55: 4319882 | F55: 4723937 | G55: 4059031
A56: Себестоимость продаж | D56: 2120 | E56: 2983084 | F56: 3117946 | G56: 2294620
A57: Валовая прибыль (убыток) | D57: 2100 | E57: 1336798 | F57: 1605991 | G57: 1764411
A58: Коммерческие расходы | D58: 2210 | E58: 137960 | F58: 49963 | G58: 54805
A59: Управленческие расходы | D59: 2220 | E59: 780092 | F59: 548045 | G59: 657575
A60: Прибыль (убыток) от продаж | D60: 2200 | E60: 418746 | F60: 1007983 | G60: 1052031
A61: Доходы от участия в других организациях | D61: 2310 | E61: 91 | F61: 87 | G61: 65
A62: Проценты к получению | D62: 2320 | E62: 32285 | F62: 28328 | G62: 23391
A63: Проценты к уплате | D63: 2330 | E63: 28629 | F63: 31639 | G63: 7252
A64: Прочие доходы | D64: 2340 | E64: 179399 | F64: 759580 | G64: 296175
A65: Прочие расходы | D65: 2350 | E65: 62253 | F65: 689203 | G65: 467927
A66: Прибыль (убыток) до налогообложения | D66: 2300 | E66: 539639 | F66: 1075136 | G66: 896423
... A71: Чистая прибыль (убыток) | D71: 2400 | E71: 411537 | F71: 854196 | G71: 710911
A72: Период (дни) | E72: =E54-DATE(YEAR(E54),1,1)+1 -> 365 | F72: =F54-DATE(YEAR(F54),1,1)+1 -> 366 | G72: =G54-DATE(YEAR(G54),1,1)+1 -> 365
A74: Отчет об изменении капитала (Форма №3)
D75: Код строки | E75: =E5 -> 46022 | F75: =F5 -> 45657 | G75: =G5 -> 45291
A76: Чистые активы | D76: 3600 | E76: =(E7+E19-E24)-(E37+E44-E47) -> 2211450 | F76: =(F7+F19-F24)-(F37+F44-F47) -> 1899362 | G76: =(G7+G19-G24)-(G37+G44-G47) -> 1345353
A79: Коэффициент текущей ликвидности | E79: =IFERROR((E19)/(E44-E48-E47),"") -> 3.2836953 | F79: =IFERROR((F19)/(F44-F48-F47),"") -> 2.9821276 | G79: =IFERROR((G19)/(G44-G48-G47),"") -> 3.1109339
A80: Коэффициент быстрой ликвидности | E80: =IFERROR((E23+E26)/(E44-E47-E48),"") -> 1.7494151 | F80: =IFERROR((F23+F26)/(F44-F47-F48),"") -> 1.755559 | G80: =IFERROR((G23+G26)/(G44-G47-G48),"") -> 1.3393492
A81: Длительность операционного цикла | E81: =IFERROR((E20+E23-E46)/(E55/E72),"") -> 166.83719 | F81: =IFERROR((F20+F23-F46)/(F55/F72),"") -> 140.56013 | G81: =IFERROR((G20+G23-G46)/(G55/G72),"") -> 104.59378
A82: Коэффициент автономии | E82: =IFERROR((E30)/E51,"") -> 0.70509515 | F82: =IFERROR((F30)/F51,"") -> 0.67351065 | G82: =IFERROR((G30)/G51,"") -> 0.69227907
A83: Рентабельность продаж | E83: =IFERROR((E60/E55)*100,"") -> 9.6934592 | F83: =IFERROR((F60/F55)*100,"") -> 21.337774 | G83: =IFERROR((G60/G55)*100,"") -> 25.91828
A84: Коэффициент долговой нагрузки | E84: =IFERROR((E38+E45)/((E66+E63-E62)/E72*365),"") -> 0.30470929 | F84: =IFERROR((F38+F45)/((F66+F63-F62)/F72*365),"") -> 0.16220914 | G84: =IFERROR((G38+G45)/((G66+G63-G62)/G72*365),"") -> 0.089657429
A85: Коэффициент покрытия процентов | E85: =IFERROR((E66+E63-E62)/(E63),"") -> 18.721681 | F85: =IFERROR((F66+F63-F62)/(F63),"") -> 34.086001 | G85: =IFERROR((G66+G63-G62)/(G63),"") -> 121.385
A86: Коэффициент маневренности | E86: =IFERROR((E30-E32+E47-E7)/(E19),"") -> 0.68527449 | F86: =IFERROR((F30-F32+F47-F7)/(F19),"") -> 0.65401698 | G86: =IFERROR((G30-G32+G47-G7)/(G19),"") -> 0.66896155
A87: Рентабельность капитала | E87: =IFERROR(((E66+E63-E62)/E72*365)/((E30+E37+F30+F37)/2)*100,"") -> 26.007659 | F87: =IFERROR(((F66+F63-F62)/F72*365)/((F30+F37+G30+G37)/2)*100,"") -> 65.990771 | G87: =IFERROR(((G66+G63-G62)/G72*365)/((G30+G37+H30+H37)/2)*100,"") -> 130.15888
A88: Динамика ликвидности | E88: =IFERROR(IF((IFERROR((E19)/(E44-E48-E47),"")/IFERROR((F19)/(F44-F48-F47),"")-1)>0.1,"Рост",IF((IFERROR((E19)/(E44-E48-E47),"")/IFERROR((F19)/(F44-F48-F47),"")-1)<-0.1,"Снижение","На прежнем уровне")),"Нет данных") -> Рост | F88: =IFERROR(IF((IFERROR((F19)/(F44-F48-F47),"")/IFERROR((G19)/(G44-G48-G47),"")-1)>0.1,"Рост",IF((IFERROR((F19)/(F44-F48-F47),"")/IFERROR((G19)/(G44-G48-G47),"")-1)<-0.1,"Снижение","На прежнем уровне")),"Нет данных") -> На прежнем уровне | G88: =IFERROR(IF((IFERROR((G19)/(G44-G48-G47),"")/IFERROR((H19)/(H44-H48-H47),"")-1)>0.1,"Рост",IF((IFERROR((G19)/(G44-G48-G47),"")/IFERROR((H19)/(H44-H48-H47),"")-1)<-0.1,"Снижение","На прежнем уровне")),"Нет данных") -> Нет данных
A89: Динамика рентабельности продаж | E89: =IFERROR(IF((IFERROR(((E60/E55)*100),"")/IFERROR(((F60/F55)*100),"")-1)>0.1,"Рост",IF((IFERROR(((E60/E55)*100),"")/IFERROR((F60/F55)*100,"")-1)<-0.1,"Снижение","На прежнем уровне")),"Нет данных") -> Снижение | F89: =IFERROR(IF((IFERROR(((F60/F55)*100),"")/IFERROR(((G60/G55)*100),"")-1)>0.1,"Рост",IF((IFERROR(((F60/F55)*100),"")/IFERROR((G60/G55)*100,"")-1)<-0.1,"Снижение","На прежнем уровне")),"Нет данных") -> Снижение | G89: =IFERROR(IF((IFERROR(((G60/G55)*100),"")/IFERROR(((H60/H55)*100),"")-1)>0.1,"Рост",IF((IFERROR(((G60/G55)*100),"")/IFERROR((H60/H55)*100,"")-1)<-0.1,"Снижение","На прежнем уровне")),"Нет данных") -> Нет данных

Sheet Подложка
A2: Коды ОКВЭД | C2: Сводный индикатор риска СПАРК | E2: Реестр недобросовестных поставщиков | G2: Класс | I2: Наличие СТОП-факторов | K2: Опыт работы с контрагентом | M2: Наличие просроченной дебиторской задолженности с ГК ГПН | O2: Категория контрагента | Q2: Наличие досудебных претензий | R2: Штраф | S2: Наличие исковых требований | T2: Штраф | X2: ВКР (Графовый индикатор) | Y2: Баллы (Графовый индикатор) | Z2: Баллы (Исковый индикатор) | AD2: Для коэф | AG2: для налогов
A3: 41-43, 71 | C3: Низкий | E3: Отсутствует в реестре | G3: A | I3: Нет | K3: более 3-х лет | M3: ПДЗ отсутствовала | O3: Строительство | Q3: Отсутствуют | R3: 0 | S3: Наличие судебных разбирательств с ГК ГПН | T3: 50 | X3: AAA | Y3: 10 | Z3: 10 | AD3: Рост | AE3: 3 | AG3: более 10%
A4: 62-63 | C4: Средний | E4: Включен в реестр | G4: B | I4: Да, контрагент ликвидирован | K4: от 1 до 3-х лет | M4: Техническая ПДЗ | O4: Добыча, переработка и транспортировка газа, нефти и нефтепродуктов | Q4: 1 претензия | R4: 5 | S4: Приняты решения суда в пользу ГК ГПН | T4: 70 | X4: AA+ | Y4: 8 | Z4: 8 | AD4: Снижение | AE4: -3 | AG4: не более 10%
A5: 06, 49.5, 09, 19.2 | C5: Высокий | E5: Информация отсутствует | G5: C | I5: Да, контрагент находится в состоянии банкротства | K5: менее 1 года | M5: Разовая ПДЗ продолжительностью менее 30 дней | O5: Транспортировка и хранение | Q5: 2-3 претензии | R5: 15 | S5: Отсутствуют | T5: 0 | X5: AA | Y5: 8 | Z5: 8 | AD5: На прежнем уровне | AE5: 0 | AG5: Информация отсутствует
A6: 49-53, за искл. 49.5, 51, 50 | C6: Информация отсутствует | I6: Да, отрицательные Чистые активы за последние 2 года | K6: отсутствует | M6: Разовая ПДЗ продолжительностью более 30 дней | O6: Торговля | Q6: 4-6 претензии | R6: 30 | X6: AA- | Y6: 8 | Z6: 8 | AD6: Нет данных | AE6: 0
A7: 45-47 | M7: Неоднократное возникновение ПДЗ | O7: Производство | Q7: 7 и более претензий | R7: 50 | X7: A+ | Y7: 5 | Z7: 5
A8: 10-33, 35, за искл.19.2 | M8: Наличие проблем по взысканию задолженности с контрагента (судебные разбирательства, исполнительное производство) | O8: Авиакомпания | X8: A | Y8: 5 | Z8: 5
A9: 51 | M9: Информация отсутствует | O9: Судовладелец | X9: A- | Y9: 5 | Z9: 5
A10: 50 | O10: Прочие | X10: BBB+ | Y10: 3 | Z10: 3
O11: ИТ | X11: BBB | Y11: 3 | Z11: 3
X12: BBB- | Y12: 3 | Z12: 3
X13: BB+ | Y13: 0 | Z13: 0
X14: BB | Y14: 0 | Z14: 0
A15: РСБУ | E15: МСФО | X15: BB- | Y15: 0 | Z15: 0
A16: Текущий период точка | E16: Текущий период точка | X16: B+ | Y16: -3 | Z16: -6
A17: ось X | B17: ось Y | E17: ось X | F17: ось Y | X17: B | Y17: -3 | Z17: -6
A18: 1 | B18: =IF(A18=$A$28,$A$29,"") -> 2 | E18: 1 | F18: =IF(E18=$E$28,$E$29,"") -> 1 | X18: B- | Y18: -3 | Z18: -6
A19: 2 | B19: =IF(A19=$A$28,$A$29,"") | E19: 2 | F19: =IF(E19=$E$28,$E$29,"") | X19: CCC+ | Y19: -5 | Z19: -12
A20: 3 | B20: =IF(A20=$A$28,$A$29,"") | E20: 3 | F20: =IF(E20=$E$28,$E$29,"") | X20: CCC | Y20: -5 | Z20: -12
A21: 4 | B21: =IF(A21=$A$28,$A$29,"") | E21: 4 | F21: =IF(E21=$E$28,$E$29,"") | X21: CCC- | Y21: -5 | Z21: -12
X22: CC+ | Y22: -8 | Z22: -18
A23: Мэппинг | E23: Мэппинг | X23: CC | Y23: -8 | Z23: -18
A24: A | B24: 3 | E24: A | F24: 3 | X24: CC- | Y24: -8 | Z24: -18
A25: B | B25: 2 | E25: B | F25: 2 | X25: C | Y25: -10 | Z25: -25
A26: C | B26: 1 | E26: C | F26: 1 | X26: C- | Y26: -10 | Z26: -25
X27: NR | Y27: 0 | Z27: 0
A28: ='РСБУ расчет лимита'!J60 -> 1 | E28: ='МСФО расчет лимита'!$J$57 -> 1 | X28: Нет данных | Y28: 0 | Z28: 0
A29: =INDEX(B24:B26,MATCH('РСБУ расчет лимита'!J61,Подложка!A24:A26,0)) -> 2 | E29: =INDEX(F24:F26,MATCH('МСФО расчет лимита'!$J$58,Подложка!E24:E26,0)) -> 1
C32: Коды ОКВЭД 41-43, 71 | H32: Коды ОКВЭД 06, 49.5, 09, 19.2 | M32: Коды ОКВЭД 49-53, за искл. 49.5, 51, 50 | R32: Коды ОКВЭД 45-47 | W32: Коды ОКВЭД 05, 07-08, 10-33, 35, за искл.19.2 | AB32: Коды ОКВЭД 51 | AG32: Коды ОКВЭД 50 | AL32: Остальные коды ОКВЭД | AQ32: Коды ОКВЭД 62-63
A33: № | B33: ФИНАНСОВЫЕ ПОКАЗАТЕЛИ | C33: Строительство | H33: Добыча, переработка и транспортировка газа, нефти и нефтепродуктов | M33: Транспортировка и хранение | R33: Торговля | W33: Производство | AB33: Авиакомпания | AG33: Судовладелец | AL33: Прочие | AQ33: ИТ
B34: Кол-во баллов | C34: 40 | D34: 70 | E34: 100 | H34: 40 | I34: 70 | J34: 100 | M34: 40 | N34: 70 | O34: 100 | R34: 40 | S34: 70 | T34: 100 | W34: 40 | X34: 70 | Y34: 100 | AB34: 40 | AC34: 70 | AD34: 100 | AG34: 40 | AH34: 70 | AI34: 100 | AL34: 40 | AM34: 70 | AN34: 100 | AQ34: 40 | AR34: 70 | AS34: 100
A35: 1.1 | B35: Коэффициент текущей ликвидности | C35: 1 | D35: 1.4 | E35: 2.2 | H35: 0.9 | I35: 1.3 | J35: 2.2 | M35: 0.8 | N35: 1.2 | O35: 2 | R35: 1.1 | S35: 1.5 | T35: 2.4 | W35: 1 | X35: 1.5 | Y35: 2.6 | AB35: 1 | AC35: 1.9 | AD35: 3.2 | AG35: 0.7 | AH35: 1.3 | AI35: 2.5 | AL35: 1 | AM35: 1.6 | AN35: 3.4 | AQ35: 1.1 | AR35: 1.9 | AS35: 3.4
A36: 1.2 | B36: Коэффициент быстрой ликвидности | C36: 0.7 | D36: 1.1 | E36: 1.7 | H36: 0.6 | I36: 1 | J36: 1.7 | M36: 0.6 | N36: 1.1 | O36: 1.7 | R36: 0.5 | S36: 0.9 | T36: 1.4 | W36: 0.5 | X36: 0.9 | Y36: 1.5 | AB36: 0.7 | AC36: 1.4 | AD36: 2.7 | AG36: 0.5 | AH36: 1 | AI36: 1.8 | AL36: 0.7 | AM36: 1.2 | AN36: 2.5 | AQ36: 0.8 | AR36: 1.3 | AS36: 2.7
A37: 1.3 | B37: Длительность операционного цикла | C37: 80 | D37: 30 | E37: 0 | H37: 90 | I37: 35 | J37: 0 | M37: 50 | N37: 20 | O37: 0 | R37: 60 | S37: 30 | T37: 5 | W37: 120 | X37: 50 | Y37: 2 | AB37: 95 | AC37: 30 | AD37: 0 | AG37: 70 | AH37: 20 | AI37: 0 | AL37: 70 | AM37: 20 | AN37: 0 | AQ37: 85 | AR37: 25 | AS37: 0
A38: 1.4 | B38: Коэффициент автономии | C38: 0.1 | D38: 0.4 | E38: 0.6 | H38: 0.1 | I38: 0.4 | J38: 0.7 | M38: 0.1 | N38: 0.3 | O38: 0.6 | R38: 0.1 | S38: 0.3 | T38: 0.6 | W38: 0.2 | X38: 0.4 | Y38: 0.7 | AB38: 0.1 | AC38: 0.4 | AD38: 0.8 | AG38: 0.1 | AH38: 0.3 | AI38: 0.7 | AL38: 0.2 | AM38: 0.5 | AN38: 0.8 | AQ38: 0.2 | AR38: 0.5 | AS38: 0.8
A39: 1.5 | B39: Рентабельность продаж | C39: 2 | D39: 6 | E39: 13 | H39: 1 | I39: 6 | J39: 13 | M39: 1 | N39: 5 | O39: 11 | R39: 1 | S39: 3 | T39: 6 | W39: 2 | X39: 7 | Y39: 15 | AB39: 0 | AC39: 4 | AD39: 12 | AG39: 0 | AH39: 4 | AI39: 17 | AL39: 2 | AM39: 9 | AN39: 22 | AQ39: 2 | AR39: 10 | AS39: 19
A40: 1.6 | B40: Коэффициент долговой нагрузки | C40: 1.1 | D40: 0.3 | E40: 0 | H40: 3.3 | I40: 1.3 | J40: 0 | M40: 2.5 | N40: 0.8 | O40: 0.2 | R40: 3.7 | S40: 1.5 | T40: 0.3 | W40: 2.7 | X40: 0.9 | Y40: 0.1 | AB40: 0.9 | AC40: 0.3 | AD40: 0 | AG40: 1.6 | AH40: 0.3 | AI40: 0 | AL40: 0.9 | AM40: 0.3 | AN40: 0 | AQ40: 1.5 | AR40: 0.2 | AS40: 0
A41: 1.7 | B41: Коэффициент покрытия процентов | C41: 1.2 | D41: 3.2 | E41: 11.5 | H41: 0.5 | I41: 2.2 | J41: 8.1 | M41: 1.1 | N41: 2 | O41: 4.9 | R41: 0.9 | S41: 1.6 | T41: 4.4 | W41: 1.1 | X41: 2.8 | Y41: 9.2 | AB41: 1.1 | AC41: 2.6 | AD41: 5.9 | AG41: 0 | AH41: 1.4 | AI41: 4.9 | AL41: 0.8 | AM41: 2.5 | AN41: 9.3 | AQ41: 0.5 | AR41: 3.1 | AS41: 18.2
A42: 1.8 | B42: Коэффициент маневренности | C42: -0.1 | D42: 0.2 | E42: 0.5 | H42: -0.4 | I42: 0 | J42: 0.4 | M42: -0.6 | N42: 0 | O42: 0.4 | R42: 0 | S42: 0.2 | T42: 0.5 | W42: -0.2 | X42: 0.2 | Y42: 0.6 | AB42: -0.6 | AC42: 0.1 | AD42: 0.6 | AG42: -0.7 | AH42: 0 | AI42: 0.4 | AL42: -0.2 | AM42: 0.3 | AN42: 0.7 | AQ42: 0.1 | AR42: 0.4 | AS42: 0.7
A43: 1.9 | B43: Рентабельность капитала | C43: 4 | D43: 19 | E43: 43 | H43: 1 | I43: 10 | J43: 26 | M43: 5 | N43: 15 | O43: 30 | R43: 6 | S43: 20 | T43: 43 | W43: 5 | X43: 15 | Y43: 32 | AB43: 1 | AC43: 12 | AD43: 42 | AG43: 2 | AH43: 14 | AI43: 39 | AL43: 3 | AM43: 16 | AN43: 45 | AQ43: 4 | AR43: 24 | AS43: 66
A44: Период 2 | F44: Порог | G44: Балл | K44: Порог | L44: Балл | P44: Порог | Q44: Балл | U44: Порог | V44: Балл | Z44: Порог | AA44: Балл | AE44: Порог | AF44: Балл | AJ44: Порог | AK44: Балл | AO44: Порог | AP44: Балл | AT44: Порог | AU44: Балл
A45: 1.1 | B45: Коэффициент текущей ликвидности | C45: =IF('РСБУ отчетность'!$E$79>=Подложка!C35,1,0) -> 1 | D45: =IF('РСБУ отчетность'!$E$79>=Подложка!D35,1,0) -> 1 | E45: =IF('РСБУ отчетность'!$E$79>=Подложка!E35,1,0) -> 1 | F45: =SUM(C45:E45) -> 3 | G45: =IF(F45=3,100,IF(F45=2,70,IF(F45=1,40,0))) -> 100 | H45: =IF('РСБУ отчетность'!$E$79>=Подложка!H35,1,0) -> 1 | I45: =IF('РСБУ отчетность'!$E$79>=Подложка!I35,1,0) -> 1 | J45: =IF('РСБУ отчетность'!$E$79>=Подложка!J35,1,0) -> 1 | K45: =SUM(H45:J45) -> 3 | L45: =IF(K45=3,100,IF(K45=2,70,IF(K45=1,40,0))) -> 100 | M45: =IF('РСБУ отчетность'!$E$79>=Подложка!M35,1,0) -> 1 | N45: =IF('РСБУ отчетность'!$E$79>=Подложка!N35,1,0) -> 1 | O45: =IF('РСБУ отчетность'!$E$79>=Подложка!O35,1,0) -> 1 | P45: =SUM(M45:O45) -> 3 | Q45: =IF(P45=3,100,IF(P45=2,70,IF(P45=1,40,0))) -> 100 | R45: =IF('РСБУ отчетность'!$E$79>=Подложка!R35,1,0) -> 1 | S45: =IF('РСБУ отчетность'!$E$79>=Подложка!S35,1,0) -> 1 | T45: =IF('РСБУ отчетность'!$E$79>=Подложка!T35,1,0) -> 1 | U45: =SUM(R45:T45) -> 3 | V45: =IF(U45=3,100,IF(U45=2,70,IF(U45=1,40,0))) -> 100 | W45: =IF('РСБУ отчетность'!$E$79>=Подложка!W35,1,0) -> 1 | X45: =IF('РСБУ отчетность'!$E$79>=Подложка!X35,1,0) -> 1 | Y45: =IF('РСБУ отчетность'!$E$79>=Подложка!Y35,1,0) -> 1 | Z45: =SUM(W45:Y45) -> 3 | AA45: =IF(Z45=3,100,IF(Z45=2,70,IF(Z45=1,40,0))) -> 100 | AB45: =IF('РСБУ отчетность'!$E$79>=Подложка!AB35,1,0) -> 1 | AC45: =IF('РСБУ отчетность'!$E$79>=Подложка!AC35,1,0) -> 1 | AD45: =IF('РСБУ отчетность'!$E$79>=Подложка!AD35,1,0) -> 1 | AE45: =SUM(AB45:AD45) -> 3 | AF45: =IF(AE45=3,100,IF(AE45=2,70,IF(AE45=1,40,0))) -> 100 | AG45: =IF('РСБУ отчетность'!$E$79>=Подложка!AG35,1,0) -> 1 | AH45: =IF('РСБУ отчетность'!$E$79>=Подложка!AH35,1,0) -> 1 | AI45: =IF('РСБУ отчетность'!$E$79>=Подложка!AI35,1,0) -> 1 | AJ45: =SUM(AG45:AI45) -> 3 | AK45: =IF(AJ45=3,100,IF(AJ45=2,70,IF(AJ45=1,40,0))) -> 100 | AL45: =IF('РСБУ отчетность'!$E$79>=Подложка!AL35,1,0) -> 1 | AM45: =IF('РСБУ отчетность'!$E$79>=Подложка!AM35,1,0) -> 1 | AN45: =IF('РСБУ отчетность'!$E$79>=Подложка!AN35,1,0) -> 0 | AO45: =SUM(AL45:AN45) -> 2 | AP45: =IF(AO45=3,100,IF(AO45=2,70,IF(AO45=1,40,0))) -> 70 | AQ45: =IF('РСБУ отчетность'!$E$79>=Подложка!AQ35,1,0) -> 1 | AR45: =IF('РСБУ отчетность'!$E$79>=Подложка!AR35,1,0) -> 1 | AS45: =IF('РСБУ отчетность'!$E$79>=Подложка!AS35,1,0) -> 0 | AT45: =SUM(AQ45:AS45) -> 2 | AU45: =IF(AT45=3,100,IF(AT45=2,70,IF(AT45=1,40,0))) -> 70
A46: 1.2 | B46: Коэффициент быстрой ликвидности | C46: =IF('РСБУ отчетность'!$E$80>=Подложка!C36,1,0) -> 1 | D46: =IF('РСБУ отчетность'!$E$80>=Подложка!D36,1,0) -> 1 | E46: =IF('РСБУ отчетность'!$E$80>=Подложка!E36,1,0) -> 1 | F46: =SUM(C46:E46) -> 3 | G46: =IF(F46=3,100,IF(F46=2,70,IF(F46=1,40,0))) -> 100 | H46: =IF('РСБУ отчетность'!$E$80>=Подложка!H36,1,0) -> 1 | I46: =IF('РСБУ отчетность'!$E$80>=Подложка!I36,1,0) -> 1 | J46: =IF('РСБУ отчетность'!$E$80>=Подложка!J36,1,0) -> 1 | K46: =SUM(H46:J46) -> 3 | L46: =IF(K46=3,100,IF(K46=2,70,IF(K46=1,40,0))) -> 100 | M46: =IF('РСБУ отчетность'!$E$80>=Подложка!M36,1,0) -> 1 | N46: =IF('РСБУ отчетность'!$E$80>=Подложка!N36,1,0) -> 1 | O46: =IF('РСБУ отчетность'!$E$80>=Подложка!O36,1,0) -> 1 | P46: =SUM(M46:O46) -> 3 | Q46: =IF(P46=3,100,IF(P46=2,70,IF(P46=1,40,0))) -> 100 | R46: =IF('РСБУ отчетность'!$E$80>=Подложка!R36,1,0) -> 1 | S46: =IF('РСБУ отчетность'!$E$80>=Подложка!S36,1,0) -> 1 | T46: =IF('РСБУ отчетность'!$E$80>=Подложка!T36,1,0) -> 1 | U46: =SUM(R46:T46) -> 3 | V46: =IF(U46=3,100,IF(U46=2,70,IF(U46=1,40,0))) -> 100 | W46: =IF('РСБУ отчетность'!$E$80>=Подложка!W36,1,0) -> 1 | X46: =IF('РСБУ отчетность'!$E$80>=Подложка!X36,1,0) -> 1 | Y46: =IF('РСБУ отчетность'!$E$80>=Подложка!Y36,1,0) -> 1 | Z46: =SUM(W46:Y46) -> 3 | AA46: =IF(Z46=3,100,IF(Z46=2,70,IF(Z46=1,40,0))) -> 100 | AB46: =IF('РСБУ отчетность'!$E$80>=Подложка!AB36,1,0) -> 1 | AC46: =IF('РСБУ отчетность'!$E$80>=Подложка!AC36,1,0) -> 1 | AD46: =IF('РСБУ отчетность'!$E$80>=Подложка!AD36,1,0) -> 0 | AE46: =SUM(AB46:AD46) -> 2 | AF46: =IF(AE46=3,100,IF(AE46=2,70,IF(AE46=1,40,0))) -> 70 | AG46: =IF('РСБУ отчетность'!$E$80>=Подложка!AG36,1,0) -> 1 | AH46: =IF('РСБУ отчетность'!$E$80>=Подложка!AH36,1,0) -> 1 | AI46: =IF('РСБУ отчетность'!$E$80>=Подложка!AI36,1,0) -> 0 | AJ46: =SUM(AG46:AI46) -> 2 | AK46: =IF(AJ46=3,100,IF(AJ46=2,70,IF(AJ46=1,40,0))) -> 70 | AL46: =IF('РСБУ отчетность'!$E$80>=Подложка!AL36,1,0) -> 1 | AM46: =IF('РСБУ отчетность'!$E$80>=Подложка!AM36,1,0) -> 1 | AN46: =IF('РСБУ отчетность'!$E$80>=Подложка!AN36,1,0) -> 0 | AO46: =SUM(AL46:AN46) -> 2 | AP46: =IF(AO46=3,100,IF(AO46=2,70,IF(AO46=1,40,0))) -> 70 | AQ46: =IF('РСБУ отчетность'!$E$80>=Подложка!AQ36,1,0) -> 1 | AR46: =IF('РСБУ отчетность'!$E$80>=Подложка!AR36,1,0) -> 1 | AS46: =IF('РСБУ отчетность'!$E$80>=Подложка!AS36,1,0) -> 0 | AT46: =SUM(AQ46:AS46) -> 2 | AU46: =IF(AT46=3,100,IF(AT46=2,70,IF(AT46=1,40,0))) -> 70
A47: 1.3 | B47: Длительность операционного цикла | C47: =IF('РСБУ отчетность'!$E$81<Подложка!C37,1,0) -> 0 | D47: =IF('РСБУ отчетность'!$E$81<=Подложка!D37,1,0) -> 0 | E47: =IF('РСБУ отчетность'!$E$81<Подложка!E37,1,0) -> 0 | F47: =SUM(C47:E47) -> 0 | G47: =IF(F47=3,100,IF(F47=2,70,IF(F47=1,40,0))) -> 0 | H47: =IF('РСБУ отчетность'!$E$81<Подложка!H37,1,0) -> 0 | I47: =IF('РСБУ отчетность'!$E$81<=Подложка!I37,1,0) -> 0 | J47: =IF('РСБУ отчетность'!$E$81<Подложка!J37,1,0) -> 0 | K47: =SUM(H47:J47) -> 0 | L47: =IF(K47=3,100,IF(K47=2,70,IF(K47=1,40,0))) -> 0 | M47: =IF('РСБУ отчетность'!$E$81<Подложка!M37,1,0) -> 0 | N47: =IF('РСБУ отчетность'!$E$81<=Подложка!N37,1,0) -> 0 | O47: =IF('РСБУ отчетность'!$E$81<Подложка!O37,1,0) -> 0 | P47: =SUM(M47:O47) -> 0 | Q47: =IF(P47=3,100,IF(P47=2,70,IF(P47=1,40,0))) -> 0 | R47: =IF('РСБУ отчетность'!$E$81<Подложка!R37,1,0) -> 0 | S47: =IF('РСБУ отчетность'!$E$81<=Подложка!S37,1,0) -> 0 | T47: =IF('РСБУ отчетность'!$E$81<Подложка!T37,1,0) -> 0 | U47: =SUM(R47:T47) -> 0 | V47: =IF(U47=3,100,IF(U47=2,70,IF(U47=1,40,0))) -> 0 | W47: =IF('РСБУ отчетность'!$E$81<Подложка!W37,1,0) -> 0 | X47: =IF('РСБУ отчетность'!$E$81<=Подложка!X37,1,0) -> 0 | Y47: =IF('РСБУ отчетность'!$E$81<Подложка!Y37,1,0) -> 0 | Z47: =SUM(W47:Y47) -> 0 | AA47: =IF(Z47=3,100,IF(Z47=2,70,IF(Z47=1,40,0))) -> 0 | AB47: =IF('РСБУ отчетность'!$E$81<Подложка!AB37,1,0) -> 0 | AC47: =IF('РСБУ отчетность'!$E$81<=Подложка!AC37,1,0) -> 0 | AD47: =IF('РСБУ отчетность'!$E$81<Подложка!AD37,1,0) -> 0 | AE47: =SUM(AB47:AD47) -> 0 | AF47: =IF(AE47=3,100,IF(AE47=2,70,IF(AE47=1,40,0))) -> 0 | AG47: =IF('РСБУ отчетность'!$E$81<Подложка!AG37,1,0) -> 0 | AH47: =IF('РСБУ отчетность'!$E$81<=Подложка!AH37,1,0) -> 0 | AI47: =IF('РСБУ отчетность'!$E$81<Подложка!AI37,1,0) -> 0 | AJ47: =SUM(AG47:AI47) -> 0 | AK47: =IF(AJ47=3,100,IF(AJ47=2,70,IF(AJ47=1,40,0))) -> 0 | AL47: =IF('РСБУ отчетность'!$E$81<Подложка!AL37,1,0) -> 0 | AM47: =IF('РСБУ отчетность'!$E$81<=Подложка!AM37,1,0) -> 0 | AN47: =IF('РСБУ отчетность'!$E$81<Подложка!AN37,1,0) -> 0 | AO47: =SUM(AL47:AN47) -> 0 | AP47: =IF(AO47=3,100,IF(AO47=2,70,IF(AO47=1,40,0))) -> 0 | AQ47: =IF('РСБУ отчетность'!$E$81<Подложка!AQ37,1,0) -> 0 | AR47: =IF('РСБУ отчетность'!$E$81<=Подложка!AR37,1,0) -> 0 | AS47: =IF('РСБУ отчетность'!$E$81<Подложка!AS37,1,0) -> 0 | AT47: =SUM(AQ47:AS47) -> 0 | AU47: =IF(AT47=3,100,IF(AT47=2,70,IF(AT47=1,40,0))) -> 0
A48: 1.4 | B48: Коэффициент автономии | C48: =IF('РСБУ отчетность'!$E$82>=Подложка!C38,1,0) -> 1 | D48: =IF('РСБУ отчетность'!$E$82>=Подложка!D38,1,0) -> 1 | E48: =IF('РСБУ отчетность'!$E$82>=Подложка!E38,1,0) -> 1 | F48: =SUM(C48:E48) -> 3 | G48: =IF(F48=3,100,IF(F48=2,70,IF(F48=1,40,0))) -> 100 | H48: =IF('РСБУ отчетность'!$E$82>=Подложка!H38,1,0) -> 1 | I48: =IF('РСБУ отчетность'!$E$82>=Подложка!I38,1,0) -> 1 | J48: =IF('РСБУ отчетность'!$E$82>=Подложка!J38,1,0) -> 1 | K48: =SUM(H48:J48) -> 3 | L48: =IF(K48=3,100,IF(K48=2,70,IF(K48=1,40,0))) -> 100 | M48: =IF('РСБУ отчетность'!$E$82>=Подложка!M38,1,0) -> 1 | N48: =IF('РСБУ отчетность'!$E$82>=Подложка!N38,1,0) -> 1 | O48: =IF('РСБУ отчетность'!$E$82>=Подложка!O38,1,0) -> 1 | P48: =SUM(M48:O48) -> 3 | Q48: =IF(P48=3,100,IF(P48=2,70,IF(P48=1,40,0))) -> 100 | R48: =IF('РСБУ отчетность'!$E$82>=Подложка!R38,1,0) -> 1 | S48: =IF('РСБУ отчетность'!$E$82>=Подложка!S38,1,0) -> 1 | T48: =IF('РСБУ отчетность'!$E$82>=Подложка!T38,1,0) -> 1 | U48: =SUM(R48:T48) -> 3 | V48: =IF(U48=3,100,IF(U48=2,70,IF(U48=1,40,0))) -> 100 | W48: =IF('РСБУ отчетность'!$E$82>=Подложка!W38,1,0) -> 1 | X48: =IF('РСБУ отчетность'!$E$82>=Подложка!X38,1,0) -> 1 | Y48: =IF('РСБУ отчетность'!$E$82>=Подложка!Y38,1,0) -> 1 | Z48: =SUM(W48:Y48) -> 3 | AA48: =IF(Z48=3,100,IF(Z48=2,70,IF(Z48=1,40,0))) -> 100 | AB48: =IF('РСБУ отчетность'!$E$82>=Подложка!AB38,1,0) -> 1 | AC48: =IF('РСБУ отчетность'!$E$82>=Подложка!AC38,1,0) -> 1 | AD48: =IF('РСБУ отчетность'!$E$82>=Подложка!AD38,1,0) -> 0 | AE48: =SUM(AB48:AD48) -> 2 | AF48: =IF(AE48=3,100,IF(AE48=2,70,IF(AE48=1,40,0))) -> 70 | AG48: =IF('РСБУ отчетность'!$E$82>=Подложка!AG38,1,0) -> 1 | AH48: =IF('РСБУ отчетность'!$E$82>=Подложка!AH38,1,0) -> 1 | AI48: =IF('РСБУ отчетность'!$E$82>=Подложка!AI38,1,0) -> 1 | AJ48: =SUM(AG48:AI48) -> 3 | AK48: =IF(AJ48=3,100,IF(AJ48=2,70,IF(AJ48=1,40,0))) -> 100 | AL48: =IF('РСБУ отчетность'!$E$82>=Подложка!AL38,1,0) -> 1 | AM48: =IF('РСБУ отчетность'!$E$82>=Подложка!AM38,1,0) -> 1 | AN48: =IF('РСБУ отчетность'!$E$82>=Подложка!AN38,1,0) -> 0 | AO48: =SUM(AL48:AN48) -> 2 | AP48: =IF(AO48=3,100,IF(AO48=2,70,IF(AO48=1,40,0))) -> 70 | AQ48: =IF('РСБУ отчетность'!$E$82>=Подложка!AQ38,1,0) -> 1 | AR48: =IF('РСБУ отчетность'!$E$82>=Подложка!AR38,1,0) -> 1 | AS48: =IF('РСБУ отчетность'!$E$82>=Подложка!AS38,1,0) -> 0 | AT48: =SUM(AQ48:AS48) -> 2 | AU48: =IF(AT48=3,100,IF(AT48=2,70,IF(AT48=1,40,0))) -> 70
A49: 1.5 | B49: Рентабельность продаж | C49: =IF('РСБУ отчетность'!$E$83>=Подложка!C39,1,0) -> 1 | D49: =IF('РСБУ отчетность'!$E$83>=Подложка!D39,1,0) -> 1 | E49: =IF('РСБУ отчетность'!$E$83>=Подложка!E39,1,0) -> 0 | F49: =SUM(C49:E49) -> 2 | G49: =IF(F49=3,100,IF(F49=2,70,IF(F49=1,40,0))) -> 70 | H49: =IF('РСБУ отчетность'!$E$83>=Подложка!H39,1,0) -> 1 | I49: =IF('РСБУ отчетность'!$E$83>=Подложка!I39,1,0) -> 1 | J49: =IF('РСБУ отчетность'!$E$83>=Подложка!J39,1,0) -> 0 | K49: =SUM(H49:J49) -> 2 | L49: =IF(K49=3,100,IF(K49=2,70,IF(K49=1,40,0))) -> 70 | M49: =IF('РСБУ отчетность'!$E$83>=Подложка!M39,1,0) -> 1 | N49: =IF('РСБУ отчетность'!$E$83>=Подложка!N39,1,0) -> 1 | O49: =IF('РСБУ отчетность'!$E$83>=Подложка!O39,1,0) -> 0 | P49: =SUM(M49:O49) -> 2 | Q49: =IF(P49=3,100,IF(P49=2,70,IF(P49=1,40,0))) -> 70 | R49: =IF('РСБУ отчетность'!$E$83>=Подложка!R39,1,0) -> 1 | S49: =IF('РСБУ отчетность'!$E$83>=Подложка!S39,1,0) -> 1 | T49: =IF('РСБУ отчетность'!$E$83>=Подложка!T39,1,0) -> 1 | U49: =SUM(R49:T49) -> 3 | V49: =IF(U49=3,100,IF(U49=2,70,IF(U49=1,40,0))) -> 100 | W49: =IF('РСБУ отчетность'!$E$83>=Подложка!W39,1,0) -> 1 | X49: =IF('РСБУ отчетность'!$E$83>=Подложка!X39,1,0) -> 1 | Y49: =IF('РСБУ отчетность'!$E$83>=Подложка!Y39,1,0) -> 0 | Z49: =SUM(W49:Y49) -> 2 | AA49: =IF(Z49=3,100,IF(Z49=2,70,IF(Z49=1,40,0))) -> 70 | AB49: =IF('РСБУ отчетность'!$E$83>=Подложка!AB39,1,0) -> 1 | AC49: =IF('РСБУ отчетность'!$E$83>=Подложка!AC39,1,0) -> 1 | AD49: =IF('РСБУ отчетность'!$E$83>=Подложка!AD39,1,0) -> 0 | AE49: =SUM(AB49:AD49) -> 2 | AF49: =IF(AE49=3,100,IF(AE49=2,70,IF(AE49=1,40,0))) -> 70 | AG49: =IF('РСБУ отчетность'!$E$83>=Подложка!AG39,1,0) -> 1 | AH49: =IF('РСБУ отчетность'!$E$83>=Подложка!AH39,1,0) -> 1 | AI49: =IF('РСБУ отчетность'!$E$83>=Подложка!AI39,1,0) -> 0 | AJ49: =SUM(AG49:AI49) -> 2 | AK49: =IF(AJ49=3,100,IF(AJ49=2,70,IF(AJ49=1,40,0))) -> 70 | AL49: =IF('РСБУ отчетность'!$E$83>=Подложка!AL39,1,0) -> 1 | AM49: =IF('РСБУ отчетность'!$E$83>=Подложка!AM39,1,0) -> 1 | AN49: =IF('РСБУ отчетность'!$E$83>=Подложка!AN39,1,0) -> 0 | AO49: =SUM(AL49:AN49) -> 2 | AP49: =IF(AO49=3,100,IF(AO49=2,70,IF(AO49=1,40,0))) -> 70 | AQ49: =IF('РСБУ отчетность'!$E$83>=Подложка!AQ39,1,0) -> 1 | AR49: =IF('РСБУ отчетность'!$E$83>=Подложка!AR39,1,0) -> 0 | AS49: =IF('РСБУ отчетность'!$E$83>=Подложка!AS39,1,0) -> 0 | AT49: =SUM(AQ49:AS49) -> 1 | AU49: =IF(AT49=3,100,IF(AT49=2,70,IF(AT49=1,40,0))) -> 40
A50: 1.6 | B50: Коэффициент долговой нагрузки | C50: =IF('РСБУ отчетность'!$E$84<Подложка!C40,1,0) -> 1 | D50: =IF('РСБУ отчетность'!$E$84<Подложка!D40,1,0) -> 0 | E50: =IF('РСБУ отчетность'!$E$84<Подложка!E40,1,0) -> 0 | F50: =SUM(C50:E50) -> 1 | G50: =IF(F50=3,100,IF(F50=2,70,IF(F50=1,40,0))) -> 40 | H50: =IF('РСБУ отчетность'!$E$84<Подложка!H40,1,0) -> 1 | I50: =IF('РСБУ отчетность'!$E$84<Подложка!I40,1,0) -> 1 | J50: =IF('РСБУ отчетность'!$E$84<Подложка!J40,1,0) -> 0 | K50: =SUM(H50:J50) -> 2 | L50: =IF(K50=3,100,IF(K50=2,70,IF(K50=1,40,0))) -> 70 | M50: =IF('РСБУ отчетность'!$E$84<Подложка!M40,1,0) -> 1 | N50: =IF('РСБУ отчетность'!$E$84<Подложка!N40,1,0) -> 1 | O50: =IF('РСБУ отчетность'!$E$84<Подложка!O40,1,0) -> 0 | P50: =SUM(M50:O50) -> 2 | Q50: =IF(P50=3,100,IF(P50=2,70,IF(P50=1,40,0))) -> 70 | R50: =IF('РСБУ отчетность'!$E$84<Подложка!R40,1,0) -> 1 | S50: =IF('РСБУ отчетность'!$E$84<Подложка!S40,1,0) -> 1 | T50: =IF('РСБУ отчетность'!$E$84<Подложка!T40,1,0) -> 0 | U50: =SUM(R50:T50) -> 2 | V50: =IF(U50=3,100,IF(U50=2,70,IF(U50=1,40,0))) -> 70 | W50: =IF('РСБУ отчетность'!$E$84<Подложка!W40,1,0) -> 1 | X50: =IF('РСБУ отчетность'!$E$84<Подложка!X40,1,0) -> 1 | Y50: =IF('РСБУ отчетность'!$E$84<Подложка!Y40,1,0) -> 0 | Z50: =SUM(W50:Y50) -> 2 | AA50: =IF(Z50=3,100,IF(Z50=2,70,IF(Z50=1,40,0))) -> 70 | AB50: =IF('РСБУ отчетность'!$E$84<Подложка!AB40,1,0) -> 1 | AC50: =IF('РСБУ отчетность'!$E$84<Подложка!AC40,1,0) -> 0 | AD50: =IF('РСБУ отчетность'!$E$84<Подложка!AD40,1,0) -> 0 | AE50: =SUM(AB50:AD50) -> 1 | AF50: =IF(AE50=3,100,IF(AE50=2,70,IF(AE50=1,40,0))) -> 40 | AG50: =IF('РСБУ отчетность'!$E$84<Подложка!AG40,1,0) -> 1 | AH50: =IF('РСБУ отчетность'!$E$84<Подложка!AH40,1,0) -> 0 | AI50: =IF('РСБУ отчетность'!$E$84<Подложка!AI40,1,0) -> 0 | AJ50: =SUM(AG50:AI50) -> 1 | AK50: =IF(AJ50=3,100,IF(AJ50=2,70,IF(AJ50=1,40,0))) -> 40 | AL50: =IF('РСБУ отчетность'!$E$84<Подложка!AL40,1,0) -> 1 | AM50: =IF('РСБУ отчетность'!$E$84<Подложка!AM40,1,0) -> 0 | AN50: =IF('РСБУ отчетность'!$E$84<Подложка!AN40,1,0) -> 0 | AO50: =SUM(AL50:AN50) -> 1 | AP50: =IF(AO50=3,100,IF(AO50=2,70,IF(AO50=1,40,0))) -> 40 | AQ50: =IF('РСБУ отчетность'!$E$84<Подложка!AQ40,1,0) -> 1 | AR50: =IF('РСБУ отчетность'!$E$84<Подложка!AR40,1,0) -> 0 | AS50: =IF('РСБУ отчетность'!$E$84<Подложка!AS40,1,0) -> 0 | AT50: =SUM(AQ50:AS50) -> 1 | AU50: =IF(AT50=3,100,IF(AT50=2,70,IF(AT50=1,40,0))) -> 40
A51: 1.7 | B51: Коэффициент покрытия процентов | C51: =IF('РСБУ отчетность'!$E$85>=Подложка!C41,1,0) -> 1 | D51: =IF('РСБУ отчетность'!$E$85>=Подложка!D41,1,0) -> 1 | E51: =IF('РСБУ отчетность'!$E$85>=Подложка!E41,1,0) -> 1 | F51: =SUM(C51:E51) -> 3 | G51: =IF(F51=3,100,IF(F51=2,70,IF(F51=1,40,0))) -> 100 | H51: =IF('РСБУ отчетность'!$E$85>=Подложка!H41,1,0) -> 1 | I51: =IF('РСБУ отчетность'!$E$85>=Подложка!I41,1,0) -> 1 | J51: =IF('РСБУ отчетность'!$E$85>=Подложка!J41,1,0) -> 1 | K51: =SUM(H51:J51) -> 3 | L51: =IF(K51=3,100,IF(K51=2,70,IF(K51=1,40,0))) -> 100 | M51: =IF('РСБУ отчетность'!$E$85>=Подложка!M41,1,0) -> 1 | N51: =IF('РСБУ отчетность'!$E$85>=Подложка!N41,1,0) -> 1 | O51: =IF('РСБУ отчетность'!$E$85>=Подложка!O41,1,0) -> 1 | P51: =SUM(M51:O51) -> 3 | Q51: =IF(P51=3,100,IF(P51=2,70,IF(P51=1,40,0))) -> 100 | R51: =IF('РСБУ отчетность'!$E$85>=Подложка!R41,1,0) -> 1 | S51: =IF('РСБУ отчетность'!$E$85>=Подложка!S41,1,0) -> 1 | T51: =IF('РСБУ отчетность'!$E$85>=Подложка!T41,1,0) -> 1 | U51: =SUM(R51:T51) -> 3 | V51: =IF(U51=3,100,IF(U51=2,70,IF(U51=1,40,0))) -> 100 | W51: =IF('РСБУ отчетность'!$E$85>=Подложка!W41,1,0) -> 1 | X51: =IF('РСБУ отчетность'!$E$85>=Подложка!X41,1,0) -> 1 | Y51: =IF('РСБУ отчетность'!$E$85>=Подложка!Y41,1,0) -> 1 | Z51: =SUM(W51:Y51) -> 3 | AA51: =IF(Z51=3,100,IF(Z51=2,70,IF(Z51=1,40,0))) -> 100 | AB51: =IF('РСБУ отчетность'!$E$85>=Подложка!AB41,1,0) -> 1 | AC51: =IF('РСБУ отчетность'!$E$85>=Подложка!AC41,1,0) -> 1 | AD51: =IF('РСБУ отчетность'!$E$85>=Подложка!AD41,1,0) -> 1 | AE51: =SUM(AB51:AD51) -> 3 | AF51: =IF(AE51=3,100,IF(AE51=2,70,IF(AE51=1,40,0))) -> 100 | AG51: =IF('РСБУ отчетность'!$E$85>=Подложка!AG41,1,0) -> 1 | AH51: =IF('РСБУ отчетность'!$E$85>=Подложка!AH41,1,0) -> 1 | AI51: =IF('РСБУ отчетность'!$E$85>=Подложка!AI41,1,0) -> 1 | AJ51: =SUM(AG51:AI51) -> 3 | AK51: =IF(AJ51=3,100,IF(AJ51=2,70,IF(AJ51=1,40,0))) -> 100 | AL51: =IF('РСБУ отчетность'!$E$85>=Подложка!AL41,1,0) -> 1 | AM51: =IF('РСБУ отчетность'!$E$85>=Подложка!AM41,1,0) -> 1 | AN51: =IF('РСБУ отчетность'!$E$85>=Подложка!AN41,1,0) -> 1 | AO51: =SUM(AL51:AN51) -> 3 | AP51: =IF(AO51=3,100,IF(AO51=2,70,IF(AO51=1,40,0))) -> 100 | AQ51: =IF('РСБУ отчетность'!$E$85>=Подложка!AQ41,1,0) -> 1 | AR51: =IF('РСБУ отчетность'!$E$85>=Подложка!AR41,1,0) -> 1 | AS51: =IF('РСБУ отчетность'!$E$85>=Подложка!AS41,1,0) -> 1 | AT51: =SUM(AQ51:AS51) -> 3 | AU51: =IF(AT51=3,100,IF(AT51=2,70,IF(AT51=1,40,0))) -> 100
A52: 1.8 | B52: Коэффициент маневренности | C52: =IF('РСБУ отчетность'!$E$86>=Подложка!C42,1,0) -> 1 | D52: =IF('РСБУ отчетность'!$E$86>=Подложка!D42,1,0) -> 1 | E52: =IF('РСБУ отчетность'!$E$86>=Подложка!E42,1,0) -> 1 | F52: =SUM(C52:E52) -> 3 | G52: =IF(F52=3,100,IF(F52=2,70,IF(F52=1,40,0))) -> 100 | H52: =IF('РСБУ отчетность'!$E$86>=Подложка!H42,1,0) -> 1 | I52: =IF('РСБУ отчетность'!$E$86>=Подложка!I42,1,0) -> 1 | J52: =IF('РСБУ отчетность'!$E$86>=Подложка!J42,1,0) -> 1 | K52: =SUM(H52:J52) -> 3 | L52: =IF(K52=3,100,IF(K52=2,70,IF(K52=1,40,0))) -> 100 | M52: =IF('РСБУ отчетность'!$E$86>=Подложка!M42,1,0) -> 1 | N52: =IF('РСБУ отчетность'!$E$86>=Подложка!N42,1,0) -> 1 | O52: =IF('РСБУ отчетность'!$E$86>=Подложка!O42,1,0) -> 1 | P52: =SUM(M52:O52) -> 3 | Q52: =IF(P52=3,100,IF(P52=2,70,IF(P52=1,40,0))) -> 100 | R52: =IF('РСБУ отчетность'!$E$86>=Подложка!R42,1,0) -> 1 | S52: =IF('РСБУ отчетность'!$E$86>=Подложка!S42,1,0) -> 1 | T52: =IF('РСБУ отчетность'!$E$86>=Подложка!T42,1,0) -> 1 | U52: =SUM(R52:T52) -> 3 | V52: =IF(U52=3,100,IF(U52=2,70,IF(U52=1,40,0))) -> 100 | W52: =IF('РСБУ отчетность'!$E$86>=Подложка!W42,1,0) -> 1 | X52: =IF('РСБУ отчетность'!$E$86>=Подложка!X42,1,0) -> 1 | Y52: =IF('РСБУ отчетность'!$E$86>=Подложка!Y42,1,0) -> 1 | Z52: =SUM(W52:Y52) -> 3 | AA52: =IF(Z52=3,100,IF(Z52=2,70,IF(Z52=1,40,0))) -> 100 | AB52: =IF('РСБУ отчетность'!$E$86>=Подложка!AB42,1,0) -> 1 | AC52: =IF('РСБУ отчетность'!$E$86>=Подложка!AC42,1,0) -> 1 | AD52: =IF('РСБУ отчетность'!$E$86>=Подложка!AD42,1,0) -> 1 | AE52: =SUM(AB52:AD52) -> 3 | AF52: =IF(AE52=3,100,IF(AE52=2,70,IF(AE52=1,40,0))) -> 100 | AG52: =IF('РСБУ отчетность'!$E$86>=Подложка!AG42,1,0) -> 1 | AH52: =IF('РСБУ отчетность'!$E$86>=Подложка!AH42,1,0) -> 1 | AI52: =IF('РСБУ отчетность'!$E$86>=Подложка!AI42,1,0) -> 1 | AJ52: =SUM(AG52:AI52) -> 3 | AK52: =IF(AJ52=3,100,IF(AJ52=2,70,IF(AJ52=1,40,0))) -> 100 | AL52: =IF('РСБУ отчетность'!$E$86>=Подложка!AL42,1,0) -> 1 | AM52: =IF('РСБУ отчетность'!$E$86>=Подложка!AM42,1,0) -> 1 | AN52: =IF('РСБУ отчетность'!$E$86>=Подложка!AN42,1,0) -> 0 | AO52: =SUM(AL52:AN52) -> 2 | AP52: =IF(AO52=3,100,IF(AO52=2,70,IF(AO52=1,40,0))) -> 70 | AQ52: =IF('РСБУ отчетность'!$E$86>=Подложка!AQ42,1,0) -> 1 | AR52: =IF('РСБУ отчетность'!$E$86>=Подложка!AR42,1,0) -> 1 | AS52: =IF('РСБУ отчетность'!$E$86>=Подложка!AS42,1,0) -> 0 | AT52: =SUM(AQ52:AS52) -> 2 | AU52: =IF(AT52=3,100,IF(AT52=2,70,IF(AT52=1,40,0))) -> 70
A53: 1.9 | B53: Рентабельность капитала | C53: =IF('РСБУ отчетность'!$E$87>=Подложка!C43,1,0) -> 1 | D53: =IF('РСБУ отчетность'!$E$87>=Подложка!D43,1,0) -> 1 | E53: =IF('РСБУ отчетность'!$E$87>=Подложка!E43,1,0) -> 0 | F53: =SUM(C53:E53) -> 2 | G53: =IF(F53=3,100,IF(F53=2,70,IF(F53=1,40,0))) -> 70 | H53: =IF('РСБУ отчетность'!$E$87>=Подложка!H43,1,0) -> 1 | I53: =IF('РСБУ отчетность'!$E$87>=Подложка!I43,1,0) -> 1 | J53: =IF('РСБУ отчетность'!$E$87>=Подложка!J43,1,0) -> 1 | K53: =SUM(H53:J53) -> 3 | L53: =IF(K53=3,100,IF(K53=2,70,IF(K53=1,40,0))) -> 100 | M53: =IF('РСБУ отчетность'!$E$87>=Подложка!M43,1,0) -> 1 | N53: =IF('РСБУ отчетность'!$E$87>=Подложка!N43,1,0) -> 1 | O53: =IF('РСБУ отчетность'!$E$87>=Подложка!O43,1,0) -> 0 | P53: =SUM(M53:O53) -> 2 | Q53: =IF(P53=3,100,IF(P53=2,70,IF(P53=1,40,0))) -> 70 | R53: =IF('РСБУ отчетность'!$E$87>=Подложка!R43,1,0) -> 1 | S53: =IF('РСБУ отчетность'!$E$87>=Подложка!S43,1,0) -> 1 | T53: =IF('РСБУ отчетность'!$E$87>=Подложка!T43,1,0) -> 0 | U53: =SUM(R53:T53) -> 2 | V53: =IF(U53=3,100,IF(U53=2,70,IF(U53=1,40,0))) -> 70 | W53: =IF('РСБУ отчетность'!$E$87>=Подложка!W43,1,0) -> 1 | X53: =IF('РСБУ отчетность'!$E$87>=Подложка!X43,1,0) -> 1 | Y53: =IF('РСБУ отчетность'!$E$87>=Подложка!Y43,1,0) -> 0 | Z53: =SUM(W53:Y53) -> 2 | AA53: =IF(Z53=3,100,IF(Z53=2,70,IF(Z53=1,40,0))) -> 70 | AB53: =IF('РСБУ отчетность'!$E$87>=Подложка!AB43,1,0) -> 1 | AC53: =IF('РСБУ отчетность'!$E$87>=Подложка!AC43,1,0) -> 1 | AD53: =IF('РСБУ отчетность'!$E$87>=Подложка!AD43,1,0) -> 0 | AE53: =SUM(AB53:AD53) -> 2 | AF53: =IF(AE53=3,100,IF(AE53=2,70,IF(AE53=1,40,0))) -> 70 | AG53: =IF('РСБУ отчетность'!$E$87>=Подложка!AG43,1,0) -> 1 | AH53: =IF('РСБУ отчетность'!$E$87>=Подложка!AH43,1,0) -> 1 | AI53: =IF('РСБУ отчетность'!$E$87>=Подложка!AI43,1,0) -> 0 | AJ53: =SUM(AG53:AI53) -> 2 | AK53: =IF(AJ53=3,100,IF(AJ53=2,70,IF(AJ53=1,40,0))) -> 70 | AL53: =IF('РСБУ отчетность'!$E$87>=Подложка!AL43,1,0) -> 1 | AM53: =IF('РСБУ отчетность'!$E$87>=Подложка!AM43,1,0) -> 1 | AN53: =IF('РСБУ отчетность'!$E$87>=Подложка!AN43,1,0) -> 0 | AO53: =SUM(AL53:AN53) -> 2 | AP53: =IF(AO53=3,100,IF(AO53=2,70,IF(AO53=1,40,0))) -> 70 | AQ53: =IF('РСБУ отчетность'!$E$87>=Подложка!AQ43,1,0) -> 1 | AR53: =IF('РСБУ отчетность'!$E$87>=Подложка!AR43,1,0) -> 1 | AS53: =IF('РСБУ отчетность'!$E$87>=Подложка!AS43,1,0) -> 0 | AT53: =SUM(AQ53:AS53) -> 2 | AU53: =IF(AT53=3,100,IF(AT53=2,70,IF(AT53=1,40,0))) -> 70
A54: Период 1 | F54: Порог | G54: Балл | K54: Порог | L54: Балл | P54: Порог | Q54: Балл | U54: Порог | V54: Балл | Z54: Порог | AA54: Балл | AE54: Порог | AF54: Балл | AJ54: Порог | AK54: Балл | AO54: Порог | AP54: Балл | AT54: Порог | AU54: Балл
A55: 1.1 | B55: Коэффициент текущей ликвидности | C55: =IF('РСБУ отчетность'!$F$79>=Подложка!C35,1,0) -> 1 | D55: =IF('РСБУ отчетность'!$F$79>=Подложка!D35,1,0) -> 1 | E55: =IF('РСБУ отчетность'!$F$79>=Подложка!E35,1,0) -> 1 | F55: =SUM(C55:E55) -> 3 | G55: =IF(F55=3,100,IF(F55=2,70,IF(F55=1,40,0))) -> 100 | H55: =IF('РСБУ отчетность'!$F$79>=Подложка!H35,1,0) -> 1 | I55: =IF('РСБУ отчетность'!$F$79>=Подложка!I35,1,0) -> 1 | J55: =IF('РСБУ отчетность'!$F$79>=Подложка!J35,1,0) -> 1 | K55: =SUM(H55:J55) -> 3 | L55: =IF(K55=3,100,IF(K55=2,70,IF(K55=1,40,0))) -> 100 | M55: =IF('РСБУ отчетность'!$F$79>=Подложка!M35,1,0) -> 1 | N55: =IF('РСБУ отчетность'!$F$79>=Подложка!N35,1,0) -> 1 | O55: =IF('РСБУ отчетность'!$F$79>=Подложка!O35,1,0) -> 1 | P55: =SUM(M55:O55) -> 3 | Q55: =IF(P55=3,100,IF(P55=2,70,IF(P55=1,40,0))) -> 100 | R55: =IF('РСБУ отчетность'!$F$79>=Подложка!R35,1,0) -> 1 | S55: =IF('РСБУ отчетность'!$F$79>=Подложка!S35,1,0) -> 1 | T55: =IF('РСБУ отчетность'!$F$79>=Подложка!T35,1,0) -> 1 | U55: =SUM(R55:T55) -> 3 | V55: =IF(U55=3,100,IF(U55=2,70,IF(U55=1,40,0))) -> 100 | W55: =IF('РСБУ отчетность'!$F$79>=Подложка!W35,1,0) -> 1 | X55: =IF('РСБУ отчетность'!$F$79>=Подложка!X35,1,0) -> 1 | Y55: =IF('РСБУ отчетность'!$F$79>=Подложка!Y35,1,0) -> 1 | Z55: =SUM(W55:Y55) -> 3 | AA55: =IF(Z55=3,100,IF(Z55=2,70,IF(Z55=1,40,0))) -> 100 | AB55: =IF('РСБУ отчетность'!$F$79>=Подложка!AB35,1,0) -> 1 | AC55: =IF('РСБУ отчетность'!$F$79>=Подложка!AC35,1,0) -> 1 | AD55: =IF('РСБУ отчетность'!$F$79>=Подложка!AD35,1,0) -> 0 | AE55: =SUM(AB55:AD55) -> 2 | AF55: =IF(AE55=3,100,IF(AE55=2,70,IF(AE55=1,40,0))) -> 70 | AG55: =IF('РСБУ отчетность'!$F$79>=Подложка!AG35,1,0) -> 1 | AH55: =IF('РСБУ отчетность'!$F$79>=Подложка!AH35,1,0) -> 1 | AI55: =IF('РСБУ отчетность'!$F$79>=Подложка!AI35,1,0) -> 1 | AJ55: =SUM(AG55:AI55) -> 3 | AK55: =IF(AJ55=3,100,IF(AJ55=2,70,IF(AJ55=1,40,0))) -> 100 | AL55: =IF('РСБУ отчетность'!$F$79>=Подложка!AL35,1,0) -> 1 | AM55: =IF('РСБУ отчетность'!$F$79>=Подложка!AM35,1,0) -> 1 | AN55: =IF('РСБУ отчетность'!$F$79>=Подложка!AN35,1,0) -> 0 | AO55: =SUM(AL55:AN55) -> 2 | AP55: =IF(AO55=3,100,IF(AO55=2,70,IF(AO55=1,40,0))) -> 70 | AQ55: =IF('РСБУ отчетность'!$F$79>=Подложка!AQ35,1,0) -> 1 | AR55: =IF('РСБУ отчетность'!$F$79>=Подложка!AR35,1,0) -> 1 | AS55: =IF('РСБУ отчетность'!$F$79>=Подложка!AS35,1,0) -> 0 | AT55: =SUM(AQ55:AS55) -> 2 | AU55: =IF(AT55=3,100,IF(AT55=2,70,IF(AT55=1,40,0))) -> 70
A56: 1.2 | B56: Коэффициент быстрой ликвидности | C56: =IF('РСБУ отчетность'!$F$80>=Подложка!C36,1,0) -> 1 | D56: =IF('РСБУ отчетность'!$F$80>=Подложка!D36,1,0) -> 1 | E56: =IF('РСБУ отчетность'!$F$80>=Подложка!E36,1,0) -> 1 | F56: =SUM(C56:E56) -> 3 | G56: =IF(F56=3,100,IF(F56=2,70,IF(F56=1,40,0))) -> 100 | H56: =IF('РСБУ отчетность'!$F$80>=Подложка!H36,1,0) -> 1 | I56: =IF('РСБУ отчетность'!$F$80>=Подложка!I36,1,0) -> 1 | J56: =IF('РСБУ отчетность'!$F$80>=Подложка!J36,1,0) -> 1 | K56: =SUM(H56:J56) -> 3 | L56: =IF(K56=3,100,IF(K56=2,70,IF(K56=1,40,0))) -> 100 | M56: =IF('РСБУ отчетность'!$F$80>=Подложка!M36,1,0) -> 1 | N56: =IF('РСБУ отчетность'!$F$80>=Подложка!N36,1,0) -> 1 | O56: =IF('РСБУ отчетность'!$F$80>=Подложка!O36,1,0) -> 1 | P56: =SUM(M56:O56) -> 3 | Q56: =IF(P56=3,100,IF(P56=2,70,IF(P56=1,40,0))) -> 100 | R56: =IF('РСБУ отчетность'!$F$80>=Подложка!R36,1,0) -> 1 | S56: =IF('РСБУ отчетность'!$F$80>=Подложка!S36,1,0) -> 1 | T56: =IF('РСБУ отчетность'!$F$80>=Подложка!T36,1,0) -> 1 | U56: =SUM(R56:T56) -> 3 | V56: =IF(U56=3,100,IF(U56=2,70,IF(U56=1,40,0))) -> 100 | W56: =IF('РСБУ отчетность'!$F$80>=Подложка!W36,1,0) -> 1 | X56: =IF('РСБУ отчетность'!$F$80>=Подложка!X36,1,0) -> 1 | Y56: =IF('РСБУ отчетность'!$F$80>=Подложка!Y36,1,0) -> 1 | Z56: =SUM(W56:Y56) -> 3 | AA56: =IF(Z56=3,100,IF(Z56=2,70,IF(Z56=1,40,0))) -> 100 | AB56: =IF('РСБУ отчетность'!$F$80>=Подложка!AB36,1,0) -> 1 | AC56: =IF('РСБУ отчетность'!$F$80>=Подложка!AC36,1,0) -> 1 | AD56: =IF('РСБУ отчетность'!$F$80>=Подложка!AD36,1,0) -> 0 | AE56: =SUM(AB56:AD56) -> 2 | AF56: =IF(AE56=3,100,IF(AE56=2,70,IF(AE56=1,40,0))) -> 70 | AG56: =IF('РСБУ отчетность'!$F$80>=Подложка!AG36,1,0) -> 1 | AH56: =IF('РСБУ отчетность'!$F$80>=Подложка!AH36,1,0) -> 1 | AI56: =IF('РСБУ отчетность'!$F$80>=Подложка!AI36,1,0) -> 0 | AJ56: =SUM(AG56:AI56) -> 2 | AK56: =IF(AJ56=3,100,IF(AJ56=2,70,IF(AJ56=1,40,0))) -> 70 | AL56: =IF('РСБУ отчетность'!$F$80>=Подложка!AL36,1,0) -> 1 | AM56: =IF('РСБУ отчетность'!$F$80>=Подложка!AM36,1,0) -> 1 | AN56: =IF('РСБУ отчетность'!$F$80>=Подложка!AN36,1,0) -> 0 | AO56: =SUM(AL56:AN56) -> 2 | AP56: =IF(AO56=3,100,IF(AO56=2,70,IF(AO56=1,40,0))) -> 70 | AQ56: =IF('РСБУ отчетность'!$F$80>=Подложка!AQ36,1,0) -> 1 | AR56: =IF('РСБУ отчетность'!$F$80>=Подложка!AR36,1,0) -> 1 | AS56: =IF('РСБУ отчетность'!$F$80>=Подложка!AS36,1,0) -> 0 | AT56: =SUM(AQ56:AS56) -> 2 | AU56: =IF(AT56=3,100,IF(AT56=2,70,IF(AT56=1,40,0))) -> 70
A57: 1.3 | B57: Длительность операционного цикла | C57: =IF('РСБУ отчетность'!$F$81<Подложка!C37,1,0) -> 0 | D57: =IF('РСБУ отчетность'!$F$81<Подложка!D37,1,0) -> 0 | E57: =IF('РСБУ отчетность'!$F$81<Подложка!E37,1,0) -> 0 | F57: =SUM(C57:E57) -> 0 | G57: =IF(F57=3,100,IF(F57=2,70,IF(F57=1,40,0))) -> 0 | H57: =IF('РСБУ отчетность'!$F$81<Подложка!H37,1,0) -> 0 | I57: =IF('РСБУ отчетность'!$F$81<Подложка!I37,1,0) -> 0 | J57: =IF('РСБУ отчетность'!$F$81<Подложка!J37,1,0) -> 0 | K57: =SUM(H57:J57) -> 0 | L57: =IF(K57=3,100,IF(K57=2,70,IF(K57=1,40,0))) -> 0 | M57: =IF('РСБУ отчетность'!$F$81<Подложка!M37,1,0) -> 0 | N57: =IF('РСБУ отчетность'!$F$81<Подложка!N37,1,0) -> 0 | O57: =IF('РСБУ отчетность'!$F$81<Подложка!O37,1,0) -> 0 | P57: =SUM(M57:O57) -> 0 | Q57: =IF(P57=3,100,IF(P57=2,70,IF(P57=1,40,0))) -> 0 | R57: =IF('РСБУ отчетность'!$F$81<Подложка!R37,1,0) -> 0 | S57: =IF('РСБУ отчетность'!$F$81<Подложка!S37,1,0) -> 0 | T57: =IF('РСБУ отчетность'!$F$81<Подложка!T37,1,0) -> 0 | U57: =SUM(R57:T57) -> 0 | V57: =IF(U57=3,100,IF(U57=2,70,IF(U57=1,40,0))) -> 0 | W57: =IF('РСБУ отчетность'!$F$81<Подложка!W37,1,0) -> 0 | X57: =IF('РСБУ отчетность'!$F$81<Подложка!X37,1,0) -> 0 | Y57: =IF('РСБУ отчетность'!$F$81<Подложка!Y37,1,0) -> 0 | Z57: =SUM(W57:Y57) -> 0 | AA57: =IF(Z57=3,100,IF(Z57=2,70,IF(Z57=1,40,0))) -> 0 | AB57: =IF('РСБУ отчетность'!$F$81<Подложка!AB37,1,0) -> 0 | AC57: =IF('РСБУ отчетность'!$F$81<Подложка!AC37,1,0) -> 0 | AD57: =IF('РСБУ отчетность'!$F$81<Подложка!AD37,1,0) -> 0 | AE57: =SUM(AB57:AD57) -> 0 | AF57: =IF(AE57=3,100,IF(AE57=2,70,IF(AE57=1,40,0))) -> 0 | AG57: =IF('РСБУ отчетность'!$F$81<Подложка!AG37,1,0) -> 0 | AH57: =IF('РСБУ отчетность'!$F$81<Подложка!AH37,1,0) -> 0 | AI57: =IF('РСБУ отчетность'!$F$81<Подложка!AI37,1,0) -> 0 | AJ57: =SUM(AG57:AI57) -> 0 | AK57: =IF(AJ57=3,100,IF(AJ57=2,70,IF(AJ57=1,40,0))) -> 0 | AL57: =IF('РСБУ отчетность'!$F$81<Подложка!AL37,1,0) -> 0 | AM57: =IF('РСБУ отчетность'!$F$81<Подложка!AM37,1,0) -> 0 | AN57: =IF('РСБУ отчетность'!$F$81<Подложка!AN37,1,0) -> 0 | AO57: =SUM(AL57:AN57) -> 0 | AP57: =IF(AO57=3,100,IF(AO57=2,70,IF(AO57=1,40,0))) -> 0 | AQ57: =IF('РСБУ отчетность'!$F$81<Подложка!AQ37,1,0) -> 0 | AR57: =IF('РСБУ отчетность'!$F$81<Подложка!AR37,1,0) -> 0 | AS57: =IF('РСБУ отчетность'!$F$81<Подложка!AS37,1,0) -> 0 | AT57: =SUM(AQ57:AS57) -> 0 | AU57: =IF(AT57=3,100,IF(AT57=2,70,IF(AT57=1,40,0))) -> 0
A58: 1.4 | B58: Коэффициент автономии | C58: =IF('РСБУ отчетность'!$F$82>=Подложка!C38,1,0) -> 1 | D58: =IF('РСБУ отчетность'!$F$82>=Подложка!D38,1,0) -> 1 | E58: =IF('РСБУ отчетность'!$F$82>=Подложка!E38,1,0) -> 1 | F58: =SUM(C58:E58) -> 3 | G58: =IF(F58=3,100,IF(F58=2,70,IF(F58=1,40,0))) -> 100 | H58: =IF('РСБУ отчетность'!$F$82>=Подложка!H38,1,0) -> 1 | I58: =IF('РСБУ отчетность'!$F$82>=Подложка!I38,1,0) -> 1 | J58: =IF('РСБУ отчетность'!$F$82>=Подложка!J38,1,0) -> 0 | K58: =SUM(H58:J58) -> 2 | L58: =IF(K58=3,100,IF(K58=2,70,IF(K58=1,40,0))) -> 70 | M58: =IF('РСБУ отчетность'!$F$82>=Подложка!M38,1,0) -> 1 | N58: =IF('РСБУ отчетность'!$F$82>=Подложка!N38,1,0) -> 1 | O58: =IF('РСБУ отчетность'!$F$82>=Подложка!O38,1,0) -> 1 | P58: =SUM(M58:O58) -> 3 | Q58: =IF(P58=3,100,IF(P58=2,70,IF(P58=1,40,0))) -> 100 | R58: =IF('РСБУ отчетность'!$F$82>=Подложка!R38,1,0) -> 1 | S58: =IF('РСБУ отчетность'!$F$82>=Подложка!S38,1,0) -> 1 | T58: =IF('РСБУ отчетность'!$F$82>=Подложка!T38,1,0) -> 1 | U58: =SUM(R58:T58) -> 3 | V58: =IF(U58=3,100,IF(U58=2,70,IF(U58=1,40,0))) -> 100 | W58: =IF('РСБУ отчетность'!$F$82>=Подложка!W38,1,0) -> 1 | X58: =IF('РСБУ отчетность'!$F$82>=Подложка!X38,1,0) -> 1 | Y58: =IF('РСБУ отчетность'!$F$82>=Подложка!Y38,1,0) -> 0 | Z58: =SUM(W58:Y58) -> 2 | AA58: =IF(Z58=3,100,IF(Z58=2,70,IF(Z58=1,40,0))) -> 70 | AB58: =IF('РСБУ отчетность'!$F$82>=Подложка!AB38,1,0) -> 1 | AC58: =IF('РСБУ отчетность'!$F$82>=Подложка!AC38,1,0) -> 1 | AD58: =IF('РСБУ отчетность'!$F$82>=Подложка!AD38,1,0) -> 0 | AE58: =SUM(AB58:AD58) -> 2 | AF58: =IF(AE58=3,100,IF(AE58=2,70,IF(AE58=1,40,0))) -> 70 | AG58: =IF('РСБУ отчетность'!$F$82>=Подложка!AG38,1,0) -> 1 | AH58: =IF('РСБУ отчетность'!$F$82>=Подложка!AH38,1,0) -> 1 | AI58: =IF('РСБУ отчетность'!$F$82>=Подложка!AI38,1,0) -> 0 | AJ58: =SUM(AG58:AI58) -> 2 | AK58: =IF(AJ58=3,100,IF(AJ58=2,70,IF(AJ58=1,40,0))) -> 70 | AL58: =IF('РСБУ отчетность'!$F$82>=Подложка!AL38,1,0) -> 1 | AM58: =IF('РСБУ отчетность'!$F$82>=Подложка!AM38,1,0) -> 1 | AN58: =IF('РСБУ отчетность'!$F$82>=Подложка!AN38,1,0) -> 0 | AO58: =SUM(AL58:AN58) -> 2 | AP58: =IF(AO58=3,100,IF(AO58=2,70,IF(AO58=1,40,0))) -> 70 | AQ58: =IF('РСБУ отчетность'!$F$82>=Подложка!AQ38,1,0) -> 1 | AR58: =IF('РСБУ отчетность'!$F$82>=Подложка!AR38,1,0) -> 1 | AS58: =IF('РСБУ отчетность'!$F$82>=Подложка!AS38,1,0) -> 0 | AT58: =SUM(AQ58:AS58) -> 2 | AU58: =IF(AT58=3,100,IF(AT58=2,70,IF(AT58=1,40,0))) -> 70
A59: 1.5 | B59: Рентабельность продаж | C59: =IF('РСБУ отчетность'!$F$83>=Подложка!C39,1,0) -> 1 | D59: =IF('РСБУ отчетность'!$F$83>=Подложка!D39,1,0) -> 1 | E59: =IF('РСБУ отчетность'!$F$83>=Подложка!E39,1,0) -> 1 | F59: =SUM(C59:E59) -> 3 | G59: =IF(F59=3,100,IF(F59=2,70,IF(F59=1,40,0))) -> 100 | H59: =IF('РСБУ отчетность'!$F$83>=Подложка!H39,1,0) -> 1 | I59: =IF('РСБУ отчетность'!$F$83>=Подложка!I39,1,0) -> 1 | J59: =IF('РСБУ отчетность'!$F$83>=Подложка!J39,1,0) -> 1 | K59: =SUM(H59:J59) -> 3 | L59: =IF(K59=3,100,IF(K59=2,70,IF(K59=1,40,0))) -> 100 | M59: =IF('РСБУ отчетность'!$F$83>=Подложка!M39,1,0) -> 1 | N59: =IF('РСБУ отчетность'!$F$83>=Подложка!N39,1,0) -> 1 | O59: =IF('РСБУ отчетность'!$F$83>=Подложка!O39,1,0) -> 1 | P59: =SUM(M59:O59) -> 3 | Q59: =IF(P59=3,100,IF(P59=2,70,IF(P59=1,40,0))) -> 100 | R59: =IF('РСБУ отчетность'!$F$83>=Подложка!R39,1,0) -> 1 | S59: =IF('РСБУ отчетность'!$F$83>=Подложка!S39,1,0) -> 1 | T59: =IF('РСБУ отчетность'!$F$83>=Подложка!T39,1,0) -> 1 | U59: =SUM(R59:T59) -> 3 | V59: =IF(U59=3,100,IF(U59=2,70,IF(U59=1,40,0))) -> 100 | W59: =IF('РСБУ отчетность'!$F$83>=Подложка!W39,1,0) -> 1 | X59: =IF('РСБУ отчетность'!$F$83>=Подложка!X39,1,0) -> 1 | Y59: =IF('РСБУ отчетность'!$F$83>=Подложка!Y39,1,0) -> 1 | Z59: =SUM(W59:Y59) -> 3 | AA59: =IF(Z59=3,100,IF(Z59=2,70,IF(Z59=1,40,0))) -> 100 | AB59: =IF('РСБУ отчетность'!$F$83>=Подложка!AB39,1,0) -> 1 | AC59: =IF('РСБУ отчетность'!$F$83>=Подложка!AC39,1,0) -> 1 | AD59: =IF('РСБУ отчетность'!$F$83>=Подложка!AD39,1,0) -> 1 | AE59: =SUM(AB59:AD59) -> 3 | AF59: =IF(AE59=3,100,IF(AE59=2,70,IF(AE59=1,40,0))) -> 100 | AG59: =IF('РСБУ отчетность'!$F$83>=Подложка!AG39,1,0) -> 1 | AH59: =IF('РСБУ отчетность'!$F$83>=Подложка!AH39,1,0) -> 1 | AI59: =IF('РСБУ отчетность'!$F$83>=Подложка!AI39,1,0) -> 1 | AJ59: =SUM(AG59:AI59) -> 3 | AK59: =IF(AJ59=3,100,IF(AJ59=2,70,IF(AJ59=1,40,0))) -> 100 | AL59: =IF('РСБУ отчетность'!$F$83>=Подложка!AL39,1,0) -> 1 | AM59: =IF('РСБУ отчетность'!$F$83>=Подложка!AM39,1,0) -> 1 | AN59: =IF('РСБУ отчетность'!$F$83>=Подложка!AN39,1,0) -> 0 | AO59: =SUM(AL59:AN59) -> 2 | AP59: =IF(AO59=3,100,IF(AO59=2,70,IF(AO59=1,40,0))) -> 70 | AQ59: =IF('РСБУ отчетность'!$F$83>=Подложка!AQ39,1,0) -> 1 | AR59: =IF('РСБУ отчетность'!$F$83>=Подложка!AR39,1,0) -> 1 | AS59: =IF('РСБУ отчетность'!$F$83>=Подложка!AS39,1,0) -> 1 | AT59: =SUM(AQ59:AS59) -> 3 | AU59: =IF(AT59=3,100,IF(AT59=2,70,IF(AT59=1,40,0))) -> 100
A60: 1.6 | B60: Коэффициент долговой нагрузки | C60: =IF('РСБУ отчетность'!$F$84<Подложка!C40,1,0) -> 1 | D60: =IF('РСБУ отчетность'!$F$84<Подложка!D40,1,0) -> 1 | E60: =IF('РСБУ отчетность'!$F$84<Подложка!E40,1,0) -> 0 | F60: =SUM(C60:E60) -> 2 | G60: =IF(F60=3,100,IF(F60=2,70,IF(F60=1,40,0))) -> 70 | H60: =IF('РСБУ отчетность'!$F$84<Подложка!H40,1,0) -> 1 | I60: =IF('РСБУ отчетность'!$F$84<Подложка!I40,1,0) -> 1 | J60: =IF('РСБУ отчетность'!$F$84<Подложка!J40,1,0) -> 0 | K60: =SUM(H60:J60) -> 2 | L60: =IF(K60=3,100,IF(K60=2,70,IF(K60=1,40,0))) -> 70 | M60: =IF('РСБУ отчетность'!$F$84<Подложка!M40,1,0) -> 1 | N60: =IF('РСБУ отчетность'!$F$84<Подложка!N40,1,0) -> 1 | O60: =IF('РСБУ отчетность'!$F$84<Подложка!O40,1,0) -> 1 | P60: =SUM(M60:O60) -> 3 | Q60: =IF(P60=3,100,IF(P60=2,70,IF(P60=1,40,0))) -> 100 | R60: =IF('РСБУ отчетность'!$F$84<Подложка!R40,1,0) -> 1 | S60: =IF('РСБУ отчетность'!$F$84<Подложка!S40,1,0) -> 1 | T60: =IF('РСБУ отчетность'!$F$84<Подложка!T40,1,0) -> 1 | U60: =SUM(R60:T60) -> 3 | V60: =IF(U60=3,100,IF(U60=2,70,IF(U60=1,40,0))) -> 100 | W60: =IF('РСБУ отчетность'!$F$84<Подложка!W40,1,0) -> 1 | X60: =IF('РСБУ отчетность'!$F$84<Подложка!X40,1,0) -> 1 | Y60: =IF('РСБУ отчетность'!$F$84<Подложка!Y40,1,0) -> 0 | Z60: =SUM(W60:Y60) -> 2 | AA60: =IF(Z60=3,100,IF(Z60=2,70,IF(Z60=1,40,0))) -> 70 | AB60: =IF('РСБУ отчетность'!$F$84<Подложка!AB40,1,0) -> 1 | AC60: =IF('РСБУ отчетность'!$F$84<Подложка!AC40,1,0) -> 1 | AD60: =IF('РСБУ отчетность'!$F$84<Подложка!AD40,1,0) -> 0 | AE60: =SUM(AB60:AD60) -> 2 | AF60: =IF(AE60=3,100,IF(AE60=2,70,IF(AE60=1,40,0))) -> 70 | AG60: =IF('РСБУ отчетность'!$F$84<Подложка!AG40,1,0) -> 1 | AH60: =IF('РСБУ отчетность'!$F$84<Подложка!AH40,1,0) -> 1 | AI60: =IF('РСБУ отчетность'!$F$84<Подложка!AI40,1,0) -> 0 | AJ60: =SUM(AG60:AI60) -> 2 | AK60: =IF(AJ60=3,100,IF(AJ60=2,70,IF(AJ60=1,40,0))) -> 70 | AL60: =IF('РСБУ отчетность'!$F$84<Подложка!AL40,1,0) -> 1 | AM60: =IF('РСБУ отчетность'!$F$84<Подложка!AM40,1,0) -> 1 | AN60: =IF('РСБУ отчетность'!$F$84<Подложка!AN40,1,0) -> 0 | AO60: =SUM(AL60:AN60) -> 2 | AP60: =IF(AO60=3,100,IF(AO60=2,70,IF(AO60=1,40,0))) -> 70 | AQ60: =IF('РСБУ отчетность'!$F$84<Подложка!AQ40,1,0) -> 1 | AR60: =IF('РСБУ отчетность'!$F$84<Подложка!AR40,1,0) -> 1 | AS60: =IF('РСБУ отчетность'!$F$84<Подложка!AS40,1,0) -> 0 | AT60: =SUM(AQ60:AS60) -> 2 | AU60: =IF(AT60=3,100,IF(AT60=2,70,IF(AT60=1,40,0))) -> 70
A61: 1.7 | B61: Коэффициент покрытия процентов | C61: =IF('РСБУ отчетность'!$F$85>=Подложка!C41,1,0) -> 1 | D61: =IF('РСБУ отчетность'!$F$85>=Подложка!D41,1,0) -> 1 | E61: =IF('РСБУ отчетность'!$F$85>=Подложка!E41,1,0) -> 1 | F61: =SUM(C61:E61) -> 3 | G61: =IF(F61=3,100,IF(F61=2,70,IF(F61=1,40,0))) -> 100 | H61: =IF('РСБУ отчетность'!$F$85>=Подложка!H41,1,0) -> 1 | I61: =IF('РСБУ отчетность'!$F$85>=Подложка!I41,1,0) -> 1 | J61: =IF('РСБУ отчетность'!$F$85>=Подложка!J41,1,0) -> 1 | K61: =SUM(H61:J61) -> 3 | L61: =IF(K61=3,100,IF(K61=2,70,IF(K61=1,40,0))) -> 100 | M61: =IF('РСБУ отчетность'!$F$85>=Подложка!M41,1,0) -> 1 | N61: =IF('РСБУ отчетность'!$F$85>=Подложка!N41,1,0) -> 1 | O61: =IF('РСБУ отчетность'!$F$85>=Подложка!O41,1,0) -> 1 | P61: =SUM(M61:O61) -> 3 | Q61: =IF(P61=3,100,IF(P61=2,70,IF(P61=1,40,0))) -> 100 | R61: =IF('РСБУ отчетность'!$F$85>=Подложка!R41,1,0) -> 1 | S61: =IF('РСБУ отчетность'!$F$85>=Подложка!S41,1,0) -> 1 | T61: =IF('РСБУ отчетность'!$F$85>=Подложка!T41,1,0) -> 1 | U61: =SUM(R61:T61) -> 3 | V61: =IF(U61=3,100,IF(U61=2,70,IF(U61=1,40,0))) -> 100 | W61: =IF('РСБУ отчетность'!$F$85>=Подложка!W41,1,0) -> 1 | X61: =IF('РСБУ отчетность'!$F$85>=Подложка!X41,1,0) -> 1 | Y61: =IF('РСБУ отчетность'!$F$85>=Подложка!Y41,1,0) -> 1 | Z61: =SUM(W61:Y61) -> 3 | AA61: =IF(Z61=3,100,IF(Z61=2,70,IF(Z61=1,40,0))) -> 100 | AB61: =IF('РСБУ отчетность'!$F$85>=Подложка!AB41,1,0) -> 1 | AC61: =IF('РСБУ отчетность'!$F$85>=Подложка!AC41,1,0) -> 1 | AD61: =IF('РСБУ отчетность'!$F$85>=Подложка!AD41,1,0) -> 1 | AE61: =SUM(AB61:AD61) -> 3 | AF61: =IF(AE61=3,100,IF(AE61=2,70,IF(AE61=1,40,0))) -> 100 | AG61: =IF('РСБУ отчетность'!$F$85>=Подложка!AG41,1,0) -> 1 | AH61: =IF('РСБУ отчетность'!$F$85>=Подложка!AH41,1,0) -> 1 | AI61: =IF('РСБУ отчетность'!$F$85>=Подложка!AI41,1,0) -> 1 | AJ61: =SUM(AG61:AI61) -> 3 | AK61: =IF(AJ61=3,100,IF(AJ61=2,70,IF(AJ61=1,40,0))) -> 100 | AL61: =IF('РСБУ отчетность'!$F$85>=Подложка!AL41,1,0) -> 1 | AM61: =IF('РСБУ отчетность'!$F$85>=Подложка!AM41,1,0) -> 1 | AN61: =IF('РСБУ отчетность'!$F$85>=Подложка!AN41,1,0) -> 1 | AO61: =SUM(AL61:AN61) -> 3 | AP61: =IF(AO61=3,100,IF(AO61=2,70,IF(AO61=1,40,0))) -> 100 | AQ61: =IF('РСБУ отчетность'!$F$85>=Подложка!AQ41,1,0) -> 1 | AR61: =IF('РСБУ отчетность'!$F$85>=Подложка!AR41,1,0) -> 1 | AS61: =IF('РСБУ отчетность'!$F$85>=Подложка!AS41,1,0) -> 1 | AT61: =SUM(AQ61:AS61) -> 3 | AU61: =IF(AT61=3,100,IF(AT61=2,70,IF(AT61=1,40,0))) -> 100
A62: 1.8 | B62: Коэффициент маневренности | C62: =IF('РСБУ отчетность'!$F$86>=Подложка!C42,1,0) -> 1 | D62: =IF('РСБУ отчетность'!$F$86>=Подложка!D42,1,0) -> 1 | E62: =IF('РСБУ отчетность'!$F$86>=Подложка!E42,1,0) -> 1 | F62: =SUM(C62:E62) -> 3 | G62: =IF(F62=3,100,IF(F62=2,70,IF(F62=1,40,0))) -> 100 | H62: =IF('РСБУ отчетность'!$F$86>=Подложка!H42,1,0) -> 1 | I62: =IF('РСБУ отчетность'!$F$86>=Подложка!I42,1,0) -> 1 | J62: =IF('РСБУ отчетность'!$F$86>=Подложка!J42,1,0) -> 1 | K62: =SUM(H62:J62) -> 3 | L62: =IF(K62=3,100,IF(K62=2,70,IF(K62=1,40,0))) -> 100 | M62: =IF('РСБУ отчетность'!$F$86>=Подложка!M42,1,0) -> 1 | N62: =IF('РСБУ отчетность'!$F$86>=Подложка!N42,1,0) -> 1 | O62: =IF('РСБУ отчетность'!$F$86>=Подложка!O42,1,0) -> 1 | P62: =SUM(M62:O62) -> 3 | Q62: =IF(P62=3,100,IF(P62=2,70,IF(P62=1,40,0))) -> 100 | R62: =IF('РСБУ отчетность'!$F$86>=Подложка!R42,1,0) -> 1 | S62: =IF('РСБУ отчетность'!$F$86>=Подложка!S42,1,0) -> 1 | T62: =IF('РСБУ отчетность'!$F$86>=Подложка!T42,1,0) -> 1 | U62: =SUM(R62:T62) -> 3 | V62: =IF(U62=3,100,IF(U62=2,70,IF(U62=1,40,0))) -> 100 | W62: =IF('РСБУ отчетность'!$F$86>=Подложка!W42,1,0) -> 1 | X62: =IF('РСБУ отчетность'!$F$86>=Подложка!X42,1,0) -> 1 | Y62: =IF('РСБУ отчетность'!$F$86>=Подложка!Y42,1,0) -> 1 | Z62: =SUM(W62:Y62) -> 3 | AA62: =IF(Z62=3,100,IF(Z62=2,70,IF(Z62=1,40,0))) -> 100 | AB62: =IF('РСБУ отчетность'!$F$86>=Подложка!AB42,1,0) -> 1 | AC62: =IF('РСБУ отчетность'!$F$86>=Подложка!AC42,1,0) -> 1 | AD62: =IF('РСБУ отчетность'!$F$86>=Подложка!AD42,1,0) -> 1 | AE62: =SUM(AB62:AD62) -> 3 | AF62: =IF(AE62=3,100,IF(AE62=2,70,IF(AE62=1,40,0))) -> 100 | AG62: =IF('РСБУ отчетность'!$F$86>=Подложка!AG42,1,0) -> 1 | AH62: =IF('РСБУ отчетность'!$F$86>=Подложка!AH42,1,0) -> 1 | AI62: =IF('РСБУ отчетность'!$F$86>=Подложка!AI42,1,0) -> 1 | AJ62: =SUM(AG62:AI62) -> 3 | AK62: =IF(AJ62=3,100,IF(AJ62=2,70,IF(AJ62=1,40,0))) -> 100 | AL62: =IF('РСБУ отчетность'!$F$86>=Подложка!AL42,1,0) -> 1 | AM62: =IF('РСБУ отчетность'!$F$86>=Подложка!AM42,1,0) -> 1 | AN62: =IF('РСБУ отчетность'!$F$86>=Подложка!AN42,1,0) -> 0 | AO62: =SUM(AL62:AN62) -> 2 | AP62: =IF(AO62=3,100,IF(AO62=2,70,IF(AO62=1,40,0))) -> 70 | AQ62: =IF('РСБУ отчетность'!$F$86>=Подложка!AQ42,1,0) -> 1 | AR62: =IF('РСБУ отчетность'!$F$86>=Подложка!AR42,1,0) -> 1 | AS62: =IF('РСБУ отчетность'!$F$86>=Подложка!AS42,1,0) -> 0 | AT62: =SUM(AQ62:AS62) -> 2 | AU62: =IF(AT62=3,100,IF(AT62=2,70,IF(AT62=1,40,0))) -> 70
A63: 1.9 | B63: Рентабельность капитала | C63: =IF('РСБУ отчетность'!$F$87>=Подложка!C43,1,0) -> 1 | D63: =IF('РСБУ отчетность'!$F$87>=Подложка!D43,1,0) -> 1 | E63: =IF('РСБУ отчетность'!$F$87>=Подложка!E43,1,0) -> 1 | F63: =SUM(C63:E63) -> 3 | G63: =IF(F63=3,100,IF(F63=2,70,IF(F63=1,40,0))) -> 100 | H63: =IF('РСБУ отчетность'!$F$87>=Подложка!H43,1,0) -> 1 | I63: =IF('РСБУ отчетность'!$F$87>=Подложка!I43,1,0) -> 1 | J63: =IF('РСБУ отчетность'!$F$87>=Подложка!J43,1,0) -> 1 | K63: =SUM(H63:J63) -> 3 | L63: =IF(K63=3,100,IF(K63=2,70,IF(K63=1,40,0))) -> 100 | M63: =IF('РСБУ отчетность'!$F$87>=Подложка!M43,1,0) -> 1 | N63: =IF('РСБУ отчетность'!$F$87>=Подложка!N43,1,0) -> 1 | O63: =IF('РСБУ отчетность'!$F$87>=Подложка!O43,1,0) -> 1 | P63: =SUM(M63:O63) -> 3 | Q63: =IF(P63=3,100,IF(P63=2,70,IF(P63=1,40,0))) -> 100 | R63: =IF('РСБУ отчетность'!$F$87>=Подложка!R43,1,0) -> 1 | S63: =IF('РСБУ отчетность'!$F$87>=Подложка!S43,1,0) -> 1 | T63: =IF('РСБУ отчетность'!$F$87>=Подложка!T43,1,0) -> 1 | U63: =SUM(R63:T63) -> 3 | V63: =IF(U63=3,100,IF(U63=2,70,IF(U63=1,40,0))) -> 100 | W63: =IF('РСБУ отчетность'!$F$87>=Подложка!W43,1,0) -> 1 | X63: =IF('РСБУ отчетность'!$F$87>=Подложка!X43,1,0) -> 1 | Y63: =IF('РСБУ отчетность'!$F$87>=Подложка!Y43,1,0) -> 1 | Z63: =SUM(W63:Y63) -> 3 | AA63: =IF(Z63=3,100,IF(Z63=2,70,IF(Z63=1,40,0))) -> 100 | AB63: =IF('РСБУ отчетность'!$F$87>=Подложка!AB43,1,0) -> 1 | AC63: =IF('РСБУ отчетность'!$F$87>=Подложка!AC43,1,0) -> 1 | AD63: =IF('РСБУ отчетность'!$F$87>=Подложка!AD43,1,0) -> 1 | AE63: =SUM(AB63:AD63) -> 3 | AF63: =IF(AE63=3,100,IF(AE63=2,70,IF(AE63=1,40,0))) -> 100 | AG63: =IF('РСБУ отчетность'!$F$87>=Подложка!AG43,1,0) -> 1 | AH63: =IF('РСБУ отчетность'!$F$87>=Подложка!AH43,1,0) -> 1 | AI63: =IF('РСБУ отчетность'!$F$87>=Подложка!AI43,1,0) -> 1 | AJ63: =SUM(AG63:AI63) -> 3 | AK63: =IF(AJ63=3,100,IF(AJ63=2,70,IF(AJ63=1,40,0))) -> 100 | AL63: =IF('РСБУ отчетность'!$F$87>=Подложка!AL43,1,0) -> 1 | AM63: =IF('РСБУ отчетность'!$F$87>=Подложка!AM43,1,0) -> 1 | AN63: =IF('РСБУ отчетность'!$F$87>=Подложка!AN43,1,0) -> 1 | AO63: =SUM(AL63:AN63) -> 3 | AP63: =IF(AO63=3,100,IF(AO63=2,70,IF(AO63=1,40,0))) -> 100 | AQ63: =IF('РСБУ отчетность'!$F$87>=Подложка!AQ43,1,0) -> 1 | AR63: =IF('РСБУ отчетность'!$F$87>=Подложка!AR43,1,0) -> 1 | AS63: =IF('РСБУ отчетность'!$F$87>=Подложка!AS43,1,0) -> 0 | AT63: =SUM(AQ63:AS63) -> 2 | AU63: =IF(AT63=3,100,IF(AT63=2,70,IF(AT63=1,40,0))) -> 70
A78: Расчет группы кредитоспособности РСБУ | C78: Коды ОКВЭД 41-43, 71 | H78: Коды ОКВЭД 06, 49.5, 09, 19.2 | M78: Коды ОКВЭД 49-53, за искл. 49.5, 51, 50 | R78: Коды ОКВЭД 45-47 | W78: Коды ОКВЭД 05, 07-08, 10-33, 35, за искл.19.2 | AB78: Коды ОКВЭД 51 | AG78: Коды ОКВЭД 50 | AL78: Остальные коды ОКВЭД | AQ78: Коды ОКВЭД 62-63
C79: Строительство | H79: Добыча, переработка и транспортировка газа, нефти и нефтепродуктов | M79: Транспортировка и хранение | R79: Торговля | W79: Производство | AB79: Авиакомпания | AG79: Судовладелец | AL79: Прочие | AQ79: ИТ
B80: Группа кредитоспособности | C80: 3 группа | D80: 2 группа | E80: 1 группа | H80: 3 группа | I80: 2 группа | J80: 1 группа | M80: 3 группа | N80: 2 группа | O80: 1 группа | R80: 3 группа | S80: 2 группа | T80: 1 группа | W80: 3 группа | X80: 2 группа | Y80: 1 группа | AB80: 3 группа | AC80: 2 группа | AD80: 1 группа | AG80: 3 группа | AH80: 2 группа | AI80: 1 группа | AL80: 3 группа | AM80: 2 группа | AN80: 1 группа | AQ80: 3 группа | AR80: 2 группа | AS80: 1 группа
B81: Кол-во баллов | C81: 52 | D81: 64 | E81: 81.5 | H81: 49 | I81: 63 | J81: 80 | M81: 52.25 | N81: 64 | O81: 82 | R81: 53 | S81: 64 | T81: 81 | W81: 55 | X81: 64.5 | Y81: 82 | AB81: 50 | AC81: 63 | AD81: 78 | AG81: 40 | AH81: 61 | AI81: 80 | AL81: 50 | AM81: 66 | AN81: 82 | AQ81: 54 | AR81: 67 | AS81: 82.75
A82: Период 2 | B82: Расчет порога | C82: =IF('РСБУ расчет лимита'!$J$58>=Подложка!C81,1,0) -> 1 | D82: =IF('РСБУ расчет лимита'!$J$58>=Подложка!D81,1,0) -> 1 | E82: =IF('РСБУ расчет лимита'!$J$58>=Подложка!E81,1,0) -> 1 | F82: =SUM(C82:E82) -> 3 | G82: =IF(F82=3,1,IF(F82=2,2,IF(F82=1,3,4))) -> 1 | H82: =IF('РСБУ расчет лимита'!$J$58>=Подложка!H81,1,0) -> 1 | I82: =IF('РСБУ расчет лимита'!$J$58>=Подложка!I81,1,0) -> 1 | J82: =IF('РСБУ расчет лимита'!$J$58>=Подложка!J81,1,0) -> 1 | K82: =SUM(H82:J82) -> 3 | L82: =IF(K82=3,1,IF(K82=2,2,IF(K82=1,3,4))) -> 1 | M82: =IF('РСБУ расчет лимита'!$J$58>=Подложка!M81,1,0) -> 1 | N82: =IF('РСБУ расчет лимита'!$J$58>=Подложка!N81,1,0) -> 1 | O82: =IF('РСБУ расчет лимита'!$J$58>=Подложка!O81,1,0) -> 1 | P82: =SUM(M82:O82) -> 3 | Q82: =IF(P82=3,1,IF(P82=2,2,IF(P82=1,3,4))) -> 1 | R82: =IF('РСБУ расчет лимита'!$J$58>=Подложка!R81,1,0) -> 1 | S82: =IF('РСБУ расчет лимита'!$J$58>=Подложка!S81,1,0) -> 1 | T82: =IF('РСБУ расчет лимита'!$J$58>=Подложка!T81,1,0) -> 1 | U82: =SUM(R82:T82) -> 3 | V82: =IF(U82=3,1,IF(U82=2,2,IF(U82=1,3,4))) -> 1 | W82: =IF('РСБУ расчет лимита'!$J$58>=Подложка!W81,1,0) -> 1 | X82: =IF('РСБУ расчет лимита'!$J$58>=Подложка!X81,1,0) -> 1 | Y82: =IF('РСБУ расчет лимита'!$J$58>=Подложка!Y81,1,0) -> 1 | Z82: =SUM(W82:Y82) -> 3 | AA82: =IF(Z82=3,1,IF(Z82=2,2,IF(Z82=1,3,4))) -> 1 | AB82: =IF('РСБУ расчет лимита'!$J$58>=Подложка!AB81,1,0) -> 1 | AC82: =IF('РСБУ расчет лимита'!$J$58>=Подложка!AC81,1,0) -> 1 | AD82: =IF('РСБУ расчет лимита'!$J$58>=Подложка!AD81,1,0) -> 1 | AE82: =SUM(AB82:AD82) -> 3 | AF82: =IF(AE82=3,1,IF(AE82=2,2,IF(AE82=1,3,4))) -> 1 | AG82: =IF('РСБУ расчет лимита'!$J$58>=Подложка!AG81,1,0) -> 1 | AH82: =IF('РСБУ расчет лимита'!$J$58>=Подложка!AH81,1,0) -> 1 | AI82: =IF('РСБУ расчет лимита'!$J$58>=Подложка!AI81,1,0) -> 1 | AJ82: =SUM(AG82:AI82) -> 3 | AK82: =IF(AJ82=3,1,IF(AJ82=2,2,IF(AJ82=1,3,4))) -> 1 | AL82: =IF('РСБУ расчет лимита'!$J$58>=Подложка!AL81,1,0) -> 1 | AM82: =IF('РСБУ расчет лимита'!$J$58>=Подложка!AM81,1,0) -> 1 | AN82: =IF('РСБУ расчет лимита'!$J$58>=Подложка!AN81,1,0) -> 1 | AO82: =SUM(AL82:AN82) -> 3 | AP82: =IF(AO82=3,1,IF(AO82=2,2,IF(AO82=1,3,4))) -> 1 | AQ82: =IF('РСБУ расчет лимита'!$J$58>=Подложка!AQ81,1,0) -> 1 | AR82: =IF('РСБУ расчет лимита'!$J$58>=Подложка!AR81,1,0) -> 1 | AS82: =IF('РСБУ расчет лимита'!$J$58>=Подложка!AS81,1,0) -> 1 | AT82: =SUM(AQ82:AS82) -> 3 | AU82: =IF(AT82=3,1,IF(AT82=2,2,IF(AT82=1,3,4))) -> 1
A83: Период 1 | B83: Расчет порога | C83: =IF('РСБУ расчет лимита'!$L$58>=Подложка!C82,1,0) -> 1 | D83: =IF('РСБУ расчет лимита'!$L$58>=Подложка!D82,1,0) -> 1 | E83: =IF('РСБУ расчет лимита'!$L$58>=Подложка!E82,1,0) -> 1 | F83: =SUM(C83:E83) -> 3 | G83: =IF(F83=3,1,IF(F83=2,2,IF(F83=1,3,4))) -> 1 | H83: =IF('РСБУ расчет лимита'!$L$58>=Подложка!H82,1,0) -> 1 | I83: =IF('РСБУ расчет лимита'!$L$58>=Подложка!I82,1,0) -> 1 | J83: =IF('РСБУ расчет лимита'!$L$58>=Подложка!J82,1,0) -> 1 | K83: =SUM(H83:J83) -> 3 | L83: =IF(K83=3,1,IF(K83=2,2,IF(K83=1,3,4))) -> 1 | M83: =IF('РСБУ расчет лимита'!$L$58>=Подложка!M82,1,0) -> 1 | N83: =IF('РСБУ расчет лимита'!$L$58>=Подложка!N82,1,0) -> 1 | O83: =IF('РСБУ расчет лимита'!$L$58>=Подложка!O82,1,0) -> 1 | P83: =SUM(M83:O83) -> 3 | Q83: =IF(P83=3,1,IF(P83=2,2,IF(P83=1,3,4))) -> 1 | R83: =IF('РСБУ расчет лимита'!$L$58>=Подложка!R82,1,0) -> 1 | S83: =IF('РСБУ расчет лимита'!$L$58>=Подложка!S82,1,0) -> 1 | T83: =IF('РСБУ расчет лимита'!$L$58>=Подложка!T82,1,0) -> 1 | U83: =SUM(R83:T83) -> 3 | V83: =IF(U83=3,1,IF(U83=2,2,IF(U83=1,3,4))) -> 1 | W83: =IF('РСБУ расчет лимита'!$L$58>=Подложка!W82,1,0) -> 1 | X83: =IF('РСБУ расчет лимита'!$L$58>=Подложка!X82,1,0) -> 1 | Y83: =IF('РСБУ расчет лимита'!$L$58>=Подложка!Y82,1,0) -> 1 | Z83: =SUM(W83:Y83) -> 3 | AA83: =IF(Z83=3,1,IF(Z83=2,2,IF(Z83=1,3,4))) -> 1 | AB83: =IF('РСБУ расчет лимита'!$L$58>=Подложка!AB82,1,0) -> 1 | AC83: =IF('РСБУ расчет лимита'!$L$58>=Подложка!AC82,1,0) -> 1 | AD83: =IF('РСБУ расчет лимита'!$L$58>=Подложка!AD82,1,0) -> 1 | AE83: =SUM(AB83:AD83) -> 3 | AF83: =IF(AE83=3,1,IF(AE83=2,2,IF(AE83=1,3,4))) -> 1 | AG83: =IF('РСБУ расчет лимита'!$L$58>=Подложка!AG82,1,0) -> 1 | AH83: =IF('РСБУ расчет лимита'!$L$58>=Подложка!AH82,1,0) -> 1 | AI83: =IF('РСБУ расчет лимита'!$L$58>=Подложка!AI82,1,0) -> 1 | AJ83: =SUM(AG83:AI83) -> 3 | AK83: =IF(AJ83=3,1,IF(AJ83=2,2,IF(AJ83=1,3,4))) -> 1 | AL83: =IF('РСБУ расчет лимита'!$L$58>=Подложка!AL82,1,0) -> 1 | AM83: =IF('РСБУ расчет лимита'!$L$58>=Подложка!AM82,1,0) -> 1 | AN83: =IF('РСБУ расчет лимита'!$L$58>=Подложка!AN82,1,0) -> 1 | AO83: =SUM(AL83:AN83) -> 3 | AP83: =IF(AO83=3,1,IF(AO83=2,2,IF(AO83=1,3,4))) -> 1 | AQ83: =IF('РСБУ расчет лимита'!$L$58>=Подложка!AQ82,1,0) -> 1 | AR83: =IF('РСБУ расчет лимита'!$L$58>=Подложка!AR82,1,0) -> 1 | AS83: =IF('РСБУ расчет лимита'!$L$58>=Подложка!AS82,1,0) -> 1 | AT83: =SUM(AQ83:AS83) -> 3 | AU83: =IF(AT83=3,1,IF(AT83=2,2,IF(AT83=1,3,4))) -> 1
A88: МСФО расчет баллов | C88: Коды ОКВЭД 41-43, 71 | H88: Коды ОКВЭД 06, 49.5, 09, 19.2 | M88: Коды ОКВЭД 49-53, за искл. 49.5, 51, 50 | R88: Коды ОКВЭД 45-47 | W88: Коды ОКВЭД 05, 07-08, 10-33, 35, за искл.19.2 | AB88: Коды ОКВЭД 51 | AG88: Коды ОКВЭД 50 | AL88: Остальные коды ОКВЭД | AQ88: Коды ОКВЭД 62-63
A89: № | B89: ФИНАНСОВЫЕ ПОКАЗАТЕЛИ | C89: Строительство | H89: Добыча, переработка и транспортировка газа, нефти и нефтепродуктов | M89: Транспортировка и хранение | R89: Торговля | W89: Производство | AB89: Авиакомпания | AG89: Судовладелец | AL89: Прочие | AQ89: ИТ
B90: Кол-во баллов | C90: 40 | D90: 70 | E90: 100 | H90: 40 | I90: 70 | J90: 100 | M90: 40 | N90: 70 | O90: 100 | R90: 40 | S90: 70 | T90: 100 | W90: 40 | X90: 70 | Y90: 100 | AB90: 40 | AC90: 70 | AD90: 100 | AG90: 40 | AH90: 70 | AI90: 100 | AL90: 40 | AM90: 70 | AN90: 100 | AQ90: 40 | AR90: 70 | AS90: 100
A91: Период 2 | F91: Порог | G91: Балл | K91: Порог | L91: Балл | P91: Порог | Q91: Балл | U91: Порог | V91: Балл | Z91: Порог | AA91: Балл | AE91: Порог | AF91: Балл | AJ91: Порог | AK91: Балл | AO91: Порог | AP91: Балл | AT91: Порог | AU91: Балл
A92: 1.1 | B92: Коэффициент текущей ликвидности | C92: =IF('МСФО отчетность'!$E$64>=Подложка!C35,1,0) -> 1 | D92: =IF('МСФО отчетность'!$E$64>=Подложка!D35,1,0) -> 1 | E92: =IF('МСФО отчетность'!$E$64>=Подложка!E35,1,0) -> 1 | F92: =SUM(C92:E92) -> 3 | G92: =IF(F92=3,100,IF(F92=2,70,IF(F92=1,40,0))) -> 100 | H92: =IF('МСФО отчетность'!$E$64>=Подложка!H35,1,0) -> 1 | I92: =IF('МСФО отчетность'!$E$64>=Подложка!I35,1,0) -> 1 | J92: =IF('МСФО отчетность'!$E$64>=Подложка!J35,1,0) -> 1 | K92: =SUM(H92:J92) -> 3 | L92: =IF(K92=3,100,IF(K92=2,70,IF(K92=1,40,0))) -> 100 | M92: =IF('МСФО отчетность'!$E$64>=Подложка!M35,1,0) -> 1 | N92: =IF('МСФО отчетность'!$E$64>=Подложка!N35,1,0) -> 1 | O92: =IF('МСФО отчетность'!$E$64>=Подложка!O35,1,0) -> 1 | P92: =SUM(M92:O92) -> 3 | Q92: =IF(P92=3,100,IF(P92=2,70,IF(P92=1,40,0))) -> 100 | R92: =IF('МСФО отчетность'!$E$64>=Подложка!R35,1,0) -> 1 | S92: =IF('МСФО отчетность'!$E$64>=Подложка!S35,1,0) -> 1 | T92: =IF('МСФО отчетность'!$E$64>=Подложка!T35,1,0) -> 1 | U92: =SUM(R92:T92) -> 3 | V92: =IF(U92=3,100,IF(U92=2,70,IF(U92=1,40,0))) -> 100 | W92: =IF('МСФО отчетность'!$E$64>=Подложка!W35,1,0) -> 1 | X92: =IF('МСФО отчетность'!$E$64>=Подложка!X35,1,0) -> 1 | Y92: =IF('МСФО отчетность'!$E$64>=Подложка!Y35,1,0) -> 1 | Z92: =SUM(W92:Y92) -> 3 | AA92: =IF(Z92=3,100,IF(Z92=2,70,IF(Z92=1,40,0))) -> 100 | AB92: =IF('МСФО отчетность'!$E$64>=Подложка!AB35,1,0) -> 1 | AC92: =IF('МСФО отчетность'!$E$64>=Подложка!AC35,1,0) -> 1 | AD92: =IF('МСФО отчетность'!$E$64>=Подложка!AD35,1,0) -> 1 | AE92: =SUM(AB92:AD92) -> 3 | AF92: =IF(AE92=3,100,IF(AE92=2,70,IF(AE92=1,40,0))) -> 100 | AG92: =IF('МСФО отчетность'!$E$64>=Подложка!AG35,1,0) -> 1 | AH92: =IF('МСФО отчетность'!$E$64>=Подложка!AH35,1,0) -> 1 | AI92: =IF('МСФО отчетность'!$E$64>=Подложка!AI35,1,0) -> 1 | AJ92: =SUM(AG92:AI92) -> 3 | AK92: =IF(AJ92=3,100,IF(AJ92=2,70,IF(AJ92=1,40,0))) -> 100 | AL92: =IF('МСФО отчетность'!$E$64>=Подложка!AL35,1,0) -> 1 | AM92: =IF('МСФО отчетность'!$E$64>=Подложка!AM35,1,0) -> 1 | AN92: =IF('МСФО отчетность'!$E$64>=Подложка!AN35,1,0) -> 0 | AO92: =SUM(AL92:AN92) -> 2 | AP92: =IF(AO92=3,100,IF(AO92=2,70,IF(AO92=1,40,0))) -> 70 | AQ92: =IF('МСФО отчетность'!$E$64>=Подложка!AQ35,1,0) -> 1 | AR92: =IF('МСФО отчетность'!$E$64>=Подложка!AR35,1,0) -> 1 | AS92: =IF('МСФО отчетность'!$E$64>=Подложка!AS35,1,0) -> 0 | AT92: =SUM(AQ92:AS92) -> 2 | AU92: =IF(AT92=3,100,IF(AT92=2,70,IF(AT92=1,40,0))) -> 70
A93: 1.2 | B93: Коэффициент быстрой ликвидности | C93: =IF('МСФО отчетность'!$E$65>=Подложка!C36,1,0) -> 1 | D93: =IF('МСФО отчетность'!$E$65>=Подложка!D36,1,0) -> 1 | E93: =IF('МСФО отчетность'!$E$65>=Подложка!E36,1,0) -> 1 | F93: =SUM(C93:E93) -> 3 | G93: =IF(F93=3,100,IF(F93=2,70,IF(F93=1,40,0))) -> 100 | H93: =IF('МСФО отчетность'!$E$65>=Подложка!H36,1,0) -> 1 | I93: =IF('МСФО отчетность'!$E$65>=Подложка!I36,1,0) -> 1 | J93: =IF('МСФО отчетность'!$E$65>=Подложка!J36,1,0) -> 1 | K93: =SUM(H93:J93) -> 3 | L93: =IF(K93=3,100,IF(K93=2,70,IF(K93=1,40,0))) -> 100 | M93: =IF('МСФО отчетность'!$E$65>=Подложка!M36,1,0) -> 1 | N93: =IF('МСФО отчетность'!$E$65>=Подложка!N36,1,0) -> 1 | O93: =IF('МСФО отчетность'!$E$65>=Подложка!O36,1,0) -> 1 | P93: =SUM(M93:O93) -> 3 | Q93: =IF(P93=3,100,IF(P93=2,70,IF(P93=1,40,0))) -> 100 | R93: =IF('МСФО отчетность'!$E$65>=Подложка!R36,1,0) -> 1 | S93: =IF('МСФО отчетность'!$E$65>=Подложка!S36,1,0) -> 1 | T93: =IF('МСФО отчетность'!$E$65>=Подложка!T36,1,0) -> 1 | U93: =SUM(R93:T93) -> 3 | V93: =IF(U93=3,100,IF(U93=2,70,IF(U93=1,40,0))) -> 100 | W93: =IF('МСФО отчетность'!$E$65>=Подложка!W36,1,0) -> 1 | X93: =IF('МСФО отчетность'!$E$65>=Подложка!X36,1,0) -> 1 | Y93: =IF('МСФО отчетность'!$E$65>=Подложка!Y36,1,0) -> 1 | Z93: =SUM(W93:Y93) -> 3 | AA93: =IF(Z93=3,100,IF(Z93=2,70,IF(Z93=1,40,0))) -> 100 | AB93: =IF('МСФО отчетность'!$E$65>=Подложка!AB36,1,0) -> 1 | AC93: =IF('МСФО отчетность'!$E$65>=Подложка!AC36,1,0) -> 1 | AD93: =IF('МСФО отчетность'!$E$65>=Подложка!AD36,1,0) -> 0 | AE93: =SUM(AB93:AD93) -> 2 | AF93: =IF(AE93=3,100,IF(AE93=2,70,IF(AE93=1,40,0))) -> 70 | AG93: =IF('МСФО отчетность'!$E$65>=Подложка!AG36,1,0) -> 1 | AH93: =IF('МСФО отчетность'!$E$65>=Подложка!AH36,1,0) -> 1 | AI93: =IF('МСФО отчетность'!$E$65>=Подложка!AI36,1,0) -> 0 | AJ93: =SUM(AG93:AI93) -> 2 | AK93: =IF(AJ93=3,100,IF(AJ93=2,70,IF(AJ93=1,40,0))) -> 70 | AL93: =IF('МСФО отчетность'!$E$65>=Подложка!AL36,1,0) -> 1 | AM93: =IF('МСФО отчетность'!$E$65>=Подложка!AM36,1,0) -> 1 | AN93: =IF('МСФО отчетность'!$E$65>=Подложка!AN36,1,0) -> 0 | AO93: =SUM(AL93:AN93) -> 2 | AP93: =IF(AO93=3,100,IF(AO93=2,70,IF(AO93=1,40,0))) -> 70 | AQ93: =IF('МСФО отчетность'!$E$65>=Подложка!AQ36,1,0) -> 1 | AR93: =IF('МСФО отчетность'!$E$65>=Подложка!AR36,1,0) -> 1 | AS93: =IF('МСФО отчетность'!$E$65>=Подложка!AS36,1,0) -> 0 | AT93: =SUM(AQ93:AS93) -> 2 | AU93: =IF(AT93=3,100,IF(AT93=2,70,IF(AT93=1,40,0))) -> 70
A94: 1.3 | B94: Длительность операционного цикла | C94: =IF('МСФО отчетность'!$E$66<Подложка!C37,1,0) -> 0 | D94: =IF('МСФО отчетность'!$E$66<Подложка!D37,1,0) -> 0 | E94: =IF('МСФО отчетность'!$E$66<Подложка!E37,1,0) -> 0 | F94: =SUM(C94:E94) -> 0 | G94: =IF(F94=3,100,IF(F94=2,70,IF(F94=1,40,0))) -> 0 | H94: =IF('МСФО отчетность'!$E$66<Подложка!H37,1,0) -> 0 | I94: =IF('МСФО отчетность'!$E$66<Подложка!I37,1,0) -> 0 | J94: =IF('МСФО отчетность'!$E$66<Подложка!J37,1,0) -> 0 | K94: =SUM(H94:J94) -> 0 | L94: =IF(K94=3,100,IF(K94=2,70,IF(K94=1,40,0))) -> 0 | M94: =IF('МСФО отчетность'!$E$66<Подложка!M37,1,0) -> 0 | N94: =IF('МСФО отчетность'!$E$66<Подложка!N37,1,0) -> 0 | O94: =IF('МСФО отчетность'!$E$66<Подложка!O37,1,0) -> 0 | P94: =SUM(M94:O94) -> 0 | Q94: =IF(P94=3,100,IF(P94=2,70,IF(P94=1,40,0))) -> 0 | R94: =IF('МСФО отчетность'!$E$66<Подложка!R37,1,0) -> 0 | S94: =IF('МСФО отчетность'!$E$66<Подложка!S37,1,0) -> 0 | T94: =IF('МСФО отчетность'!$E$66<Подложка!T37,1,0) -> 0 | U94: =SUM(R94:T94) -> 0 | V94: =IF(U94=3,100,IF(U94=2,70,IF(U94=1,40,0))) -> 0 | W94: =IF('МСФО отчетность'!$E$66<Подложка!W37,1,0) -> 0 | X94: =IF('МСФО отчетность'!$E$66<Подложка!X37,1,0) -> 0 | Y94: =IF('МСФО отчетность'!$E$66<Подложка!Y37,1,0) -> 0 | Z94: =SUM(W94:Y94) -> 0 | AA94: =IF(Z94=3,100,IF(Z94=2,70,IF(Z94=1,40,0))) -> 0 | AB94: =IF('МСФО отчетность'!$E$66<Подложка!AB37,1,0) -> 0 | AC94: =IF('МСФО отчетность'!$E$66<Подложка!AC37,1,0) -> 0 | AD94: =IF('МСФО отчетность'!$E$66<Подложка!AD37,1,0) -> 0 | AE94: =SUM(AB94:AD94) -> 0 | AF94: =IF(AE94=3,100,IF(AE94=2,70,IF(AE94=1,40,0))) -> 0 | AG94: =IF('МСФО отчетность'!$E$66<Подложка!AG37,1,0) -> 0 | AH94: =IF('МСФО отчетность'!$E$66<Подложка!AH37,1,0) -> 0 | AI94: =IF('МСФО отчетность'!$E$66<Подложка!AI37,1,0) -> 0 | AJ94: =SUM(AG94:AI94) -> 0 | AK94: =IF(AJ94=3,100,IF(AJ94=2,70,IF(AJ94=1,40,0))) -> 0 | AL94: =IF('МСФО отчетность'!$E$66<Подложка!AL37,1,0) -> 0 | AM94: =IF('МСФО отчетность'!$E$66<Подложка!AM37,1,0) -> 0 | AN94: =IF('МСФО отчетность'!$E$66<Подложка!AN37,1,0) -> 0 | AO94: =SUM(AL94:AN94) -> 0 | AP94: =IF(AO94=3,100,IF(AO94=2,70,IF(AO94=1,40,0))) -> 0 | AQ94: =IF('МСФО отчетность'!$E$66<Подложка!AQ37,1,0) -> 0 | AR94: =IF('МСФО отчетность'!$E$66<Подложка!AR37,1,0) -> 0 | AS94: =IF('МСФО отчетность'!$E$66<Подложка!AS37,1,0) -> 0 | AT94: =SUM(AQ94:AS94) -> 0 | AU94: =IF(AT94=3,100,IF(AT94=2,70,IF(AT94=1,40,0))) -> 0
A95: 1.4 | B95: Коэффициент автономии | C95: =IF('МСФО отчетность'!$E$67>=Подложка!C38,1,0) -> 1 | D95: =IF('МСФО отчетность'!$E$67>=Подложка!D38,1,0) -> 1 | E95: =IF('МСФО отчетность'!$E$67>=Подложка!E38,1,0) -> 1 | F95: =SUM(C95:E95) -> 3 | G95: =IF(F95=3,100,IF(F95=2,70,IF(F95=1,40,0))) -> 100 | H95: =IF('МСФО отчетность'!$E$67>=Подложка!H38,1,0) -> 1 | I95: =IF('МСФО отчетность'!$E$67>=Подложка!I38,1,0) -> 1 | J95: =IF('МСФО отчетность'!$E$67>=Подложка!J38,1,0) -> 1 | K95: =SUM(H95:J95) -> 3 | L95: =IF(K95=3,100,IF(K95=2,70,IF(K95=1,40,0))) -> 100 | M95: =IF('МСФО отчетность'!$E$67>=Подложка!M38,1,0) -> 1 | N95: =IF('МСФО отчетность'!$E$67>=Подложка!N38,1,0) -> 1 | O95: =IF('МСФО отчетность'!$E$67>=Подложка!O38,1,0) -> 1 | P95: =SUM(M95:O95) -> 3 | Q95: =IF(P95=3,100,IF(P95=2,70,IF(P95=1,40,0))) -> 100 | R95: =IF('МСФО отчетность'!$E$67>=Подложка!R38,1,0) -> 1 | S95: =IF('МСФО отчетность'!$E$67>=Подложка!S38,1,0) -> 1 | T95: =IF('МСФО отчетность'!$E$67>=Подложка!T38,1,0) -> 1 | U95: =SUM(R95:T95) -> 3 | V95: =IF(U95=3,100,IF(U95=2,70,IF(U95=1,40,0))) -> 100 | W95: =IF('МСФО отчетность'!$E$67>=Подложка!W38,1,0) -> 1 | X95: =IF('МСФО отчетность'!$E$67>=Подложка!X38,1,0) -> 1 | Y95: =IF('МСФО отчетность'!$E$67>=Подложка!Y38,1,0) -> 1 | Z95: =SUM(W95:Y95) -> 3 | AA95: =IF(Z95=3,100,IF(Z95=2,70,IF(Z95=1,40,0))) -> 100 | AB95: =IF('МСФО отчетность'!$E$67>=Подложка!AB38,1,0) -> 1 | AC95: =IF('МСФО отчетность'!$E$67>=Подложка!AC38,1,0) -> 1 | AD95: =IF('МСФО отчетность'!$E$67>=Подложка!AD38,1,0) -> 0 | AE95: =SUM(AB95:AD95) -> 2 | AF95: =IF(AE95=3,100,IF(AE95=2,70,IF(AE95=1,40,0))) -> 70 | AG95: =IF('МСФО отчетность'!$E$67>=Подложка!AG38,1,0) -> 1 | AH95: =IF('МСФО отчетность'!$E$67>=Подложка!AH38,1,0) -> 1 | AI95: =IF('МСФО отчетность'!$E$67>=Подложка!AI38,1,0) -> 1 | AJ95: =SUM(AG95:AI95) -> 3 | AK95: =IF(AJ95=3,100,IF(AJ95=2,70,IF(AJ95=1,40,0))) -> 100 | AL95: =IF('МСФО отчетность'!$E$67>=Подложка!AL38,1,0) -> 1 | AM95: =IF('МСФО отчетность'!$E$67>=Подложка!AM38,1,0) -> 1 | AN95: =IF('МСФО отчетность'!$E$67>=Подложка!AN38,1,0) -> 0 | AO95: =SUM(AL95:AN95) -> 2 | AP95: =IF(AO95=3,100,IF(AO95=2,70,IF(AO95=1,40,0))) -> 70 | AQ95: =IF('МСФО отчетность'!$E$67>=Подложка!AQ38,1,0) -> 1 | AR95: =IF('МСФО отчетность'!$E$67>=Подложка!AR38,1,0) -> 1 | AS95: =IF('МСФО отчетность'!$E$67>=Подложка!AS38,1,0) -> 0 | AT95: =SUM(AQ95:AS95) -> 2 | AU95: =IF(AT95=3,100,IF(AT95=2,70,IF(AT95=1,40,0))) -> 70
A96: 1.5 | B96: Рентабельность продаж | C96: =IF('МСФО отчетность'!$E$68>=Подложка!C39,1,0) -> 1 | D96: =IF('МСФО отчетность'!$E$68>=Подложка!D39,1,0) -> 1 | E96: =IF('МСФО отчетность'!$E$68>=Подложка!E39,1,0) -> 0 | F96: =SUM(C96:E96) -> 2 | G96: =IF(F96=3,100,IF(F96=2,70,IF(F96=1,40,0))) -> 70 | H96: =IF('МСФО отчетность'!$E$68>=Подложка!H39,1,0) -> 1 | I96: =IF('МСФО отчетность'!$E$68>=Подложка!I39,1,0) -> 1 | J96: =IF('МСФО отчетность'!$E$68>=Подложка!J39,1,0) -> 0 | K96: =SUM(H96:J96) -> 2 | L96: =IF(K96=3,100,IF(K96=2,70,IF(K96=1,40,0))) -> 70 | M96: =IF('МСФО отчетность'!$E$68>=Подложка!M39,1,0) -> 1 | N96: =IF('МСФО отчетность'!$E$68>=Подложка!N39,1,0) -> 1 | O96: =IF('МСФО отчетность'!$E$68>=Подложка!O39,1,0) -> 0 | P96: =SUM(M96:O96) -> 2 | Q96: =IF(P96=3,100,IF(P96=2,70,IF(P96=1,40,0))) -> 70 | R96: =IF('МСФО отчетность'!$E$68>=Подложка!R39,1,0) -> 1 | S96: =IF('МСФО отчетность'!$E$68>=Подложка!S39,1,0) -> 1 | T96: =IF('МСФО отчетность'!$E$68>=Подложка!T39,1,0) -> 1 | U96: =SUM(R96:T96) -> 3 | V96: =IF(U96=3,100,IF(U96=2,70,IF(U96=1,40,0))) -> 100 | W96: =IF('МСФО отчетность'!$E$68>=Подложка!W39,1,0) -> 1 | X96: =IF('МСФО отчетность'!$E$68>=Подложка!X39,1,0) -> 1 | Y96: =IF('МСФО отчетность'!$E$68>=Подложка!Y39,1,0) -> 0 | Z96: =SUM(W96:Y96) -> 2 | AA96: =IF(Z96=3,100,IF(Z96=2,70,IF(Z96=1,40,0))) -> 70 | AB96: =IF('МСФО отчетность'!$E$68>=Подложка!AB39,1,0) -> 1 | AC96: =IF('МСФО отчетность'!$E$68>=Подложка!AC39,1,0) -> 1 | AD96: =IF('МСФО отчетность'!$E$68>=Подложка!AD39,1,0) -> 0 | AE96: =SUM(AB96:AD96) -> 2 | AF96: =IF(AE96=3,100,IF(AE96=2,70,IF(AE96=1,40,0))) -> 70 | AG96: =IF('МСФО отчетность'!$E$68>=Подложка!AG39,1,0) -> 1 | AH96: =IF('МСФО отчетность'!$E$68>=Подложка!AH39,1,0) -> 1 | AI96: =IF('МСФО отчетность'!$E$68>=Подложка!AI39,1,0) -> 0 | AJ96: =SUM(AG96:AI96) -> 2 | AK96: =IF(AJ96=3,100,IF(AJ96=2,70,IF(AJ96=1,40,0))) -> 70 | AL96: =IF('МСФО отчетность'!$E$68>=Подложка!AL39,1,0) -> 1 | AM96: =IF('МСФО отчетность'!$E$68>=Подложка!AM39,1,0) -> 1 | AN96: =IF('МСФО отчетность'!$E$68>=Подложка!AN39,1,0) -> 0 | AO96: =SUM(AL96:AN96) -> 2 | AP96: =IF(AO96=3,100,IF(AO96=2,70,IF(AO96=1,40,0))) -> 70 | AQ96: =IF('МСФО отчетность'!$E$68>=Подложка!AQ39,1,0) -> 1 | AR96: =IF('МСФО отчетность'!$E$68>=Подложка!AR39,1,0) -> 0 | AS96: =IF('МСФО отчетность'!$E$68>=Подложка!AS39,1,0) -> 0 | AT96: =SUM(AQ96:AS96) -> 1 | AU96: =IF(AT96=3,100,IF(AT96=2,70,IF(AT96=1,40,0))) -> 40
A97: 1.6 | B97: Коэффициент долговой нагрузки | C97: =IF('МСФО отчетность'!$E$69<Подложка!C40,1,0) -> 1 | D97: =IF('МСФО отчетность'!$E$69<Подложка!D40,1,0) -> 0 | E97: =IF('МСФО отчетность'!$E$69<Подложка!E40,1,0) -> 0 | F97: =SUM(C97:E97) -> 1 | G97: =IF(F97=3,100,IF(F97=2,70,IF(F97=1,40,0))) -> 40 | H97: =IF('МСФО отчетность'!$E$69<Подложка!H40,1,0) -> 1 | I97: =IF('МСФО отчетность'!$E$69<Подложка!I40,1,0) -> 1 | J97: =IF('МСФО отчетность'!$E$69<Подложка!J40,1,0) -> 0 | K97: =SUM(H97:J97) -> 2 | L97: =IF(K97=3,100,IF(K97=2,70,IF(K97=1,40,0))) -> 70 | M97: =IF('МСФО отчетность'!$E$69<Подложка!M40,1,0) -> 1 | N97: =IF('МСФО отчетность'!$E$69<Подложка!N40,1,0) -> 1 | O97: =IF('МСФО отчетность'!$E$69<Подложка!O40,1,0) -> 0 | P97: =SUM(M97:O97) -> 2 | Q97: =IF(P97=3,100,IF(P97=2,70,IF(P97=1,40,0))) -> 70 | R97: =IF('МСФО отчетность'!$E$69<Подложка!R40,1,0) -> 1 | S97: =IF('МСФО отчетность'!$E$69<Подложка!S40,1,0) -> 1 | T97: =IF('МСФО отчетность'!$E$69<Подложка!T40,1,0) -> 0 | U97: =SUM(R97:T97) -> 2 | V97: =IF(U97=3,100,IF(U97=2,70,IF(U97=1,40,0))) -> 70 | W97: =IF('МСФО отчетность'!$E$69<Подложка!W40,1,0) -> 1 | X97: =IF('МСФО отчетность'!$E$69<Подложка!X40,1,0) -> 1 | Y97: =IF('МСФО отчетность'!$E$69<Подложка!Y40,1,0) -> 0 | Z97: =SUM(W97:Y97) -> 2 | AA97: =IF(Z97=3,100,IF(Z97=2,70,IF(Z97=1,40,0))) -> 70 | AB97: =IF('МСФО отчетность'!$E$69<Подложка!AB40,1,0) -> 1 | AC97: =IF('МСФО отчетность'!$E$69<Подложка!AC40,1,0) -> 0 | AD97: =IF('МСФО отчетность'!$E$69<Подложка!AD40,1,0) -> 0 | AE97: =SUM(AB97:AD97) -> 1 | AF97: =IF(AE97=3,100,IF(AE97=2,70,IF(AE97=1,40,0))) -> 40 | AG97: =IF('МСФО отчетность'!$E$69<Подложка!AG40,1,0) -> 1 | AH97: =IF('МСФО отчетность'!$E$69<Подложка!AH40,1,0) -> 0 | AI97: =IF('МСФО отчетность'!$E$69<Подложка!AI40,1,0) -> 0 | AJ97: =SUM(AG97:AI97) -> 1 | AK97: =IF(AJ97=3,100,IF(AJ97=2,70,IF(AJ97=1,40,0))) -> 40 | AL97: =IF('МСФО отчетность'!$E$69<Подложка!AL40,1,0) -> 1 | AM97: =IF('МСФО отчетность'!$E$69<Подложка!AM40,1,0) -> 0 | AN97: =IF('МСФО отчетность'!$E$69<Подложка!AN40,1,0) -> 0 | AO97: =SUM(AL97:AN97) -> 1 | AP97: =IF(AO97=3,100,IF(AO97=2,70,IF(AO97=1,40,0))) -> 40 | AQ97: =IF('МСФО отчетность'!$E$69<Подложка!AQ40,1,0) -> 1 | AR97: =IF('МСФО отчетность'!$E$69<Подложка!AR40,1,0) -> 0 | AS97: =IF('МСФО отчетность'!$E$69<Подложка!AS40,1,0) -> 0 | AT97: =SUM(AQ97:AS97) -> 1 | AU97: =IF(AT97=3,100,IF(AT97=2,70,IF(AT97=1,40,0))) -> 40
A98: 1.7 | B98: Коэффициент покрытия процентов | C98: =IF('МСФО отчетность'!$E$70>=Подложка!C41,1,0) -> 1 | D98: =IF('МСФО отчетность'!$E$70>=Подложка!D41,1,0) -> 1 | E98: =IF('МСФО отчетность'!$E$70>=Подложка!E41,1,0) -> 1 | F98: =SUM(C98:E98) -> 3 | G98: =IF(F98=3,100,IF(F98=2,70,IF(F98=1,40,0))) -> 100 | H98: =IF('МСФО отчетность'!$E$70>=Подложка!H41,1,0) -> 1 | I98: =IF('МСФО отчетность'!$E$70>=Подложка!I41,1,0) -> 1 | J98: =IF('МСФО отчетность'!$E$70>=Подложка!J41,1,0) -> 1 | K98: =SUM(H98:J98) -> 3 | L98: =IF(K98=3,100,IF(K98=2,70,IF(K98=1,40,0))) -> 100 | M98: =IF('МСФО отчетность'!$E$70>=Подложка!M41,1,0) -> 1 | N98: =IF('МСФО отчетность'!$E$70>=Подложка!N41,1,0) -> 1 | O98: =IF('МСФО отчетность'!$E$70>=Подложка!O41,1,0) -> 1 | P98: =SUM(M98:O98) -> 3 | Q98: =IF(P98=3,100,IF(P98=2,70,IF(P98=1,40,0))) -> 100 | R98: =IF('МСФО отчетность'!$E$70>=Подложка!R41,1,0) -> 1 | S98: =IF('МСФО отчетность'!$E$70>=Подложка!S41,1,0) -> 1 | T98: =IF('МСФО отчетность'!$E$70>=Подложка!T41,1,0) -> 1 | U98: =SUM(R98:T98) -> 3 | V98: =IF(U98=3,100,IF(U98=2,70,IF(U98=1,40,0))) -> 100 | W98: =IF('МСФО отчетность'!$E$70>=Подложка!W41,1,0) -> 1 | X98: =IF('МСФО отчетность'!$E$70>=Подложка!X41,1,0) -> 1 | Y98: =IF('МСФО отчетность'!$E$70>=Подложка!Y41,1,0) -> 1 | Z98: =SUM(W98:Y98) -> 3 | AA98: =IF(Z98=3,100,IF(Z98=2,70,IF(Z98=1,40,0))) -> 100 | AB98: =IF('МСФО отчетность'!$E$70>=Подложка!AB41,1,0) -> 1 | AC98: =IF('МСФО отчетность'!$E$70>=Подложка!AC41,1,0) -> 1 | AD98: =IF('МСФО отчетность'!$E$70>=Подложка!AD41,1,0) -> 1 | AE98: =SUM(AB98:AD98) -> 3 | AF98: =IF(AE98=3,100,IF(AE98=2,70,IF(AE98=1,40,0))) -> 100 | AG98: =IF('МСФО отчетность'!$E$70>=Подложка!AG41,1,0) -> 1 | AH98: =IF('МСФО отчетность'!$E$70>=Подложка!AH41,1,0) -> 1 | AI98: =IF('МСФО отчетность'!$E$70>=Подложка!AI41,1,0) -> 1 | AJ98: =SUM(AG98:AI98) -> 3 | AK98: =IF(AJ98=3,100,IF(AJ98=2,70,IF(AJ98=1,40,0))) -> 100 | AL98: =IF('МСФО отчетность'!$E$70>=Подложка!AL41,1,0) -> 1 | AM98: =IF('МСФО отчетность'!$E$70>=Подложка!AM41,1,0) -> 1 | AN98: =IF('МСФО отчетность'!$E$70>=Подложка!AN41,1,0) -> 1 | AO98: =SUM(AL98:AN98) -> 3 | AP98: =IF(AO98=3,100,IF(AO98=2,70,IF(AO98=1,40,0))) -> 100 | AQ98: =IF('МСФО отчетность'!$E$70>=Подложка!AQ41,1,0) -> 1 | AR98: =IF('МСФО отчетность'!$E$70>=Подложка!AR41,1,0) -> 1 | AS98: =IF('МСФО отчетность'!$E$70>=Подложка!AS41,1,0) -> 1 | AT98: =SUM(AQ98:AS98) -> 3 | AU98: =IF(AT98=3,100,IF(AT98=2,70,IF(AT98=1,40,0))) -> 100
A99: 1.8 | B99: Коэффициент маневренности | C99: =IF('МСФО отчетность'!$E$71>=Подложка!C42,1,0) -> 1 | D99: =IF('МСФО отчетность'!$E$71>=Подложка!D42,1,0) -> 1 | E99: =IF('МСФО отчетность'!$E$71>=Подложка!E42,1,0) -> 1 | F99: =SUM(C99:E99) -> 3 | G99: =IF(F99=3,100,IF(F99=2,70,IF(F99=1,40,0))) -> 100 | H99: =IF('МСФО отчетность'!$E$71>=Подложка!H42,1,0) -> 1 | I99: =IF('МСФО отчетность'!$E$71>=Подложка!I42,1,0) -> 1 | J99: =IF('МСФО отчетность'!$E$71>=Подложка!J42,1,0) -> 1 | K99: =SUM(H99:J99) -> 3 | L99: =IF(K99=3,100,IF(K99=2,70,IF(K99=1,40,0))) -> 100 | M99: =IF('МСФО отчетность'!$E$71>=Подложка!M42,1,0) -> 1 | N99: =IF('МСФО отчетность'!$E$71>=Подложка!N42,1,0) -> 1 | O99: =IF('МСФО отчетность'!$E$71>=Подложка!O42,1,0) -> 1 | P99: =SUM(M99:O99) -> 3 | Q99: =IF(P99=3,100,IF(P99=2,70,IF(P99=1,40,0))) -> 100 | R99: =IF('МСФО отчетность'!$E$71>=Подложка!R42,1,0) -> 1 | S99: =IF('МСФО отчетность'!$E$71>=Подложка!S42,1,0) -> 1 | T99: =IF('МСФО отчетность'!$E$71>=Подложка!T42,1,0) -> 1 | U99: =SUM(R99:T99) -> 3 | V99: =IF(U99=3,100,IF(U99=2,70,IF(U99=1,40,0))) -> 100 | W99: =IF('МСФО отчетность'!$E$71>=Подложка!W42,1,0) -> 1 | X99: =IF('МСФО отчетность'!$E$71>=Подложка!X42,1,0) -> 1 | Y99: =IF('МСФО отчетность'!$E$71>=Подложка!Y42,1,0) -> 1 | Z99: =SUM(W99:Y99) -> 3 | AA99: =IF(Z99=3,100,IF(Z99=2,70,IF(Z99=1,40,0))) -> 100 | AB99: =IF('МСФО отчетность'!$E$71>=Подложка!AB42,1,0) -> 1 | AC99: =IF('МСФО отчетность'!$E$71>=Подложка!AC42,1,0) -> 1 | AD99: =IF('МСФО отчетность'!$E$71>=Подложка!AD42,1,0) -> 1 | AE99: =SUM(AB99:AD99) -> 3 | AF99: =IF(AE99=3,100,IF(AE99=2,70,IF(AE99=1,40,0))) -> 100 | AG99: =IF('МСФО отчетность'!$E$71>=Подложка!AG42,1,0) -> 1 | AH99: =IF('МСФО отчетность'!$E$71>=Подложка!AH42,1,0) -> 1 | AI99: =IF('МСФО отчетность'!$E$71>=Подложка!AI42,1,0) -> 1 | AJ99: =SUM(AG99:AI99) -> 3 | AK99: =IF(AJ99=3,100,IF(AJ99=2,70,IF(AJ99=1,40,0))) -> 100 | AL99: =IF('МСФО отчетность'!$E$71>=Подложка!AL42,1,0) -> 1 | AM99: =IF('МСФО отчетность'!$E$71>=Подложка!AM42,1,0) -> 1 | AN99: =IF('МСФО отчетность'!$E$71>=Подложка!AN42,1,0) -> 0 | AO99: =SUM(AL99:AN99) -> 2 | AP99: =IF(AO99=3,100,IF(AO99=2,70,IF(AO99=1,40,0))) -> 70 | AQ99: =IF('МСФО отчетность'!$E$71>=Подложка!AQ42,1,0) -> 1 | AR99: =IF('МСФО отчетность'!$E$71>=Подложка!AR42,1,0) -> 1 | AS99: =IF('МСФО отчетность'!$E$71>=Подложка!AS42,1,0) -> 0 | AT99: =SUM(AQ99:AS99) -> 2 | AU99: =IF(AT99=3,100,IF(AT99=2,70,IF(AT99=1,40,0))) -> 70
A100: 1.9 | B100: Рентабельность капитала | C100: =IF('МСФО отчетность'!$E$72>=Подложка!C43,1,0) -> 1 | D100: =IF('МСФО отчетность'!$E$72>=Подложка!D43,1,0) -> 1 | E100: =IF('МСФО отчетность'!$E$72>=Подложка!E43,1,0) -> 0 | F100: =SUM(C100:E100) -> 2 | G100: =IF(F100=3,100,IF(F100=2,70,IF(F100=1,40,0))) -> 70 | H100: =IF('МСФО отчетность'!$E$72>=Подложка!H43,1,0) -> 1 | I100: =IF('МСФО отчетность'!$E$72>=Подложка!I43,1,0) -> 1 | J100: =IF('МСФО отчетность'!$E$72>=Подложка!J43,1,0) -> 1 | K100: =SUM(H100:J100) -> 3 | L100: =IF(K100=3,100,IF(K100=2,70,IF(K100=1,40,0))) -> 100 | M100: =IF('МСФО отчетность'!$E$72>=Подложка!M43,1,0) -> 1 | N100: =IF('МСФО отчетность'!$E$72>=Подложка!N43,1,0) -> 1 | O100: =IF('МСФО отчетность'!$E$72>=Подложка!O43,1,0) -> 0 | P100: =SUM(M100:O100) -> 2 | Q100: =IF(P100=3,100,IF(P100=2,70,IF(P100=1,40,0))) -> 70 | R100: =IF('МСФО отчетность'!$E$72>=Подложка!R43,1,0) -> 1 | S100: =IF('МСФО отчетность'!$E$72>=Подложка!S43,1,0) -> 1 | T100: =IF('МСФО отчетность'!$E$72>=Подложка!T43,1,0) -> 0 | U100: =SUM(R100:T100) -> 2 | V100: =IF(U100=3,100,IF(U100=2,70,IF(U100=1,40,0))) -> 70 | W100: =IF('МСФО отчетность'!$E$72>=Подложка!W43,1,0) -> 1 | X100: =IF('МСФО отчетность'!$E$72>=Подложка!X43,1,0) -> 1 | Y100: =IF('МСФО отчетность'!$E$72>=Подложка!Y43,1,0) -> 0 | Z100: =SUM(W100:Y100) -> 2 | AA100: =IF(Z100=3,100,IF(Z100=2,70,IF(Z100=1,40,0))) -> 70 | AB100: =IF('МСФО отчетность'!$E$72>=Подложка!AB43,1,0) -> 1 | AC100: =IF('МСФО отчетность'!$E$72>=Подложка!AC43,1,0) -> 1 | AD100: =IF('МСФО отчетность'!$E$72>=Подложка!AD43,1,0) -> 0 | AE100: =SUM(AB100:AD100) -> 2 | AF100: =IF(AE100=3,100,IF(AE100=2,70,IF(AE100=1,40,0))) -> 70 | AG100: =IF('МСФО отчетность'!$E$72>=Подложка!AG43,1,0) -> 1 | AH100: =IF('МСФО отчетность'!$E$72>=Подложка!AH43,1,0) -> 1 | AI100: =IF('МСФО отчетность'!$E$72>=Подложка!AI43,1,0) -> 0 | AJ100: =SUM(AG100:AI100) -> 2 | AK100: =IF(AJ100=3,100,IF(AJ100=2,70,IF(AJ100=1,40,0))) -> 70 | AL100: =IF('МСФО отчетность'!$E$72>=Подложка!AL43,1,0) -> 1 | AM100: =IF('МСФО отчетность'!$E$72>=Подложка!AM43,1,0) -> 1 | AN100: =IF('МСФО отчетность'!$E$72>=Подложка!AN43,1,0) -> 0 | AO100: =SUM(AL100:AN100) -> 2 | AP100: =IF(AO100=3,100,IF(AO100=2,70,IF(AO100=1,40,0))) -> 70 | AQ100: =IF('МСФО отчетность'!$E$72>=Подложка!AQ43,1,0) -> 1 | AR100: =IF('МСФО отчетность'!$E$72>=Подложка!AR43,1,0) -> 1 | AS100: =IF('МСФО отчетность'!$E$72>=Подложка!AS43,1,0) -> 0 | AT100: =SUM(AQ100:AS100) -> 2 | AU100: =IF(AT100=3,100,IF(AT100=2,70,IF(AT100=1,40,0))) -> 70
A101: Период 1 | F101: Порог | G101: Балл | K101: Порог | L101: Балл | P101: Порог | Q101: Балл | U101: Порог | V101: Балл | Z101: Порог | AA101: Балл | AE101: Порог | AF101: Балл | AJ101: Порог | AK101: Балл | AO101: Порог | AP101: Балл | AT101: Порог | AU101: Балл
A102: 1.1 | B102: Коэффициент текущей ликвидности | C102: =IF('МСФО отчетность'!$F$64>=Подложка!C$35,1,0) -> 1 | D102: =IF('МСФО отчетность'!$F$64>=Подложка!D$35,1,0) -> 1 | E102: =IF('МСФО отчетность'!$F$64>=Подложка!E$35,1,0) -> 1 | F102: =SUM(C102:E102) -> 3 | G102: =IF(F102=3,100,IF(F102=2,70,IF(F102=1,40,0))) -> 100 | H102: =IF('МСФО отчетность'!$F$64>=Подложка!H$35,1,0) -> 1 | I102: =IF('МСФО отчетность'!$F$64>=Подложка!I$35,1,0) -> 1 | J102: =IF('МСФО отчетность'!$F$64>=Подложка!J$35,1,0) -> 1 | K102: =SUM(H102:J102) -> 3 | L102: =IF(K102=3,100,IF(K102=2,70,IF(K102=1,40,0))) -> 100 | M102: =IF('МСФО отчетность'!$F$64>=Подложка!M$35,1,0) -> 1 | N102: =IF('МСФО отчетность'!$F$64>=Подложка!N$35,1,0) -> 1 | O102: =IF('МСФО отчетность'!$F$64>=Подложка!O$35,1,0) -> 1 | P102: =SUM(M102:O102) -> 3 | Q102: =IF(P102=3,100,IF(P102=2,70,IF(P102=1,40,0))) -> 100 | R102: =IF('МСФО отчетность'!$F$64>=Подложка!R$35,1,0) -> 1 | S102: =IF('МСФО отчетность'!$F$64>=Подложка!S$35,1,0) -> 1 | T102: =IF('МСФО отчетность'!$F$64>=Подложка!T$35,1,0) -> 1 | U102: =SUM(R102:T102) -> 3 | V102: =IF(U102=3,100,IF(U102=2,70,IF(U102=1,40,0))) -> 100 | W102: =IF('МСФО отчетность'!$F$64>=Подложка!W$35,1,0) -> 1 | X102: =IF('МСФО отчетность'!$F$64>=Подложка!X$35,1,0) -> 1 | Y102: =IF('МСФО отчетность'!$F$64>=Подложка!Y$35,1,0) -> 1 | Z102: =SUM(W102:Y102) -> 3 | AA102: =IF(Z102=3,100,IF(Z102=2,70,IF(Z102=1,40,0))) -> 100 | AB102: =IF('МСФО отчетность'!$F$64>=Подложка!AB$35,1,0) -> 1 | AC102: =IF('МСФО отчетность'!$F$64>=Подложка!AC$35,1,0) -> 1 | AD102: =IF('МСФО отчетность'!$F$64>=Подложка!AD$35,1,0) -> 0 | AE102: =SUM(AB102:AD102) -> 2 | AF102: =IF(AE102=3,100,IF(AE102=2,70,IF(AE102=1,40,0))) -> 70 | AG102: =IF('МСФО отчетность'!$F$64>=Подложка!AG$35,1,0) -> 1 | AH102: =IF('МСФО отчетность'!$F$64>=Подложка!AH$35,1,0) -> 1 | AI102: =IF('МСФО отчетность'!$F$64>=Подложка!AI$35,1,0) -> 1 | AJ102: =SUM(AG102:AI102) -> 3 | AK102: =IF(AJ102=3,100,IF(AJ102=2,70,IF(AJ102=1,40,0))) -> 100 | AL102: =IF('МСФО отчетность'!$F$64>=Подложка!AL$35,1,0) -> 1 | AM102: =IF('МСФО отчетность'!$F$64>=Подложка!AM$35,1,0) -> 1 | AN102: =IF('МСФО отчетность'!$F$64>=Подложка!AN$35,1,0) -> 0 | AO102: =SUM(AL102:AN102) -> 2 | AP102: =IF(AO102=3,100,IF(AO102=2,70,IF(AO102=1,40,0))) -> 70 | AQ102: =IF('МСФО отчетность'!$F$64>=Подложка!AQ$35,1,0) -> 1 | AR102: =IF('МСФО отчетность'!$F$64>=Подложка!AR$35,1,0) -> 1 | AS102: =IF('МСФО отчетность'!$F$64>=Подложка!AS$35,1,0) -> 0 | AT102: =SUM(AQ102:AS102) -> 2 | AU102: =IF(AT102=3,100,IF(AT102=2,70,IF(AT102=1,40,0))) -> 70
A103: 1.2 | B103: Коэффициент быстрой ликвидности | C103: =IF('МСФО отчетность'!$F$65>=Подложка!C$36,1,0) -> 1 | D103: =IF('МСФО отчетность'!$F$65>=Подложка!D$36,1,0) -> 1 | E103: =IF('МСФО отчетность'!$F$65>=Подложка!E$36,1,0) -> 1 | F103: =SUM(C103:E103) -> 3 | G103: =IF(F103=3,100,IF(F103=2,70,IF(F103=1,40,0))) -> 100 | H103: =IF('МСФО отчетность'!$F$65>=Подложка!H$36,1,0) -> 1 | I103: =IF('МСФО отчетность'!$F$65>=Подложка!I$36,1,0) -> 1 | J103: =IF('МСФО отчетность'!$F$65>=Подложка!J$36,1,0) -> 1 | K103: =SUM(H103:J103) -> 3 | L103: =IF(K103=3,100,IF(K103=2,70,IF(K103=1,40,0))) -> 100 | M103: =IF('МСФО отчетность'!$F$65>=Подложка!M$36,1,0) -> 1 | N103: =IF('МСФО отчетность'!$F$65>=Подложка!N$36,1,0) -> 1 | O103: =IF('МСФО отчетность'!$F$65>=Подложка!O$36,1,0) -> 1 | P103: =SUM(M103:O103) -> 3 | Q103: =IF(P103=3,100,IF(P103=2,70,IF(P103=1,40,0))) -> 100 | R103: =IF('МСФО отчетность'!$F$65>=Подложка!R$36,1,0) -> 1 | S103: =IF('МСФО отчетность'!$F$65>=Подложка!S$36,1,0) -> 1 | T103: =IF('МСФО отчетность'!$F$65>=Подложка!T$36,1,0) -> 1 | U103: =SUM(R103:T103) -> 3 | V103: =IF(U103=3,100,IF(U103=2,70,IF(U103=1,40,0))) -> 100 | W103: =IF('МСФО отчетность'!$F$65>=Подложка!W$36,1,0) -> 1 | X103: =IF('МСФО отчетность'!$F$65>=Подложка!X$36,1,0) -> 1 | Y103: =IF('МСФО отчетность'!$F$65>=Подложка!Y$36,1,0) -> 1 | Z103: =SUM(W103:Y103) -> 3 | AA103: =IF(Z103=3,100,IF(Z103=2,70,IF(Z103=1,40,0))) -> 100 | AB103: =IF('МСФО отчетность'!$F$65>=Подложка!AB$36,1,0) -> 1 | AC103: =IF('МСФО отчетность'!$F$65>=Подложка!AC$36,1,0) -> 1 | AD103: =IF('МСФО отчетность'!$F$65>=Подложка!AD$36,1,0) -> 0 | AE103: =SUM(AB103:AD103) -> 2 | AF103: =IF(AE103=3,100,IF(AE103=2,70,IF(AE103=1,40,0))) -> 70 | AG103: =IF('МСФО отчетность'!$F$65>=Подложка!AG$36,1,0) -> 1 | AH103: =IF('МСФО отчетность'!$F$65>=Подложка!AH$36,1,0) -> 1 | AI103: =IF('МСФО отчетность'!$F$65>=Подложка!AI$36,1,0) -> 0 | AJ103: =SUM(AG103:AI103) -> 2 | AK103: =IF(AJ103=3,100,IF(AJ103=2,70,IF(AJ103=1,40,0))) -> 70 | AL103: =IF('МСФО отчетность'!$F$65>=Подложка!AL$36,1,0) -> 1 | AM103: =IF('МСФО отчетность'!$F$65>=Подложка!AM$36,1,0) -> 1 | AN103: =IF('МСФО отчетность'!$F$65>=Подложка!AN$36,1,0) -> 0 | AO103: =SUM(AL103:AN103) -> 2 | AP103: =IF(AO103=3,100,IF(AO103=2,70,IF(AO103=1,40,0))) -> 70 | AQ103: =IF('МСФО отчетность'!$F$65>=Подложка!AQ$36,1,0) -> 1 | AR103: =IF('МСФО отчетность'!$F$65>=Подложка!AR$36,1,0) -> 1 | AS103: =IF('МСФО отчетность'!$F$65>=Подложка!AS$36,1,0) -> 0 | AT103: =SUM(AQ103:AS103) -> 2 | AU103: =IF(AT103=3,100,IF(AT103=2,70,IF(AT103=1,40,0))) -> 70
A104: 1.3 | B104: Длительность операционного цикла | C104: =IF('МСФО отчетность'!$F$66<Подложка!C$37,1,0) -> 0 | D104: =IF('МСФО отчетность'!$F$66<Подложка!D$37,1,0) -> 0 | E104: =IF('МСФО отчетность'!$F$66<Подложка!E$37,1,0) -> 0 | F104: =SUM(C104:E104) -> 0 | G104: =IF(F104=3,100,IF(F104=2,70,IF(F104=1,40,0))) -> 0 | H104: =IF('МСФО отчетность'!$F$66<Подложка!H$37,1,0) -> 0 | I104: =IF('МСФО отчетность'!$F$66<Подложка!I$37,1,0) -> 0 | J104: =IF('МСФО отчетность'!$F$66<Подложка!J$37,1,0) -> 0 | K104: =SUM(H104:J104) -> 0 | L104: =IF(K104=3,100,IF(K104=2,70,IF(K104=1,40,0))) -> 0 | M104: =IF('МСФО отчетность'!$F$66<Подложка!M$37,1,0) -> 0 | N104: =IF('МСФО отчетность'!$F$66<Подложка!N$37,1,0) -> 0 | O104: =IF('МСФО отчетность'!$F$66<Подложка!O$37,1,0) -> 0 | P104: =SUM(M104:O104) -> 0 | Q104: =IF(P104=3,100,IF(P104=2,70,IF(P104=1,40,0))) -> 0 | R104: =IF('МСФО отчетность'!$F$66<Подложка!R$37,1,0) -> 0 | S104: =IF('МСФО отчетность'!$F$66<Подложка!S$37,1,0) -> 0 | T104: =IF('МСФО отчетность'!$F$66<Подложка!T$37,1,0) -> 0 | U104: =SUM(R104:T104) -> 0 | V104: =IF(U104=3,100,IF(U104=2,70,IF(U104=1,40,0))) -> 0 | W104: =IF('МСФО отчетность'!$F$66<Подложка!W$37,1,0) -> 0 | X104: =IF('МСФО отчетность'!$F$66<Подложка!X$37,1,0) -> 0 | Y104: =IF('МСФО отчетность'!$F$66<Подложка!Y$37,1,0) -> 0 | Z104: =SUM(W104:Y104) -> 0 | AA104: =IF(Z104=3,100,IF(Z104=2,70,IF(Z104=1,40,0))) -> 0 | AB104: =IF('МСФО отчетность'!$F$66<Подложка!AB$37,1,0) -> 0 | AC104: =IF('МСФО отчетность'!$F$66<Подложка!AC$37,1,0) -> 0 | AD104: =IF('МСФО отчетность'!$F$66<Подложка!AD$37,1,0) -> 0 | AE104: =SUM(AB104:AD104) -> 0 | AF104: =IF(AE104=3,100,IF(AE104=2,70,IF(AE104=1,40,0))) -> 0 | AG104: =IF('МСФО отчетность'!$F$66<Подложка!AG$37,1,0) -> 0 | AH104: =IF('МСФО отчетность'!$F$66<Подложка!AH$37,1,0) -> 0 | AI104: =IF('МСФО отчетность'!$F$66<Подложка!AI$37,1,0) -> 0 | AJ104: =SUM(AG104:AI104) -> 0 | AK104: =IF(AJ104=3,100,IF(AJ104=2,70,IF(AJ104=1,40,0))) -> 0 | AL104: =IF('МСФО отчетность'!$F$66<Подложка!AL$37,1,0) -> 0 | AM104: =IF('МСФО отчетность'!$F$66<Подложка!AM$37,1,0) -> 0 | AN104: =IF('МСФО отчетность'!$F$66<Подложка!AN$37,1,0) -> 0 | AO104: =SUM(AL104:AN104) -> 0 | AP104: =IF(AO104=3,100,IF(AO104=2,70,IF(AO104=1,40,0))) -> 0 | AQ104: =IF('МСФО отчетность'!$F$66<Подложка!AQ$37,1,0) -> 0 | AR104: =IF('МСФО отчетность'!$F$66<Подложка!AR$37,1,0) -> 0 | AS104: =IF('МСФО отчетность'!$F$66<Подложка!AS$37,1,0) -> 0 | AT104: =SUM(AQ104:AS104) -> 0 | AU104: =IF(AT104=3,100,IF(AT104=2,70,IF(AT104=1,40,0))) -> 0
A105: 1.4 | B105: Коэффициент автономии | C105: =IF('МСФО отчетность'!$F$67>=Подложка!C$38,1,0) -> 1 | D105: =IF('МСФО отчетность'!$F$67>=Подложка!D$38,1,0) -> 1 | E105: =IF('МСФО отчетность'!$F$67>=Подложка!E$38,1,0) -> 1 | F105: =SUM(C105:E105) -> 3 | G105: =IF(F105=3,100,IF(F105=2,70,IF(F105=1,40,0))) -> 100 | H105: =IF('МСФО отчетность'!$F$67>=Подложка!H$38,1,0) -> 1 | I105: =IF('МСФО отчетность'!$F$67>=Подложка!I$38,1,0) -> 1 | J105: =IF('МСФО отчетность'!$F$67>=Подложка!J$38,1,0) -> 0 | K105: =SUM(H105:J105) -> 2 | L105: =IF(K105=3,100,IF(K105=2,70,IF(K105=1,40,0))) -> 70 | M105: =IF('МСФО отчетность'!$F$67>=Подложка!M$38,1,0) -> 1 | N105: =IF('МСФО отчетность'!$F$67>=Подложка!N$38,1,0) -> 1 | O105: =IF('МСФО отчетность'!$F$67>=Подложка!O$38,1,0) -> 1 | P105: =SUM(M105:O105) -> 3 | Q105: =IF(P105=3,100,IF(P105=2,70,IF(P105=1,40,0))) -> 100 | R105: =IF('МСФО отчетность'!$F$67>=Подложка!R$38,1,0) -> 1 | S105: =IF('МСФО отчетность'!$F$67>=Подложка!S$38,1,0) -> 1 | T105: =IF('МСФО отчетность'!$F$67>=Подложка!T$38,1,0) -> 1 | U105: =SUM(R105:T105) -> 3 | V105: =IF(U105=3,100,IF(U105=2,70,IF(U105=1,40,0))) -> 100 | W105: =IF('МСФО отчетность'!$F$67>=Подложка!W$38,1,0) -> 1 | X105: =IF('МСФО отчетность'!$F$67>=Подложка!X$38,1,0) -> 1 | Y105: =IF('МСФО отчетность'!$F$67>=Подложка!Y$38,1,0) -> 0 | Z105: =SUM(W105:Y105) -> 2 | AA105: =IF(Z105=3,100,IF(Z105=2,70,IF(Z105=1,40,0))) -> 70 | AB105: =IF('МСФО отчетность'!$F$67>=Подложка!AB$38,1,0) -> 1 | AC105: =IF('МСФО отчетность'!$F$67>=Подложка!AC$38,1,0) -> 1 | AD105: =IF('МСФО отчетность'!$F$67>=Подложка!AD$38,1,0) -> 0 | AE105: =SUM(AB105:AD105) -> 2 | AF105: =IF(AE105=3,100,IF(AE105=2,70,IF(AE105=1,40,0))) -> 70 | AG105: =IF('МСФО отчетность'!$F$67>=Подложка!AG$38,1,0) -> 1 | AH105: =IF('МСФО отчетность'!$F$67>=Подложка!AH$38,1,0) -> 1 | AI105: =IF('МСФО отчетность'!$F$67>=Подложка!AI$38,1,0) -> 0 | AJ105: =SUM(AG105:AI105) -> 2 | AK105: =IF(AJ105=3,100,IF(AJ105=2,70,IF(AJ105=1,40,0))) -> 70 | AL105: =IF('МСФО отчетность'!$F$67>=Подложка!AL$38,1,0) -> 1 | AM105: =IF('МСФО отчетность'!$F$67>=Подложка!AM$38,1,0) -> 1 | AN105: =IF('МСФО отчетность'!$F$67>=Подложка!AN$38,1,0) -> 0 | AO105: =SUM(AL105:AN105) -> 2 | AP105: =IF(AO105=3,100,IF(AO105=2,70,IF(AO105=1,40,0))) -> 70 | AQ105: =IF('МСФО отчетность'!$F$67>=Подложка!AQ$38,1,0) -> 1 | AR105: =IF('МСФО отчетность'!$F$67>=Подложка!AR$38,1,0) -> 1 | AS105: =IF('МСФО отчетность'!$F$67>=Подложка!AS$38,1,0) -> 0 | AT105: =SUM(AQ105:AS105) -> 2 | AU105: =IF(AT105=3,100,IF(AT105=2,70,IF(AT105=1,40,0))) -> 70
A106: 1.5 | B106: Рентабельность продаж | C106: =IF('МСФО отчетность'!$F$68>=Подложка!C$39,1,0) -> 1 | D106: =IF('МСФО отчетность'!$F$68>=Подложка!D$39,1,0) -> 1 | E106: =IF('МСФО отчетность'!$F$68>=Подложка!E$39,1,0) -> 1 | F106: =SUM(C106:E106) -> 3 | G106: =IF(F106=3,100,IF(F106=2,70,IF(F106=1,40,0))) -> 100 | H106: =IF('МСФО отчетность'!$F$68>=Подложка!H$39,1,0) -> 1 | I106: =IF('МСФО отчетность'!$F$68>=Подложка!I$39,1,0) -> 1 | J106: =IF('МСФО отчетность'!$F$68>=Подложка!J$39,1,0) -> 1 | K106: =SUM(H106:J106) -> 3 | L106: =IF(K106=3,100,IF(K106=2,70,IF(K106=1,40,0))) -> 100 | M106: =IF('МСФО отчетность'!$F$68>=Подложка!M$39,1,0) -> 1 | N106: =IF('МСФО отчетность'!$F$68>=Подложка!N$39,1,0) -> 1 | O106: =IF('МСФО отчетность'!$F$68>=Подложка!O$39,1,0) -> 1 | P106: =SUM(M106:O106) -> 3 | Q106: =IF(P106=3,100,IF(P106=2,70,IF(P106=1,40,0))) -> 100 | R106: =IF('МСФО отчетность'!$F$68>=Подложка!R$39,1,0) -> 1 | S106: =IF('МСФО отчетность'!$F$68>=Подложка!S$39,1,0) -> 1 | T106: =IF('МСФО отчетность'!$F$68>=Подложка!T$39,1,0) -> 1 | U106: =SUM(R106:T106) -> 3 | V106: =IF(U106=3,100,IF(U106=2,70,IF(U106=1,40,0))) -> 100 | W106: =IF('МСФО отчетность'!$F$68>=Подложка!W$39,1,0) -> 1 | X106: =IF('МСФО отчетность'!$F$68>=Подложка!X$39,1,0) -> 1 | Y106: =IF('МСФО отчетность'!$F$68>=Подложка!Y$39,1,0) -> 1 | Z106: =SUM(W106:Y106) -> 3 | AA106: =IF(Z106=3,100,IF(Z106=2,70,IF(Z106=1,40,0))) -> 100 | AB106: =IF('МСФО отчетность'!$F$68>=Подложка!AB$39,1,0) -> 1 | AC106: =IF('МСФО отчетность'!$F$68>=Подложка!AC$39,1,0) -> 1 | AD106: =IF('МСФО отчетность'!$F$68>=Подложка!AD$39,1,0) -> 1 | AE106: =SUM(AB106:AD106) -> 3 | AF106: =IF(AE106=3,100,IF(AE106=2,70,IF(AE106=1,40,0))) -> 100 | AG106: =IF('МСФО отчетность'!$F$68>=Подложка!AG$39,1,0) -> 1 | AH106: =IF('МСФО отчетность'!$F$68>=Подложка!AH$39,1,0) -> 1 | AI106: =IF('МСФО отчетность'!$F$68>=Подложка!AI$39,1,0) -> 1 | AJ106: =SUM(AG106:AI106) -> 3 | AK106: =IF(AJ106=3,100,IF(AJ106=2,70,IF(AJ106=1,40,0))) -> 100 | AL106: =IF('МСФО отчетность'!$F$68>=Подложка!AL$39,1,0) -> 1 | AM106: =IF('МСФО отчетность'!$F$68>=Подложка!AM$39,1,0) -> 1 | AN106: =IF('МСФО отчетность'!$F$68>=Подложка!AN$39,1,0) -> 0 | AO106: =SUM(AL106:AN106) -> 2 | AP106: =IF(AO106=3,100,IF(AO106=2,70,IF(AO106=1,40,0))) -> 70 | AQ106: =IF('МСФО отчетность'!$F$68>=Подложка!AQ$39,1,0) -> 1 | AR106: =IF('МСФО отчетность'!$F$68>=Подложка!AR$39,1,0) -> 1 | AS106: =IF('МСФО отчетность'!$F$68>=Подложка!AS$39,1,0) -> 1 | AT106: =SUM(AQ106:AS106) -> 3 | AU106: =IF(AT106=3,100,IF(AT106=2,70,IF(AT106=1,40,0))) -> 100
A107: 1.6 | B107: Коэффициент долговой нагрузки | C107: =IF('МСФО отчетность'!$F$69<Подложка!C$40,1,0) -> 1 | D107: =IF('МСФО отчетность'!$F$69<Подложка!D$40,1,0) -> 1 | E107: =IF('МСФО отчетность'!$F$69<Подложка!E$40,1,0) -> 0 | F107: =SUM(C107:E107) -> 2 | G107: =IF(F107=3,100,IF(F107=2,70,IF(F107=1,40,0))) -> 70 | H107: =IF('МСФО отчетность'!$F$69<Подложка!H$40,1,0) -> 1 | I107: =IF('МСФО отчетность'!$F$69<Подложка!I$40,1,0) -> 1 | J107: =IF('МСФО отчетность'!$F$69<Подложка!J$40,1,0) -> 0 | K107: =SUM(H107:J107) -> 2 | L107: =IF(K107=3,100,IF(K107=2,70,IF(K107=1,40,0))) -> 70 | M107: =IF('МСФО отчетность'!$F$69<Подложка!M$40,1,0) -> 1 | N107: =IF('МСФО отчетность'!$F$69<Подложка!N$40,1,0) -> 1 | O107: =IF('МСФО отчетность'!$F$69<Подложка!O$40,1,0) -> 1 | P107: =SUM(M107:O107) -> 3 | Q107: =IF(P107=3,100,IF(P107=2,70,IF(P107=1,40,0))) -> 100 | R107: =IF('МСФО отчетность'!$F$69<Подложка!R$40,1,0) -> 1 | S107: =IF('МСФО отчетность'!$F$69<Подложка!S$40,1,0) -> 1 | T107: =IF('МСФО отчетность'!$F$69<Подложка!T$40,1,0) -> 1 | U107: =SUM(R107:T107) -> 3 | V107: =IF(U107=3,100,IF(U107=2,70,IF(U107=1,40,0))) -> 100 | W107: =IF('МСФО отчетность'!$F$69<Подложка!W$40,1,0) -> 1 | X107: =IF('МСФО отчетность'!$F$69<Подложка!X$40,1,0) -> 1 | Y107: =IF('МСФО отчетность'!$F$69<Подложка!Y$40,1,0) -> 0 | Z107: =SUM(W107:Y107) -> 2 | AA107: =IF(Z107=3,100,IF(Z107=2,70,IF(Z107=1,40,0))) -> 70 | AB107: =IF('МСФО отчетность'!$F$69<Подложка!AB$40,1,0) -> 1 | AC107: =IF('МСФО отчетность'!$F$69<Подложка!AC$40,1,0) -> 1 | AD107: =IF('МСФО отчетность'!$F$69<Подложка!AD$40,1,0) -> 0 | AE107: =SUM(AB107:AD107) -> 2 | AF107: =IF(AE107=3,100,IF(AE107=2,70,IF(AE107=1,40,0))) -> 70 | AG107: =IF('МСФО отчетность'!$F$69<Подложка!AG$40,1,0) -> 1 | AH107: =IF('МСФО отчетность'!$F$69<Подложка!AH$40,1,0) -> 1 | AI107: =IF('МСФО отчетность'!$F$69<Подложка!AI$40,1,0) -> 0 | AJ107: =SUM(AG107:AI107) -> 2 | AK107: =IF(AJ107=3,100,IF(AJ107=2,70,IF(AJ107=1,40,0))) -> 70 | AL107: =IF('МСФО отчетность'!$F$69<Подложка!AL$40,1,0) -> 1 | AM107: =IF('МСФО отчетность'!$F$69<Подложка!AM$40,1,0) -> 1 | AN107: =IF('МСФО отчетность'!$F$69<Подложка!AN$40,1,0) -> 0 | AO107: =SUM(AL107:AN107) -> 2 | AP107: =IF(AO107=3,100,IF(AO107=2,70,IF(AO107=1,40,0))) -> 70 | AQ107: =IF('МСФО отчетность'!$F$69<Подложка!AQ$40,1,0) -> 1 | AR107: =IF('МСФО отчетность'!$F$69<Подложка!AR$40,1,0) -> 1 | AS107: =IF('МСФО отчетность'!$F$69<Подложка!AS$40,1,0) -> 0 | AT107: =SUM(AQ107:AS107) -> 2 | AU107: =IF(AT107=3,100,IF(AT107=2,70,IF(AT107=1,40,0))) -> 70
A108: 1.7 | B108: Коэффициент покрытия процентов | C108: =IF('МСФО отчетность'!$F$70>=Подложка!C41,1,0) -> 1 | D108: =IF('МСФО отчетность'!$F$70>=Подложка!D41,1,0) -> 1 | E108: =IF('МСФО отчетность'!$F$70>=Подложка!E41,1,0) -> 1 | F108: =SUM(C108:E108) -> 3 | G108: =IF(F108=3,100,IF(F108=2,70,IF(F108=1,40,0))) -> 100 | H108: =IF('МСФО отчетность'!$F$70>=Подложка!H41,1,0) -> 1 | I108: =IF('МСФО отчетность'!$F$70>=Подложка!I41,1,0) -> 1 | J108: =IF('МСФО отчетность'!$F$70>=Подложка!J41,1,0) -> 1 | K108: =SUM(H108:J108) -> 3 | L108: =IF(K108=3,100,IF(K108=2,70,IF(K108=1,40,0))) -> 100 | M108: =IF('МСФО отчетность'!$F$70>=Подложка!M41,1,0) -> 1 | N108: =IF('МСФО отчетность'!$F$70>=Подложка!N41,1,0) -> 1 | O108: =IF('МСФО отчетность'!$F$70>=Подложка!O41,1,0) -> 1 | P108: =SUM(M108:O108) -> 3 | Q108: =IF(P108=3,100,IF(P108=2,70,IF(P108=1,40,0))) -> 100 | R108: =IF('МСФО отчетность'!$F$70>=Подложка!R41,1,0) -> 1 | S108: =IF('МСФО отчетность'!$F$70>=Подложка!S41,1,0) -> 1 | T108: =IF('МСФО отчетность'!$F$70>=Подложка!T41,1,0) -> 1 | U108: =SUM(R108:T108) -> 3 | V108: =IF(U108=3,100,IF(U108=2,70,IF(U108=1,40,0))) -> 100 | W108: =IF('МСФО отчетность'!$F$70>=Подложка!W41,1,0) -> 1 | X108: =IF('МСФО отчетность'!$F$70>=Подложка!X41,1,0) -> 1 | Y108: =IF('МСФО отчетность'!$F$70>=Подложка!Y41,1,0) -> 1 | Z108: =SUM(W108:Y108) -> 3 | AA108: =IF(Z108=3,100,IF(Z108=2,70,IF(Z108=1,40,0))) -> 100 | AB108: =IF('МСФО отчетность'!$F$70>=Подложка!AB41,1,0) -> 1 | AC108: =IF('МСФО отчетность'!$F$70>=Подложка!AC41,1,0) -> 1 | AD108: =IF('МСФО отчетность'!$F$70>=Подложка!AD41,1,0) -> 1 | AE108: =SUM(AB108:AD108) -> 3 | AF108: =IF(AE108=3,100,IF(AE108=2,70,IF(AE108=1,40,0))) -> 100 | AG108: =IF('МСФО отчетность'!$F$70>=Подложка!AG41,1,0) -> 1 | AH108: =IF('МСФО отчетность'!$F$70>=Подложка!AH41,1,0) -> 1 | AI108: =IF('МСФО отчетность'!$F$70>=Подложка!AI41,1,0) -> 1 | AJ108: =SUM(AG108:AI108) -> 3 | AK108: =IF(AJ108=3,100,IF(AJ108=2,70,IF(AJ108=1,40,0))) -> 100 | AL108: =IF('МСФО отчетность'!$F$70>=Подложка!AL41,1,0) -> 1 | AM108: =IF('МСФО отчетность'!$F$70>=Подложка!AM41,1,0) -> 1 | AN108: =IF('МСФО отчетность'!$F$70>=Подложка!AN41,1,0) -> 1 | AO108: =SUM(AL108:AN108) -> 3 | AP108: =IF(AO108=3,100,IF(AO108=2,70,IF(AO108=1,40,0))) -> 100 | AQ108: =IF('МСФО отчетность'!$F$70>=Подложка!AQ41,1,0) -> 1 | AR108: =IF('МСФО отчетность'!$F$70>=Подложка!AR41,1,0) -> 1 | AS108: =IF('МСФО отчетность'!$F$70>=Подложка!AS41,1,0) -> 1 | AT108: =SUM(AQ108:AS108) -> 3 | AU108: =IF(AT108=3,100,IF(AT108=2,70,IF(AT108=1,40,0))) -> 100
A109: 1.8 | B109: Коэффициент маневренности | C109: =IF('МСФО отчетность'!$F$71>=Подложка!C52,1,0) -> 0 | D109: =IF('МСФО отчетность'!$F$71>=Подложка!D52,1,0) -> 0 | E109: =IF('МСФО отчетность'!$F$71>=Подложка!E52,1,0) -> 0 | F109: =SUM(C109:E109) -> 0 | G109: =IF(F109=3,100,IF(F109=2,70,IF(F109=1,40,0))) -> 0 | H109: =IF('МСФО отчетность'!$F$71>=Подложка!H52,1,0) -> 0 | I109: =IF('МСФО отчетность'!$F$71>=Подложка!I52,1,0) -> 0 | J109: =IF('МСФО отчетность'!$F$71>=Подложка!J52,1,0) -> 0 | K109: =SUM(H109:J109) -> 0 | L109: =IF(K109=3,100,IF(K109=2,70,IF(K109=1,40,0))) -> 0 | M109: =IF('МСФО отчетность'!$F$71>=Подложка!M52,1,0) -> 0 | N109: =IF('МСФО отчетность'!$F$71>=Подложка!N52,1,0) -> 0 | O109: =IF('МСФО отчетность'!$F$71>=Подложка!O52,1,0) -> 0 | P109: =SUM(M109:O109) -> 0 | Q109: =IF(P109=3,100,IF(P109=2,70,IF(P109=1,40,0))) -> 0 | R109: =IF('МСФО отчетность'!$F$71>=Подложка!R52,1,0) -> 0 | S109: =IF('МСФО отчетность'!$F$71>=Подложка!S52,1,0) -> 0 | T109: =IF('МСФО отчетность'!$F$71>=Подложка!T52,1,0) -> 0 | U109: =SUM(R109:T109) -> 0 | V109: =IF(U109=3,100,IF(U109=2,70,IF(U109=1,40,0))) -> 0 | W109: =IF('МСФО отчетность'!$F$71>=Подложка!W52,1,0) -> 0 | X109: =IF('МСФО отчетность'!$F$71>=Подложка!X52,1,0) -> 0 | Y109: =IF('МСФО отчетность'!$F$71>=Подложка!Y52,1,0) -> 0 | Z109: =SUM(W109:Y109) -> 0 | AA109: =IF(Z109=3,100,IF(Z109=2,70,IF(Z109=1,40,0))) -> 0 | AB109: =IF('МСФО отчетность'!$F$71>=Подложка!AB52,1,0) -> 0 | AC109: =IF('МСФО отчетность'!$F$71>=Подложка!AC52,1,0) -> 0 | AD109: =IF('МСФО отчетность'!$F$71>=Подложка!AD52,1,0) -> 0 | AE109: =SUM(AB109:AD109) -> 0 | AF109: =IF(AE109=3,100,IF(AE109=2,70,IF(AE109=1,40,0))) -> 0 | AG109: =IF('МСФО отчетность'!$F$71>=Подложка!AG52,1,0) -> 0 | AH109: =IF('МСФО отчетность'!$F$71>=Подложка!AH52,1,0) -> 0 | AI109: =IF('МСФО отчетность'!$F$71>=Подложка!AI52,1,0) -> 0 | AJ109: =SUM(AG109:AI109) -> 0 | AK109: =IF(AJ109=3,100,IF(AJ109=2,70,IF(AJ109=1,40,0))) -> 0 | AL109: =IF('МСФО отчетность'!$F$71>=Подложка!AL52,1,0) -> 0 | AM109: =IF('МСФО отчетность'!$F$71>=Подложка!AM52,1,0) -> 0 | AN109: =IF('МСФО отчетность'!$F$71>=Подложка!AN52,1,0) -> 1 | AO109: =SUM(AL109:AN109) -> 1 | AP109: =IF(AO109=3,100,IF(AO109=2,70,IF(AO109=1,40,0))) -> 40 | AQ109: =IF('МСФО отчетность'!$F$71>=Подложка!AQ52,1,0) -> 0 | AR109: =IF('МСФО отчетность'!$F$71>=Подложка!AR52,1,0) -> 0 | AS109: =IF('МСФО отчетность'!$F$71>=Подложка!AS52,1,0) -> 1 | AT109: =SUM(AQ109:AS109) -> 1 | AU109: =IF(AT109=3,100,IF(AT109=2,70,IF(AT109=1,40,0))) -> 40
A110: 1.9 | B110: Рентабельность капитала | C110: =IF('МСФО отчетность'!$F$72>=Подложка!C53,1,0) -> 1 | D110: =IF('МСФО отчетность'!$F$72>=Подложка!D53,1,0) -> 1 | E110: =IF('МСФО отчетность'!$F$72>=Подложка!E53,1,0) -> 1 | F110: =SUM(C110:E110) -> 3 | G110: =IF(F110=3,100,IF(F110=2,70,IF(F110=1,40,0))) -> 100 | H110: =IF('МСФО отчетность'!$F$72>=Подложка!H53,1,0) -> 1 | I110: =IF('МСФО отчетность'!$F$72>=Подложка!I53,1,0) -> 1 | J110: =IF('МСФО отчетность'!$F$72>=Подложка!J53,1,0) -> 1 | K110: =SUM(H110:J110) -> 3 | L110: =IF(K110=3,100,IF(K110=2,70,IF(K110=1,40,0))) -> 100 | M110: =IF('МСФО отчетность'!$F$72>=Подложка!M53,1,0) -> 1 | N110: =IF('МСФО отчетность'!$F$72>=Подложка!N53,1,0) -> 1 | O110: =IF('МСФО отчетность'!$F$72>=Подложка!O53,1,0) -> 1 | P110: =SUM(M110:O110) -> 3 | Q110: =IF(P110=3,100,IF(P110=2,70,IF(P110=1,40,0))) -> 100 | R110: =IF('МСФО отчетность'!$F$72>=Подложка!R53,1,0) -> 1 | S110: =IF('МСФО отчетность'!$F$72>=Подложка!S53,1,0) -> 1 | T110: =IF('МСФО отчетность'!$F$72>=Подложка!T53,1,0) -> 1 | U110: =SUM(R110:T110) -> 3 | V110: =IF(U110=3,100,IF(U110=2,70,IF(U110=1,40,0))) -> 100 | W110: =IF('МСФО отчетность'!$F$72>=Подложка!W53,1,0) -> 1 | X110: =IF('МСФО отчетность'!$F$72>=Подложка!X53,1,0) -> 1 | Y110: =IF('МСФО отчетность'!$F$72>=Подложка!Y53,1,0) -> 1 | Z110: =SUM(W110:Y110) -> 3 | AA110: =IF(Z110=3,100,IF(Z110=2,70,IF(Z110=1,40,0))) -> 100 | AB110: =IF('МСФО отчетность'!$F$72>=Подложка!AB53,1,0) -> 1 | AC110: =IF('МСФО отчетность'!$F$72>=Подложка!AC53,1,0) -> 1 | AD110: =IF('МСФО отчетность'!$F$72>=Подложка!AD53,1,0) -> 1 | AE110: =SUM(AB110:AD110) -> 3 | AF110: =IF(AE110=3,100,IF(AE110=2,70,IF(AE110=1,40,0))) -> 100 | AG110: =IF('МСФО отчетность'!$F$72>=Подложка!AG53,1,0) -> 1 | AH110: =IF('МСФО отчетность'!$F$72>=Подложка!AH53,1,0) -> 1 | AI110: =IF('МСФО отчетность'!$F$72>=Подложка!AI53,1,0) -> 1 | AJ110: =SUM(AG110:AI110) -> 3 | AK110: =IF(AJ110=3,100,IF(AJ110=2,70,IF(AJ110=1,40,0))) -> 100 | AL110: =IF('МСФО отчетность'!$F$72>=Подложка!AL53,1,0) -> 1 | AM110: =IF('МСФО отчетность'!$F$72>=Подложка!AM53,1,0) -> 1 | AN110: =IF('МСФО отчетность'!$F$72>=Подложка!AN53,1,0) -> 1 | AO110: =SUM(AL110:AN110) -> 3 | AP110: =IF(AO110=3,100,IF(AO110=2,70,IF(AO110=1,40,0))) -> 100 | AQ110: =IF('МСФО отчетность'!$F$72>=Подложка!AQ53,1,0) -> 1 | AR110: =IF('МСФО отчетность'!$F$72>=Подложка!AR53,1,0) -> 1 | AS110: =IF('МСФО отчетность'!$F$72>=Подложка!AS53,1,0) -> 1 | AT110: =SUM(AQ110:AS110) -> 3 | AU110: =IF(AT110=3,100,IF(AT110=2,70,IF(AT110=1,40,0))) -> 100
A120: Расчет группы кредитоспособности МСФО | C120: Коды ОКВЭД 41-43, 71 | H120: Коды ОКВЭД 06, 49.5, 09, 19.2 | M120: Коды ОКВЭД 49-53, за искл. 49.5, 51, 50 | R120: Коды ОКВЭД 45-47 | W120: Коды ОКВЭД 05, 07-08, 10-33, 35, за искл.19.2 | AB120: Коды ОКВЭД 51 | AG120: Коды ОКВЭД 50 | AL120: Остальные коды ОКВЭД | AQ120: Коды ОКВЭД 62-63
C121: Строительство | H121: Добыча, переработка и транспортировка газа, нефти и нефтепродуктов | M121: Транспортировка и хранение | R121: Торговля | W121: Производство | AB121: Авиакомпания | AG121: Судовладелец | AL121: Прочие | AQ121: ИТ
B122: Группа кредитоспособности | C122: 3 группа | D122: 2 группа | E122: 1 группа | H122: 3 группа | I122: 2 группа | J122: 1 группа | M122: 3 группа | N122: 2 группа | O122: 1 группа | R122: 3 группа | S122: 2 группа | T122: 1 группа | W122: 3 группа | X122: 2 группа | Y122: 1 группа | AB122: 3 группа | AC122: 2 группа | AD122: 1 группа | AG122: 3 группа | AH122: 2 группа | AI122: 1 группа | AL122: 3 группа | AM122: 2 группа | AN122: 1 группа | AQ122: 3 группа | AR122: 2 группа | AS122: 1 группа
B123: Кол-во баллов | C123: 54 | D123: 66 | E123: 82 | H123: 51 | I123: 58 | J123: 80 | M123: 54 | N123: 66 | O123: 82 | R123: 54 | S123: 66 | T123: 81 | W123: 54 | X123: 67 | Y123: 82 | AB123: 49 | AC123: 60 | AD123: 78 | AG123: 46 | AH123: 56 | AI123: 70 | AL123: 52 | AM123: 68 | AN123: 82 | AQ123: 53 | AR123: 69 | AS123: 83
A124: Период 2 | B124: Расчет порога | C124: =IF('МСФО расчет лимита'!$J$55>=Подложка!C123,1,0) -> 1 | D124: =IF('МСФО расчет лимита'!$J$55>=Подложка!D123,1,0) -> 1 | E124: =IF('МСФО расчет лимита'!$J$55>=Подложка!E123,1,0) -> 0 | F124: =SUM(C124:E124) -> 2 | G124: =IF(F124=3,1,IF(F124=2,2,IF(F124=1,3,4))) -> 2 | H124: =IF('МСФО расчет лимита'!$J$55>=Подложка!H123,1,0) -> 1 | I124: =IF('МСФО расчет лимита'!$J$55>=Подложка!I123,1,0) -> 1 | J124: =IF('МСФО расчет лимита'!$J$55>=Подложка!J123,1,0) -> 0 | K124: =SUM(H124:J124) -> 2 | L124: =IF(K124=3,1,IF(K124=2,2,IF(K124=1,3,4))) -> 2 | M124: =IF('МСФО расчет лимита'!$J$55>=Подложка!M123,1,0) -> 1 | N124: =IF('МСФО расчет лимита'!$J$55>=Подложка!N123,1,0) -> 1 | O124: =IF('МСФО расчет лимита'!$J$55>=Подложка!O123,1,0) -> 0 | P124: =SUM(M124:O124) -> 2 | Q124: =IF(P124=3,1,IF(P124=2,2,IF(P124=1,3,4))) -> 2 | R124: =IF('МСФО расчет лимита'!$J$55>=Подложка!R123,1,0) -> 1 | S124: =IF('МСФО расчет лимита'!$J$55>=Подложка!S123,1,0) -> 1 | T124: =IF('МСФО расчет лимита'!$J$55>=Подложка!T123,1,0) -> 0 | U124: =SUM(R124:T124) -> 2 | V124: =IF(U124=3,1,IF(U124=2,2,IF(U124=1,3,4))) -> 2 | W124: =IF('МСФО расчет лимита'!$J$55>=Подложка!W123,1,0) -> 1 | X124: =IF('МСФО расчет лимита'!$J$55>=Подложка!X123,1,0) -> 1 | Y124: =IF('МСФО расчет лимита'!$J$55>=Подложка!Y123,1,0) -> 0 | Z124: =SUM(W124:Y124) -> 2 | AA124: =IF(Z124=3,1,IF(Z124=2,2,IF(Z124=1,3,4))) -> 2 | AB124: =IF('МСФО расчет лимита'!$J$55>=Подложка!AB123,1,0) -> 1 | AC124: =IF('МСФО расчет лимита'!$J$55>=Подложка!AC123,1,0) -> 1 | AD124: =IF('МСФО расчет лимита'!$J$55>=Подложка!AD123,1,0) -> 0 | AE124: =SUM(AB124:AD124) -> 2 | AF124: =IF(AE124=3,1,IF(AE124=2,2,IF(AE124=1,3,4))) -> 2 | AG124: =IF('МСФО расчет лимита'!$J$55>=Подложка!AG123,1,0) -> 1 | AH124: =IF('МСФО расчет лимита'!$J$55>=Подложка!AH123,1,0) -> 1 | AI124: =IF('МСФО расчет лимита'!$J$55>=Подложка!AI123,1,0) -> 1 | AJ124: =SUM(AG124:AI124) -> 3 | AK124: =IF(AJ124=3,1,IF(AJ124=2,2,IF(AJ124=1,3,4))) -> 1 | AL124: =IF('МСФО расчет лимита'!$J$55>=Подложка!AL123,1,0) -> 1 | AM124: =IF('МСФО расчет лимита'!$J$55>=Подложка!AM123,1,0) -> 1 | AN124: =IF('МСФО расчет лимита'!$J$55>=Подложка!AN123,1,0) -> 0 | AO124: =SUM(AL124:AN124) -> 2 | AP124: =IF(AO124=3,1,IF(AO124=2,2,IF(AO124=1,3,4))) -> 2 | AQ124: =IF('МСФО расчет лимита'!$J$55>=Подложка!AQ123,1,0) -> 1 | AR124: =IF('МСФО расчет лимита'!$J$55>=Подложка!AR123,1,0) -> 1 | AS124: =IF('МСФО расчет лимита'!$J$55>=Подложка!AS123,1,0) -> 0 | AT124: =SUM(AQ124:AS124) -> 2 | AU124: =IF(AT124=3,1,IF(AT124=2,2,IF(AT124=1,3,4))) -> 2
A125: Период 1 | B125: Расчет порога | C125: =IF('МСФО расчет лимита'!$L$55>=Подложка!C123,1,0) -> 1 | D125: =IF('МСФО расчет лимита'!$L$55>=Подложка!D123,1,0) -> 1 | E125: =IF('МСФО расчет лимита'!$L$55>=Подложка!E123,1,0) -> 0 | F125: =SUM(C125:E125) -> 2 | G125: =IF(F125=3,1,IF(F125=2,2,IF(F125=1,3,4))) -> 2 | H125: =IF('МСФО расчет лимита'!$L$55>=Подложка!H123,1,0) -> 1 | I125: =IF('МСФО расчет лимита'!$L$55>=Подложка!I123,1,0) -> 1 | J125: =IF('МСФО расчет лимита'!$L$55>=Подложка!J123,1,0) -> 0 | K125: =SUM(H125:J125) -> 2 | L125: =IF(K125=3,1,IF(K125=2,2,IF(K125=1,3,4))) -> 2 | M125: =IF('МСФО расчет лимита'!$L$55>=Подложка!M123,1,0) -> 1 | N125: =IF('МСФО расчет лимита'!$L$55>=Подложка!N123,1,0) -> 1 | O125: =IF('МСФО расчет лимита'!$L$55>=Подложка!O123,1,0) -> 0 | P125: =SUM(M125:O125) -> 2 | Q125: =IF(P125=3,1,IF(P125=2,2,IF(P125=1,3,4))) -> 2 | R125: =IF('МСФО расчет лимита'!$L$55>=Подложка!R123,1,0) -> 1 | S125: =IF('МСФО расчет лимита'!$L$55>=Подложка!S123,1,0) -> 1 | T125: =IF('МСФО расчет лимита'!$L$55>=Подложка!T123,1,0) -> 0 | U125: =SUM(R125:T125) -> 2 | V125: =IF(U125=3,1,IF(U125=2,2,IF(U125=1,3,4))) -> 2 | W125: =IF('МСФО расчет лимита'!$L$55>=Подложка!W123,1,0) -> 1 | X125: =IF('МСФО расчет лимита'!$L$55>=Подложка!X123,1,0) -> 1 | Y125: =IF('МСФО расчет лимита'!$L$55>=Подложка!Y123,1,0) -> 0 | Z125: =SUM(W125:Y125) -> 2 | AA125: =IF(Z125=3,1,IF(Z125=2,2,IF(Z125=1,3,4))) -> 2 | AB125: =IF('МСФО расчет лимита'!$L$55>=Подложка!AB123,1,0) -> 1 | AC125: =IF('МСФО расчет лимита'!$L$55>=Подложка!AC123,1,0) -> 1 | AD125: =IF('МСФО расчет лимита'!$L$55>=Подложка!AD123,1,0) -> 0 | AE125: =SUM(AB125:AD125) -> 2 | AF125: =IF(AE125=3,1,IF(AE125=2,2,IF(AE125=1,3,4))) -> 2 | AG125: =IF('МСФО расчет лимита'!$L$55>=Подложка!AG123,1,0) -> 1 | AH125: =IF('МСФО расчет лимита'!$L$55>=Подложка!AH123,1,0) -> 1 | AI125: =IF('МСФО расчет лимита'!$L$55>=Подложка!AI123,1,0) -> 1 | AJ125: =SUM(AG125:AI125) -> 3 | AK125: =IF(AJ125=3,1,IF(AJ125=2,2,IF(AJ125=1,3,4))) -> 1 | AL125: =IF('МСФО расчет лимита'!$L$55>=Подложка!AL123,1,0) -> 1 | AM125: =IF('МСФО расчет лимита'!$L$55>=Подложка!AM123,1,0) -> 1 | AN125: =IF('МСФО расчет лимита'!$L$55>=Подложка!AN123,1,0) -> 0 | AO125: =SUM(AL125:AN125) -> 2 | AP125: =IF(AO125=3,1,IF(AO125=2,2,IF(AO125=1,3,4))) -> 2 | AQ125: =IF('МСФО расчет лимита'!$L$55>=Подложка!AQ123,1,0) -> 1 | AR125: =IF('МСФО расчет лимита'!$L$55>=Подложка!AR123,1,0) -> 1 | AS125: =IF('МСФО расчет лимита'!$L$55>=Подложка!AS123,1,0) -> 0 | AT125: =SUM(AQ125:AS125) -> 2 | AU125: =IF(AT125=3,1,IF(AT125=2,2,IF(AT125=1,3,4))) -> 2

Sheet МСФО расчет лимита
F1: ЭКСПРЕСС-ОЦЕНКА КОНТРАГЕНТА
K3: Дата оценки | N3: (Голубая ячейка заполняется вручную)
B5: ДАННЫЕ О КОНТРАГЕНТЕ
B7: 1.1 Наименование контрагента: | H7: СНПХ, АО | N7: (Голубая ячейка заполняется вручную)
B8: 1.2 Идентификационный номер (TIN): | H8: 1660000129 | N8: (Голубая ячейка заполняется вручную)
B9: 1.3 Код контрагента в системе учета (при наличии): | N9: (Заполняется вручную)
B10: 1.3 Категория: | H10: Производство | N10: (В голубой ячейке выбрать значение из списка)
B11: 1.4 Наличие СТОП-факторов: | H11: Нет | N11: (В голубой ячейке выбрать значение из списка)
B13: ИТОГОВОЕ ЗАКЛЮЧЕНИЕ
H14: =J22 -> 46022 | L14: ='МСФО отчетность'!F5 -> 45657 | N14: (Автоматический расчет)
B15: ВНУТРЕННИЙ КРЕДИТНЫЙ РЕЙТИНГ | H15: =J58&J57 -> C1 | J15: =J57 -> 1 | M15: =L58&L57 -> B1 | N15: (Автоматический расчет)
B16: СКОРИНГ-БАЛЛ | H16: =ROUND(J55,0)&" "&K55 -> 74 из 100 | J16: =J55 -> 74 | M16: =L55&" "&K55 -> 70 из 100 | N16: (Автоматический расчет)
B17: ="КРЕДИТНЫЙ ЛИМИТ КОНТРАГЕНТА, "&'МСФО отчетность'!C2&" "&'МСФО отчетность'!C3 -> КРЕДИТНЫЙ ЛИМИТ КОНТРАГЕНТА, mln $ | H17: =J89 -> 1491319.8 | J17: =H17 -> 1491319.8 | K17: =L83*L85*L87*(1-L88) -> 1223618.2 | L17: =L89 -> 1223618.2 | N17: (Автоматический расчет)
B18: ="ЛИМИТ АВАНСОВОГО ПЛАТЕЖА, "&'МСФО отчетность'!C2&" "&'МСФО отчетность'!C3 -> ЛИМИТ АВАНСОВОГО ПЛАТЕЖА, mln $ | H18: =J90 -> 52141.5 | J18: =H18 -> 52141.5 | L18: =L90 -> 35823.9
B20: 1. ФИНАНСОВЫЕ ПОКАЗАТЕЛИ
J22: ='МСФО отчетность'!E5 -> 46022 | L22: ='МСФО отчетность'!F5 -> 45657 | N22: (Автоматический расчет)
B23: Наименование показателя | I23: Макс. балл | J23: Значение | K23: Баллы | L23: Значение | M23: Баллы
B24: 1.1 Коэффициент текущей ликвидности | I24: 10 | J24: ='МСФО отчетность'!E64 -> 3.2836953 | K24: =ROUND(IF(J24="",0,IF($H$10="Строительство",Подложка!G92*I24/100,IF($H$10="Добыча, переработка и транспортировка газа, нефти и нефтепродуктов",Подложка!L92*I24/100,IF($H$10="Транспортировка и хранение",Подложка!Q92*I24/100,IF($H$10="Торговля",Подложка!V92*I24/100,IF($H$10="Производство",Подложка!AA92*I24/100,IF($H$10="Авиакомпания",Подложка!AF92*I24/100,IF($H$10="Судовладелец",Подложка!AK92*I24/100,IF($H$10="Прочие",Подложка!AP92*I24/100,IF($H$10="ИТ",Подложка!AU92*I24/100,0)))))))))),0) -> 10 | L24: ='МСФО отчетность'!F64 -> 2.9821276 | M24: =IF(L24="",0,IF($H$10="Строительство",Подложка!G55*I24/100,IF($H$10="Добыча, переработка и транспортировка газа, нефти и нефтепродуктов",Подложка!L55*I24/100,IF($H$10="Транспортировка и хранение",Подложка!Q55*I24/100,IF($H$10="Торговля",Подложка!V55*I24/100,IF($H$10="Производство",Подложка!AA55*I24/100,IF($H$10="Авиакомпания",Подложка!AF55*I24/100,IF($H$10="Судовладелец",Подложка!AK55*I24/100,IF($H$10="Прочие",Подложка!AP55*I24/100,IF($H$10="ИТ",Подложка!AU55*I24/100,0)))))))))) -> 10 | N24: (Автоматический расчет)
B25: 1.2 Коэффициент быстрой ликвидности | I25: 5 | J25: ='МСФО отчетность'!E65 -> 1.7494151 | K25: =ROUND(IF(J25="",0,IF($H$10="Строительство",Подложка!G93*I25/100,IF($H$10="Добыча, переработка и транспортировка газа, нефти и нефтепродуктов",Подложка!L93*I25/100,IF($H$10="Транспортировка и хранение",Подложка!Q93*I25/100,IF($H$10="Торговля",Подложка!V93*I25/100,IF($H$10="Производство",Подложка!AA93*I25/100,IF($H$10="Авиакомпания",Подложка!AF93*I25/100,IF($H$10="Судовладелец",Подложка!AK93*I25/100,IF($H$10="Прочие",Подложка!AP93*I25/100,IF($H$10="ИТ",Подложка!AU93*I25/100,0)))))))))),0) -> 5 | L25: ='МСФО отчетность'!F65 -> 1.755559 | M25: =IF(L25="",0,IF($H$10="Строительство",Подложка!G56*I25/100,IF($H$10="Добыча, переработка и транспортировка газа, нефти и нефтепродуктов",Подложка!L56*I25/100,IF($H$10="Транспортировка и хранение",Подложка!Q56*I25/100,IF($H$10="Торговля",Подложка!V56*I25/100,IF($H$10="Производство",Подложка!AA56*I25/100,IF($H$10="Авиакомпания",Подложка!AF56*I25/100,IF($H$10="Судовладелец",Подложка!AK56*I25/100,IF($H$10="Прочие",Подложка!AP56*I25/100,IF($H$10="ИТ",Подложка!AU56*I25/100,0)))))))))) -> 5 | N25: (Автоматический расчет)
B26: 1.3 Длительность операционного цикла | I26: 5 | J26: ='МСФО отчетность'!E66 -> 166.83719 | K26: =ROUND(IF($H$10="Строительство",Подложка!G94*I26/100,IF($H$10="Добыча, переработка и транспортировка газа, нефти и нефтепродуктов",Подложка!L94*I26/100,IF($H$10="Транспортировка и хранение",Подложка!Q94*I26/100,IF($H$10="Торговля",Подложка!V94*I26/100,IF($H$10="Производство",Подложка!AA94*I26/100,IF($H$10="Авиакомпания",Подложка!AF94*I26/100,IF($H$10="Судовладелец",Подложка!AK94*I26/100,IF($H$10="Прочие",Подложка!AP94*I26/100,IF($H$10="ИТ",Подложка!AU94*I26/100,0))))))))),0) -> 0 | L26: ='МСФО отчетность'!F66 -> 140.56013 | M26: =IF(L26="",0,IF($H$10="Строительство",Подложка!G57*I26/100,IF($H$10="Добыча, переработка и транспортировка газа, нефти и нефтепродуктов",Подложка!L57*I26/100,IF($H$10="Транспортировка и хранение",Подложка!Q57*I26/100,IF($H$10="Торговля",Подложка!V57*I26/100,IF($H$10="Производство",Подложка!AA57*I26/100,IF($H$10="Авиакомпания",Подложка!AF57*I26/100,IF($H$10="Судовладелец",Подложка!AK57*I26/100,IF($H$10="Прочие",Подложка!AP57*I26/100,IF($H$10="ИТ",Подложка!AU57*I26/100,0)))))))))) -> 0 | N26: (Автоматический расчет)
B27: 1.4 Коэффициент автономии | I27: 10 | J27: ='МСФО отчетность'!E67 -> 0.70509515 | K27: =ROUND(IF(J27="",0,IF($H$10="Строительство",Подложка!G95*I27/100,IF($H$10="Добыча, переработка и транспортировка газа, нефти и нефтепродуктов",Подложка!L95*I27/100,IF($H$10="Транспортировка и хранение",Подложка!Q95*I27/100,IF($H$10="Торговля",Подложка!V95*I27/100,IF($H$10="Производство",Подложка!AA95*I27/100,IF($H$10="Авиакомпания",Подложка!AF95*I27/100,IF($H$10="Судовладелец",Подложка!AK95*I27/100,IF($H$10="Прочие",Подложка!AP95*I27/100,IF($H$10="ИТ",Подложка!AU95*I27/100,0)))))))))),0) -> 10 | L27: ='МСФО отчетность'!F67 -> 0.67351065 | M27: =IF(L27="",0,IF($H$10="Строительство",Подложка!G58*I27/100,IF($H$10="Добыча, переработка и транспортировка газа, нефти и нефтепродуктов",Подложка!L58*I27/100,IF($H$10="Транспортировка и хранение",Подложка!Q58*I27/100,IF($H$10="Торговля",Подложка!V58*I27/100,IF($H$10="Производство",Подложка!AA58*I27/100,IF($H$10="Авиакомпания",Подложка!AF58*I27/100,IF($H$10="Судовладелец",Подложка!AK58*I27/100,IF($H$10="Прочие",Подложка!AP58*I27/100,IF($H$10="ИТ",Подложка!AU58*I27/100,0)))))))))) -> 7 | N27: (Автоматический расчет)
B28: 1.5 Рентабельность продаж | I28: 5 | J28: ='МСФО отчетность'!E68 -> 9.6934592 | K28: =ROUND(IF(J28="",0,IF($H$10="Строительство",Подложка!G96*I28/100,IF($H$10="Добыча, переработка и транспортировка газа, нефти и нефтепродуктов",Подложка!L96*I28/100,IF($H$10="Транспортировка и хранение",Подложка!Q96*I28/100,IF($H$10="Торговля",Подложка!V96*I28/100,IF($H$10="Производство",Подложка!AA96*I28/100,IF($H$10="Авиакомпания",Подложка!AF96*I28/100,IF($H$10="Судовладелец",Подложка!AK96*I28/100,IF($H$10="Прочие",Подложка!AP96*I28/100,IF($H$10="ИТ",Подложка!AU96*I28/100,0)))))))))),0) -> 4 | L28: ='МСФО отчетность'!F68 -> 21.337774 | M28: =IF(L28="",0,IF($H$10="Строительство",Подложка!G59*I28/100,IF($H$10="Добыча, переработка и транспортировка газа, нефти и нефтепродуктов",Подложка!L59*I28/100,IF($H$10="Транспортировка и хранение",Подложка!Q59*I28/100,IF($H$10="Торговля",Подложка!V59*I28/100,IF($H$10="Производство",Подложка!AA59*I28/100,IF($H$10="Авиакомпания",Подложка!AF59*I28/100,IF($H$10="Судовладелец",Подложка!AK59*I28/100,IF($H$10="Прочие",Подложка!AP59*I28/100,IF($H$10="ИТ",Подложка!AU59*I28/100,0)))))))))) -> 5 | N28: (Автоматический расчет)
B29: 1.6 Коэффициент долговой нагрузки | I29: 10 | J29: ='МСФО отчетность'!E69 -> 0.30470929 | K29: =ROUND(IF(J29=0,I29,IF(OR(J29="",J29<0),0,IF($H$10="Строительство",Подложка!G97*I29/100,IF($H$10="Добыча, переработка и транспортировка газа, нефти и нефтепродуктов",Подложка!L97*I29/100,IF($H$10="Транспортировка и хранение",Подложка!Q97*I29/100,IF($H$10="Торговля",Подложка!V97*I29/100,IF($H$10="Производство",Подложка!AA97*I29/100,IF($H$10="Авиакомпания",Подложка!AF97*I29/100,IF($H$10="Судовладелец",Подложка!AK97*I29/100,IF($H$10="Прочие",Подложка!AP97*I29/100,IF($H$10="ИТ",Подложка!AU97*I29/100,0))))))))))),0) -> 7 | L29: ='МСФО отчетность'!F69 -> 0.16220914 | M29: =IF(L29="",0,IF($H$10="Строительство",Подложка!G60*I29/100,IF($H$10="Добыча, переработка и транспортировка газа, нефти и нефтепродуктов",Подложка!L60*I29/100,IF($H$10="Транспортировка и хранение",Подложка!Q60*I29/100,IF($H$10="Торговля",Подложка!V60*I29/100,IF($H$10="Производство",Подложка!AA60*I29/100,IF($H$10="Авиакомпания",Подложка!AF60*I29/100,IF($H$10="Судовладелец",Подложка!AK60*I29/100,IF($H$10="Прочие",Подложка!AP60*I29/100,IF($H$10="ИТ",Подложка!AU60*I29/100,0)))))))))) -> 7 | N29: (Автоматический расчет)
B30: 1.7 Коэффициент покрытия процентов | I30: 5 | J30: ='МСФО отчетность'!E70 -> 18.721681 | K30: =ROUND(IF(J30=0,I30,IF(OR(J30="",J30<0),0,IF($H$10="Строительство",Подложка!G98*I30/100,IF($H$10="Добыча, переработка и транспортировка газа, нефти и нефтепродуктов",Подложка!L98*I30/100,IF($H$10="Транспортировка и хранение",Подложка!Q98*I30/100,IF($H$10="Торговля",Подложка!V98*I30/100,IF($H$10="Производство",Подложка!AA98*I30/100,IF($H$10="Авиакомпания",Подложка!AF98*I30/100,IF($H$10="Судовладелец",Подложка!AK98*I30/100,IF($H$10="Прочие",Подложка!AP98*I30/100,IF($H$10="ИТ",Подложка!AU98*I30/100,0))))))))))),0) -> 5 | L30: ='МСФО отчетность'!F70 -> 34.086001 | M30: =IF(L30="",0,IF($H$10="Строительство",Подложка!G61*I30/100,IF($H$10="Добыча, переработка и транспортировка газа, нефти и нефтепродуктов",Подложка!L61*I30/100,IF($H$10="Транспортировка и хранение",Подложка!Q61*I30/100,IF($H$10="Торговля",Подложка!V61*I30/100,IF($H$10="Производство",Подложка!AA61*I30/100,IF($H$10="Авиакомпания",Подложка!AF61*I30/100,IF($H$10="Судовладелец",Подложка!AK61*I30/100,IF($H$10="Прочие",Подложка!AP61*I30/100,IF($H$10="ИТ",Подложка!AU61*I30/100,0)))))))))) -> 5 | N30: (Автоматический расчет)
B31: 1.8 Коэффициент маневренности | I31: 5 | J31: ='МСФО отчетность'!E71 -> 0.68527449 | K31: =ROUND(IF(J24="",0,IF(OR(J31="",J31<0),0,IF($H$10="Строительство",Подложка!G99*I31/100,IF($H$10="Добыча, переработка и транспортировка газа, нефти и нефтепродуктов",Подложка!L99*I31/100,IF($H$10="Транспортировка и хранение",Подложка!Q99*I31/100,IF($H$10="Торговля",Подложка!V99*I31/100,IF($H$10="Производство",Подложка!AA99*I31/100,IF($H$10="Авиакомпания",Подложка!AF99*I31/100,IF($H$10="Судовладелец",Подложка!AK99*I31/100,IF($H$10="Прочие",Подложка!AP99*I31/100,IF($H$10="ИТ",Подложка!AU99*I31/100,0))))))))))),0) -> 5 | L31: ='МСФО отчетность'!F71 -> 0.65401698 | M31: =IF(L31="",0,IF($H$10="Строительство",Подложка!G62*I31/100,IF($H$10="Добыча, переработка и транспортировка газа, нефти и нефтепродуктов",Подложка!L62*I31/100,IF($H$10="Транспортировка и хранение",Подложка!Q62*I31/100,IF($H$10="Торговля",Подложка!V62*I31/100,IF($H$10="Производство",Подложка!AA62*I31/100,IF($H$10="Авиакомпания",Подложка!AF62*I31/100,IF($H$10="Судовладелец",Подложка!AK62*I31/100,IF($H$10="Прочие",Подложка!AP62*I31/100,IF($H$10="ИТ",Подложка!AU62*I31/100,0)))))))))) -> 5 | N31: (Автоматический расчет)
B32: 1.9 Рентабельность капитала | I32: 4 | J32: ='МСФО отчетность'!E72 -> 26.007659 | K32: =ROUND(IF(J32="",0,IF(OR(J32="",J32<0),0,IF($H$10="Строительство",Подложка!G100*I32/100,IF($H$10="Добыча, переработка и транспортировка газа, нефти и нефтепродуктов",Подложка!L100*I32/100,IF($H$10="Транспортировка и хранение",Подложка!Q100*I32/100,IF($H$10="Торговля",Подложка!V100*I32/100,IF($H$10="Производство",Подложка!AA100*I32/100,IF($H$10="Авиакомпания",Подложка!AF100*I32/100,IF($H$10="Судовладелец",Подложка!AK100*I32/100,IF($H$10="Прочие",Подложка!AP100*I32/100,IF($H$10="ИТ",Подложка!AU100*I32/100,0))))))))))),0) -> 3 | L32: ='МСФО отчетность'!F72 -> 65.990771 | M32: =IF(L32="",0,IF($H$10="Строительство",Подложка!G63*I32/100,IF($H$10="Добыча, переработка и транспортировка газа, нефти и нефтепродуктов",Подложка!L63*I32/100,IF($H$10="Транспортировка и хранение",Подложка!Q63*I32/100,IF($H$10="Торговля",Подложка!V63*I32/100,IF($H$10="Производство",Подложка!AA63*I32/100,IF($H$10="Авиакомпания",Подложка!AF63*I32/100,IF($H$10="Судовладелец",Подложка!AK63*I32/100,IF($H$10="Прочие",Подложка!AP63*I32/100,IF($H$10="ИТ",Подложка!AU63*I32/100,0)))))))))) -> 4 | N32: (Автоматический расчет)
B33: 1.10 Динамика ликвидности | I33: 3 | J33: ='МСФО отчетность'!E73 -> Рост | K33: =VLOOKUP(J33,Подложка!$AD$3:$AE$6,2,0) -> 3 | L33: ='МСФО отчетность'!F73 -> На прежнем уровне | M33: =VLOOKUP(L33,Подложка!$AD$3:$AE$6,2,0) -> 0 | N33: (Автоматический расчет)
B34: 1.11 Динамика рентабельности продаж | I34: 3 | J34: ='МСФО отчетность'!E74 -> Снижение | K34: =VLOOKUP(J34,Подложка!$AD$3:$AE$6,2,0) -> -3 | L34: ='МСФО отчетность'!F74 -> Снижение | M34: =VLOOKUP(L34,Подложка!$AD$3:$AE$6,2,0) -> -3 | N34: (Автоматический расчет)
B35: Итого баллов с учетом веса показателей | I35: =SUM(I24:I34) -> 65 | K35: =SUM(K24:K34) -> 49 | M35: =SUM(M24:M34) -> 45 | N35: (Автоматический расчет)
B37: 2. ПОКАЗАТЕЛИ ДЕЛОВОЙ РЕПУТАЦИИ
J39: ='МСФО отчетность'!E5 -> 46022 | L39: ='МСФО отчетность'!F5 -> 45657 | N39: (Автоматический расчет)
B40: Наименование показателя | I40: Макс. балл | J40: Значение | K40: Баллы | L40: Значение | M40: Баллы
B41: 2.1 Опыт работы с контрагентом | I41: 10 | J41: более 3-х лет | K41: =IF($J$41="более 3-х лет",100*I41/100,IF($J$41="от 1 до 3-х лет",70*I41/100,IF($J$41="менее 1 года",40*I41/100,0))) -> 10 | L41: более 3-х лет | M41: =IF($L$41="более 3-х лет",100*I41/100,IF($L$41="от 1 до 3-х лет",70*I41/100,IF($L$41="менее 1 года",40*I41/100,0))) -> 10 | N41: (В голубых ячейках выбрать значение из списка)
B42: 2.2 Платежная дисциплина контрагента | I42: 15 | J42: ПДЗ отсутствовала | K42: =IF(OR(J42="ПДЗ отсутствовала",J42="Техническая ПДЗ"),15,IF(J42="Разовая ПДЗ продолжительностью менее 30 дней",10,IF(J42="Разовая ПДЗ продолжительностью более 30 дней",7.5,IF(J42="Неоднократное возникновение ПДЗ",3.5,IF(J42="Информация отсутствует",3.5,0))))) -> 15 | L42: ПДЗ отсутствовала | M42: =IF(OR(L42="ПДЗ отсутствовала",L42="Техническая ПДЗ"),15,IF(L42="Разовая ПДЗ продолжительностью менее 30 дней",10,IF(L42="Разовая ПДЗ продолжительностью более 30 дней",7.5,IF(L42="Неоднократное возникновение ПДЗ",3.5,IF(L42="Информация отсутствует",3.5,0))))) -> 15 | N42: (В голубых ячейках выбрать значение из списка)
B43: Итого баллов с учетом веса показателей | I43: 25 | K43: =SUM(K41:K42) -> 25 | M43: =SUM(M41:M42) -> 25 | N43: (Автоматический расчет)
B45: 3. ПОКАЗАТЕЛИ ИЗ ВНЕШНИХ ИСТОЧНИКОВ
J48: ='МСФО отчетность'!E5 -> 46022 | N48: (Автоматический расчет)
B49: Повышающие показатели | I49: Макс. балл | J49: Значение | K49: Баллы | L49: Дата регистрации
B50: 3.1 Возраст компании | I50: 10 | J50: =IF(OR(L98="",L98=0),"Информация отсутствует",IF(L98>TODAY(),"Информация некорректна",IF(TODAY()-L98<730,"Менее 2 лет",IF(TODAY()-L98<1825,"От 2 до 5-и лет","Более 5 лет")))) -> Информация отсутствует | K50: =IF(OR(L98="Информация отсутствует",L98="Информация некорректна"),0,IF(L98="Менее 2 лет",40*I98/100,IF(L98="От 2 до 5-и лет",70*I98/100,100*I98/100))) -> 0 | L50: 34928 | N50: (Голубая ячейка заполняется вручную)
B51: Итого баллов с учетом веса показателей | I51: 10 | K51: =IF(ROUND(SUM(K98),2)<0,0,ROUND(SUM(K98),2)) -> 0 | N51: (Автоматический расчет)
J54: ='МСФО отчетность'!E5 -> 46022 | L54: ='МСФО отчетность'!F5 -> 45657
B55: ИТОГО СКОРИНГ-БАЛЛ (1.+2.+3.) | I55: =SUM(I35,I43,I51) -> 100 | J55: =IF(LEFT(H11,2)="Да",0,SUM(K35,K43,K99)) -> 74 | K55: из 100 | L55: =IF(LEFT(H11,2)="Да",0,SUM(M35,M43,K99)) -> 70 | M55: из 100 | N55: (Автоматический расчет)
B57: Группа кредитоспособности (1-4) | J57: =IF(LEFT(H11,2)="Да",4,IF($H$10="Строительство",Подложка!G82,IF($H$10="Добыча, переработка и транспортировка газа, нефти и нефтепродуктов",Подложка!L82,IF($H$10="Транспортировка и хранение",Подложка!Q82,IF($H$10="Торговля",Подложка!V82,IF($H$10="Производство",Подложка!AA82,IF($H$10="Авиакомпания",Подложка!AF82,IF($H$10="Судовладелец",Подложка!AK82,IF($H$10="Прочие",Подложка!AP82,IF($H$10="ИТ",Подложка!AU82,0)))))))))) -> 1 | L57: =IF(LEFT(H11,2)="Да",4,IF($H$10="Строительство",Подложка!G83,IF($H$10="Добыча, переработка и транспортировка газа, нефти и нефтепродуктов",Подложка!L83,IF($H$10="Транспортировка и хранение",Подложка!Q83,IF($H$10="Торговля",Подложка!V83,IF($H$10="Производство",Подложка!AA83,IF($H$10="Авиакомпания",Подложка!AF83,IF($H$10="Судовладелец",Подложка!AK83,IF($H$10="Прочие",Подложка!AP83,IF($H$10="ИТ",Подложка!AU83,0)))))))))) -> 1 | N57: (Автоматический расчет)
B58: Класс контрагента (А-С) | J58: C | L58: B | N58: (В голубых ячейках выбрать значение из списка )
B61: 4. ДОПОЛНИТЕЛЬНЫЕ ПОКАЗАТЕЛИ
I63: Макс. балл | J63: Значение | K63: Баллы
B64: 4.1 Графовый индикатор | I64: 10 | J64: Нет данных | K64: =VLOOKUP(J64,Подложка!X3:Z28,2,0) -> 0 | N64: (Автоматический расчет)
B65: 4.2 Исковый индикатор | I65: 10 | J65: Нет данных | K65: =VLOOKUP(J65,Подложка!X3:Z28,3,0) -> 0 | N65: (Автоматический расчет)
B66: Итого дополнительных баллов | I66: 20 | K66: =K64+K65 -> 0
B68: 5. ДАННЫЕ О ПРЕТЕНЗИОННО-ИСКОВОЙ РАБОТЕ С КОНТРАГЕНТОМ
J70: Значение | L70: Размер штрафа
B71: 5.1 Наличие досудебных претензий | J71: Отсутствуют | L71: =VLOOKUP(J71,Подложка!Q3:R7,2,0) -> 0 | N71: (Автоматический расчет)
B72: 5.2 Наличие исковых требований | J72: Отсутствуют | L72: =VLOOKUP(J72,Подложка!S2:T5,2,0) -> 0 | N72: (Автоматический расчет)
B73: Итого штрафные баллы с учетом показателей | L73: =MAX(K71:M72) -> 0 | N73: (Автоматический расчет)
B75: ="6. РАСЧЕТ КРЕДИТНОГО ЛИМИТА И АВАНСОВОГО ПЛАТЕЖА"&", "&'МСФО отчетность'!C2&" "&'МСФО отчетность'!C3 -> 6. РАСЧЕТ КРЕДИТНОГО ЛИМИТА И АВАНСОВОГО ПЛАТЕЖА, mln $
J76: =J22 -> 46022 | L76: =L22 -> 45657
B77: ="Внеоборотные активы (ОС+НС), "&'МСФО отчетность'!C2&" "&'МСФО отчетность'!C3 -> Внеоборотные активы (ОС+НС), mln $ | J77: ='РСБУ отчетность'!E12 -> 173805 | L77: ='РСБУ отчетность'!F12 -> 119413 | N77: (Автоматический расчет)
B78: ="Чистые активы (ЧА), "&'МСФО отчетность'!C2&" "&'МСФО отчетность'!C3 -> Чистые активы (ЧА), mln $ | J78: ='РСБУ отчетность'!E76 -> 2211450 | L78: ='РСБУ отчетность'!F76 -> 1899362 | N78: (Автоматический расчет)
B79: Наименьшее значение (показатель 1) | J79: =MIN(J77,J78) -> 173805 | L79: =MIN(L77,L78) -> 119413 | N79: (Автоматический расчет)
B80: ="Оборотные активы (ОА), "&'МСФО отчетность'!C2&" "&'МСФО отчетность'!C3 -> Оборотные активы (ОА), mln $ | J80: ='РСБУ отчетность'!E19 -> 2935952 | L80: ='РСБУ отчетность'!F19 -> 2661200 | N80: (Автоматический расчет)
B81: ="Краткосрочные обязательства (КО), "&'МСФО отчетность'!C2&" "&'МСФО отчетность'!C3 -> Краткосрочные обязательства (КО), mln $ | J81: ='РСБУ отчетность'!E44 -> 920655 | L81: ='РСБУ отчетность'!F44 -> 913174 | N81: (Автоматический расчет)
B82: ОА-КО (показатель 2) | J82: =J80-J81 -> 2015297 | L82: =L80-L81 -> 1748026 | N82: (Автоматический расчет)
B83: База для расчета кредитного лимита (наибольшее из показателей 1 и 2) | J83: =MAX(J79,J82) -> 2015297 | L83: =MAX(L79,L82) -> 1748026 | N83: (Автоматический расчет)
B84: База для расчета лимита авансового платежа (показатель 1) | J84: =J79 -> 173805 | L84: =L79 -> 119413 | N84: (Автоматический расчет)
B85: Понижающий коэффициент (итого баллов/100) | J85: =J55/100 -> 0.74 | L85: =L55/100 -> 0.7 | N85: (Автоматический расчет)
B86: Коэффициент надежности ( по группе кредитоспособности) | J86: =IF(J57=1,0.3,IF(J57=2,0.2,IF(J57=3,0.1,IF(J57=4,0,"ошибка")))) -> 0.3 | L86: =IF(L57=1,0.3,IF(L57=2,0.2,IF(L57=3,0.1,IF(L57=4,0,"ошибка")))) -> 0.3
B87: Доп. коэффициент по индикаторам (1+доп. баллы/100) | J87: =1+K66/100 -> 1 | L87: =1+K66/100 -> 1 | N87: (Автоматический расчет)
B88: Штраф за наличие претензионно-исковой работы (штрафные баллы/100) | J88: =L73/100 -> 0 | L88: =L73/100 -> 0 | N88: (Автоматический расчет)
B89: ="Кредитный лимит контрагента, "&'МСФО отчетность'!C2&" "&'МСФО отчетность'!C3 -> Кредитный лимит контрагента, mln $ | J89: =IF(IF(J83>0,J83*J85*J87*(1-J88),0)<0,0,IF(J83>0,J83*J85*J87*(1-J88),0)) -> 1491319.8 | L89: =IF(IF(L83>0,L83*L85*L87*(1-L88),0)<0,0,IF(L83>0,L83*L85*L87*(1-L88),0)) -> 1223618.2 | N89: (Автоматический расчет)
B90: ="Лимит авансового платежа, "&'МСФО отчетность'!C2&" "&'МСФО отчетность'!C3 -> Лимит авансового платежа, mln $ | J90: =IF(J84*J86*J87*(1-J88)<0,0,IF(J84>0,J84*J86*J87*(1-J88),0)) -> 52141.5 | L90: =IF(L84*L86*L87*(1-L88)<0,0,IF(L84>0,L84*L86*L87*(1-L88),0)) -> 35823.9 | N90: (Автоматический расчет)
B92: Расчеты проводил(а): | N92: (Голубая ячейка заполняется вручную)

Sheet МСФО отчетность
A1: ДАННЫЕ ОТЧЕТНОСТИ | G1: заполнять вручную
A2: Unit | C2: mln | G2: заполняется автоматически
A3: Currency | C3: $
A4: Statement of Financial Position
E5: 46022 | F5: 45657 | G5: 45291
A6: ASSETS
A7: I. Non-current assets: | E7: =SUM(E8:E14) -> 199517 | F7: =SUM(F8:F14) -> 158892 | G7: =SUM(G8:G14) -> 136886
A8: Property, plant and equipment | E8: 173805 | F8: 119413 | G8: 94029
A9: Goodwill and other intangible assets
A10: Investments in associates and joint ventures
A11: Long-term trade and other receivables
A12: Long-term financial assets | E12: 900 | F12: 812 | G12: 822
A13: Deferred tax assets | E13: 6642 | F13: 5504 | G13: 2382
A14: Other non-current assets | E14: =18170 -> 18170 | F14: 33163 | G14: 39653
A15: II. Current assets: | E15: =SUM(E16:E18,E20:E22) -> 2935952 | F15: =SUM(F16:F18,F20:F22) -> 2661200 | G15: =SUM(G16:G18,G20:G22) -> 1806482
A16: Cash and cash equivalents | E16: 210093 | F16: 96119 | G16: 44876
A17: Short-term financial assets | E17: 0 | F17: 15000 | G17: 75905
A18: Trade and other receivables | E18: 1354059 | F18: 1470512 | G18: 732868
A19: Receivables from stakeholders
A20: Inventories | E20: 1351289 | F20: 1061615 | G20: 932045
A21: Current tax prepayments | E21: 7 | F21: 0 | G21: 0
A22: Other current assets | E22: 20504 | F22: 17954 | G22: 20788
A23: TOTAL ASSETS | E23: =E7+E15 -> 3135469 | F23: =F7+F15 -> 2820092 | G23: =G7+G15 -> 1943368
A24: LIABILITIES AND SHAREHOLDER'S EQUITY
A25: III. Equity | E25: =SUM(E26:E32) -> 2210804 | F25: =SUM(F26:F32) -> 1899362 | G25: =SUM(G26:G32) -> 1345353
A26: Share capital | E26: 19896 | F26: 19896 | G26: 19896
A27: Equity attributable to owners of the Company
A28: Reserves | E28: 20729 | F28: 86449 | G28: 86449
A29: Other reserves | E29: 995 | F29: 995 | G29: 995
A30: Additional paid-in capital | E30: 33333 | F30: 33333 | G30: 33333
A31: Retained earnings | E31: 2135851 | F31: 1758689 | G31: 1204680
A32: Non-controlling interests
A33: IV. Long-term liabilities | E33: =SUM(E34:E39) -> 4010 | F33: =SUM(F34:F39) -> 7556 | G33: =SUM(G34:G39) -> 7277
A34: Loans and borrowings
A35: Other non-current financial liabilities
A36: Deferred tax liabilities | E36: 4010 | F36: 7556 | G36: 7277
A37: Provisions
A38: Trade and other payables
A39: Other non-current liabilities
A40: V. Short-term liabilities | E40: =SUM(E41:E47) -> 920655 | F40: =SUM(F41:F47) -> 913174 | G40: =SUM(G41:G47) -> 590738
A41: Loans and borrowings | E41: 163319 | F41: 174456 | G41: 78924
A42: Trade and other payables | E42: 730781 | F42: 717927 | G42: 501764
A43: Other current financial liabilities
A44: Current income tax payable
A45: Deferred tax liabilities
A46: Provisions | E46: 25909 | F46: 20791 | G46: 10050
A47: Other current liabilities | E47: 646
A48: Deferred income | E48: 646
A49: TOTAL LIABILITIES AND EQUITY | E49: =E25+E33+E40 -> 3135469 | F49: =F25+F33+F40 -> 2820092 | G49: =G25+G33+G40 -> 1943368
E50: =E23-E49 -> 0 | F50: =F23-F49 -> 0 | G50: =G23-G49 -> 0
A51: Statement of Profit and Loss
E52: =E5 -> 46022 | F52: =F5 -> 45657 | G52: =G5 -> 45291
A53: Revenue | E53: 4319882 | F53: 4723937 | G53: 4059031
A54: Cost of sales | E54: 2983084 | F54: 3117946 | G54: 2294620
A55: Gross profit | E55: 1336798 | F55: 1605991 | G55: 1764411
A56: Results from operating activities | E56: 418746 | F56: 1007983 | G56: 1052031
A57: Finance income | E57: 32285 | F57: 28328 | G57: 23391
A58: Finance costs | E58: 28629 | F58: 31639 | G58: 7252
A59: Profit/(loss) before income tax | E59: 539639 | F59: 1075136 | G59: 896423
A60: Profit/(loss) | E60: 411537 | F60: 854196 | G60: 710911
A61: Period (day's) | E61: =E52-DATE(YEAR(E52),1,1)+1 -> 365 | F61: =F52-DATE(YEAR(F52),1,1)+1 -> 366 | G61: =G52-DATE(YEAR(G52),1,1)+1 -> 365
A64: Коэффициент текущей ликвидности | E64: =IFERROR((E15)/(E40-E48-E46),"") -> 3.2836953 | F64: =IFERROR((F15)/(F40-F48-F46),"") -> 2.9821276 | G64: =IFERROR((G15)/(G40-G48-G46),"") -> 3.1109339
A65: Коэффициент быстрой ликвидности | E65: =IFERROR((E18+E16)/(E40-E48-E46),"") -> 1.7494151 | F65: =IFERROR((F18+F16)/(F40-F48-F46),"") -> 1.755559 | G65: =IFERROR((G18+G16)/(G40-G48-G46),"") -> 1.3393492
A66: Длительность операционного цикла | E66: =IFERROR((E20+E18-E42)/(E53/E61),"") -> 166.83719 | F66: =IFERROR((F20+F18-F42)/(F53/F61),"") -> 140.56013 | G66: =IFERROR((G20+G18-G42)/(G53/G61),"") -> 104.59378
A67: Коэффициент автономии | E67: =IFERROR((E25)/E23,"") -> 0.70509515 | F67: =IFERROR((F25)/F23,"") -> 0.67351065 | G67: =IFERROR((G25)/G23,"") -> 0.69227907
A68: Рентабельность продаж | E68: =IFERROR((E56/E53)*100,"") -> 9.6934592 | F68: =IFERROR((F56/F53)*100,"") -> 21.337774 | G68: =IFERROR((G56/G53)*100,"") -> 25.91828
A69: Коэффициент долговой нагрузки | E69: =IFERROR((E34+E41)/((E59-E57+E58)/E61*365),"") -> 0.30470929 | F69: =IFERROR((F34+F41)/((F59-F57+F58)/F61*365),"") -> 0.16220914 | G69: =IFERROR((G34+G41)/((G59-G57+G58)/G61*365),"") -> 0.089657429
A70: Коэффициент покрытия процентов | E70: =IFERROR((E59+E58-E57)/(E58),"") -> 18.721681 | F70: =IFERROR((F59+F58-F57)/(F58),"") -> 34.086001 | G70: =IFERROR((G59+G58-G57)/(G58),"") -> 121.385
A71: Коэффициент маневренности | E71: =IFERROR((E25-E27+E48-E7)/(E15),"") -> 0.68527449 | F71: =IFERROR((F25-F27+F48-F7)/(F15),"") -> 0.65401698 | G71: =IFERROR((G25-G27+G48-G7)/(G15),"") -> 0.66896155
A72: Рентабельность капитала | E72: =IFERROR(((E59+E58-E57)/E61*365)/((E25+E33+F25+F33)/2)*100,"") -> 26.007659 | F72: =IFERROR(((F59+F58-F57)/F61*365)/((F25+F33+G25+G33)/2)*100,"") -> 65.990771 | G72: =IFERROR(((G59+G58-G57)/G61*365)/((G25+G33+H25+H33)/2)*100,"") -> 130.15888
A73: Динамика ликвидности | E73: =IFERROR(IF((IFERROR((E15)/(E40-E48-E46),"")/IFERROR((F15)/(F40-F48-F46),"")-1)>0.1,"Рост",IF((IFERROR((E15)/(E40-E48-E46),"")/IFERROR((F15)/(F40-F48-F46),"")-1)<-0.1,"Снижение","На прежнем уровне")),"Нет данных") -> Рост | F73: =IFERROR(IF((IFERROR((F15)/(F40-F48-F46),"")/IFERROR((G15)/(G40-G48-G46),"")-1)>0.1,"Рост",IF((IFERROR((F15)/(F40-F48-F46),"")/IFERROR((G15)/(G40-G48-G46),"")-1)<-0.1,"Снижение","На прежнем уровне")),"Нет данных") -> На прежнем уровне | G73: =IFERROR(IF((IFERROR((G15)/(G40-G48-G46),"")/IFERROR((H15)/(H40-H48-H46),"")-1)>0.1,"Рост",IF((IFERROR((G15)/(G40-G48-G46),"")/IFERROR((H15)/(H40-H48-H46),"")-1)<-0.1,"Снижение","На прежнем уровне")),"Нет данных") -> Нет данных
A74: Динамика рентабельности продаж | E74: =IFERROR(IF((IFERROR(((E56/E53)*100),"")/IFERROR(((F56/F53)*100),"")-1)>0.1,"Рост",IF((IFERROR(((E56/E53)*100),"")/IFERROR((F56/F53)*100,"")-1)<-0.1,"Снижение","На прежнем уровне")),"Нет данных") -> Снижение | F74: =IFERROR(IF((IFERROR(((F56/F53)*100),"")/IFERROR(((G56/G53)*100),"")-1)>0.1,"Рост",IF((IFERROR(((F56/F53)*100),"")/IFERROR((G56/G53)*100,"")-1)<-0.1,"Снижение","На прежнем уровне")),"Нет данных") -> Снижение | G74: =IFERROR(IF((IFERROR(((G56/G53)*100),"")/IFERROR(((H56/H53)*100),"")-1)>0.1,"Рост",IF((IFERROR(((G56/G53)*100),"")/IFERROR((H56/H53)*100,"")-1)<-0.1,"Снижение","На прежнем уровне")),"Нет данных") -> Нет данных
